Workbook
Name CF: Funções!$L$12:$L$1000
Name Data: Contagem!$Z$11
Name Projeto: Contagem!$F$9
Name Responsável: Contagem!$F$11
Name Revisão: Contagem!$Z$12
Name Revisor: Contagem!$F$12
Name UFPB: Contagem!$AA$16
Name VAF: #REF!
Name VAFA: #REF!
Name VAFB: #REF!

Sheet Contagem
D1: Sudoeste Informática
D2: Sudoeste Informática e Consultoria
D3: Missão: "Ser a mais completa solução na área de Tecnologia da Informação, de forma a contribuir para a modernização da Gestão pública."
A4: Identificação da Contagem
A7: Empresa | F7: Sudoeste Informática | R7: R$/PF | T7: 700 | W7: Custo | Y7: =Y8*T7
A8: Aplicação | F8: Viabiliza — Sistema de Licenciamento Eletrônico da SEDUR | W8: PF | Y8: =SUM(AA15:AA18)
A9: Projeto | F9: Recontagem IFPUG - Projeto de Desenvolvimento (aplicação completa)
A10: DV Número | F10: DV-SILE-003 | K10: Versão | N10: 4.0
A11: Responsável | F11: Equipe de Análise — Sudoeste Informática | W11: Criação | Z11: 46311
A12: Revisor | W12: Revisão
A14: Tipo de contagem | C14: Estimativa | O14: Sumário | Q14: PF não Ajustado | W14: Deflator | AA14: PF Local
C15: Projeto de Desenvolvimento | L15: x | Q15: ADD | S15: =Sumário!E57 | W15: 1 | AA15: =S15*W15
C16: Projeto de Melhoria | Q16: CHG | S16: =Sumário!E58 | W16: 0.8 | AA16: =S16*W16
C17: Aplicação ( Baseline ) | Q17: DEL | S17: =Sumário!E59 | W17: 0.3 | AA17: =S17*W17
Q18: TST | S18: =Sumário!E60 | W18: 0.5 | AA18: =S18*W18
K20: Propósito da Contagem
A21: Recontagem integral do tamanho funcional do Viabiliza em 16/10/2026, como projeto de desenvolvimento, seguindo o Manual de Práticas de Contagem IFPUG CPM 4.3.1. A contagem foi refeita a partir do código-fonte atual (rotas, telas, serviços, models, migrations, comandos agendados e testes), sem presumir que as funções da contagem de 01/10/2026 (versão 3.3, 1.618 PF não ajustados) continuassem válidas: cada função anterior foi conferida no código e classificada como mantida, alterada ou removida, e as funções novas foram identificadas. A coluna Observações traz, para cada função, a prova no código, a justificativa de processo elementar ou de arquivo lógico, a classificação, a lista dos DER que formam o TD e dos arquivos que formam o AR/TR, e a situação em relação à contagem anterior. Resultado: 1713 PF não ajustados. As funções removidas, as correções e as premissas estão na memória de cálculo entregue com esta planilha.
K44: Escopo da Contagem
A45: Fronteira: aplicação Viabiliza (Sistema de Licenciamento Eletrônico da SEDUR) completa, no estado do código em 16/10/2026. Inclui o console de gestão da SEDUR, o Portal do Cidadão (conta, empresas, procurações, solicitação, renovação e acompanhamento), a consulta prévia de viabilidade, a consulta pública de protocolo, a verificação pública de documentos, o recebimento de declarações do REGIN/JUCEB, as rotinas automáticas de prazos e controle, a importação mensal do benchmark REDESIM e os dados externos efetivamente lidos (GeoServer da SEDUR, contatos cadastrais da SEDUR, cadastro imobiliário da SEFAZ, lotes do SEMAP, diretório da SEDUR e geocodificação). Fora da contagem: login gov.br (implementado, mas desligado e sem credencial), envio à SEFAZ (bloqueado, HU-110), migração do legado, dados de código (CPM Parte 1 §5.4.2 d e Parte 3 Cap. 1: tipo de serviço, zona urbanística e via) e as transações que só os mantêm, funções técnicas sem efeito para o usuário (teste de conexão, ping, metadados, documentação OpenAPI, retenção de dados, reprocessamento técnico, comandos de suporte) e efeitos automáticos de outra função (envio do parecer à JUCEB, notificações e e-mails). Critério de conferência: linhas F1, F2 etc. são grupos funcionais e não pontuam. Cada função contável tem tipo, TD, AR/TR e Observações com a prova e a lista de DER e de arquivos. Todo arquivo citado no AR é ALI ou AIE desta contagem; subgrupos aparecem pelo arquivo pai. Registros automáticos em arquivos de log (trilha de auditoria, registro de acesso, chamada de integração, envio de e-mail, notificação e comunicação) contam como arquivo referenciado quando gravados no mesmo processamento (CPM Parte 1 §5.5.3 e §5.5.4).

Sheet Funções
B4: Planilha de contagem de ponto de função
B7: =Contagem!A8&" : "&Contagem!F8 | H7: =Contagem!A9&" : "&Contagem!F9
B8: DV Número: | F8: Versão: | G8: =Contagem!N10 | H8: Tipo da Contagem: | K8: =IF(ISBLANK(Contagem!L14),IF(ISBLANK(Contagem!L15),IF(ISBLANK(Contagem!L16),IF(ISBLANK(Contagem!L17),"","Aplicação (Baseline)"),"Melhoria"),"Desenvolvimento"),"Estimativa")
B9: =Contagem!A11&" : "&Contagem!F11 | H9: =Contagem!A12&" : "&Contagem!F12
B10: =Contagem!A7&" : "&Contagem!F7 | O10: ="PF = "&VALUE(Contagem!Y8)
B11: Id. Func | C11: Função Transacional (EE, CE, SE) ou Função de Dados (ALI, AIE) | H11: Tipo | I11: (I/A/E/T) | J11: TD | K11: AR/TR | L11: ctl | M11: C | N11: Complex. | O11: PF | P11: PF Local | Q11: Observações
A12: =IF(D12="",IF(C12="","",1),"") | B12: =CONCATENATE("F",A12) | C12: CNAEs | L12: =CONCATENATE(H12,M12) | M12: =IF(OR(ISBLANK(J12),ISBLANK(K12)),IF(OR(H12="ALI",H12="AIE"),"L",IF(ISBLANK(H12),"","A")),IF(H12="EE",IF(K12>=3,IF(J12>=5,"H","A"),IF(K12>=2,IF(J12>=16,"H",IF(J12<=4,"L","A")),IF(J12<=15,"L","A"))),IF(OR(H12="SE",H12="CE"),IF(K12>=4,IF(J12>=6,"H","A"),IF(K12>=2,IF(J12>=20,"H",IF(J12<=5,"L","A")),IF(J12<=19,"L","A"))),IF(OR(H12="ALI",H12="AIE"),IF(K12>=6,IF(J12>=20,"H","A"),IF(K12>=2,IF(J12>=51,"H",IF(J12<=19,"L","A")),IF(J12<=50,"L","A"))))))) | N12: =IF(M12="L","Baixa",IF(M12="A","Média",IF(M12="","","Alta"))) | O12: =IF(ISBLANK(H12),"",IF(H12="ALI",IF(M12="L",7,IF(M12="A",10,15)),IF(H12="AIE",IF(M12="L",5,IF(M12="A",7,10)),IF(H12="SE",IF(M12="L",4,IF(M12="A",5,7)),IF(OR(H12="EE",H12="CE"),IF(M12="L",3,IF(M12="A",4,6))))))) | P12: =IF(I12="I",O12*Contagem!$W$15,IF(I12="E",O12*Contagem!$W$17,IF(I12="A",O12*Contagem!$W$16,IF(I12="T",O12*Contagem!$W$18,""))))
A13: =IF(H13="",IF(C13="",A12,A12+1),A12) | B13: =IF(A13=A12,"",CONCATENATE("F",A13)) | C13: Dados - CNAE | H13: ALI | I13: I | J13: 15 | K13: 1 | L13: =CONCATENATE(H13,M13) | M13: =IF(OR(ISBLANK(J13),ISBLANK(K13)),IF(OR(H13="ALI",H13="AIE"),"L",IF(ISBLANK(H13),"","A")),IF(H13="EE",IF(K13>=3,IF(J13>=5,"H","A"),IF(K13>=2,IF(J13>=16,"H",IF(J13<=4,"L","A")),IF(J13<=15,"L","A"))),IF(OR(H13="SE",H13="CE"),IF(K13>=4,IF(J13>=6,"H","A"),IF(K13>=2,IF(J13>=20,"H",IF(J13<=5,"L","A")),IF(J13<=19,"L","A"))),IF(OR(H13="ALI",H13="AIE"),IF(K13>=6,IF(J13>=20,"H","A"),IF(K13>=2,IF(J13>=51,"H",IF(J13<=19,"L","A")),IF(J13<=50,"L","A"))))))) | N13: =IF(M13="L","Baixa",IF(M13="A","Média",IF(M13="","","Alta"))) | O13: =IF(ISBLANK(H13),"",IF(H13="ALI",IF(M13="L",7,IF(M13="A",10,15)),IF(H13="AIE",IF(M13="L",5,IF(M13="A",7,10)),IF(H13="SE",IF(M13="L",4,IF(M13="A",5,7)),IF(OR(H13="EE",H13="CE"),IF(M13="L",3,IF(M13="A",4,6))))))) | P13: =IF(I13="I",O13*Contagem!$W$15,IF(I13="E",O13*Contagem!$W$17,IF(I13="A",O13*Contagem!$W$16,IF(I13="T",O13*Contagem!$W$18,"")))) | Q13: Prova: Model app/Models/Cnae.php; migrations database/migrations/2026_06_10_144536_create_cnaes_table.php e 2026_08_13_120000_add_regras_risco_to_cnaes_table.php. Mantido pelos processos CNAEs - incluir, alterar, alterar situação e excluir (CnaeController), auditados via HasAuditoria. Teste: tests/Feature/Cnae/CnaeCrudTest.php::test_mudancas_sao_auditadas_com_attribute_changes. Arquivo lógico: Grupo lógico reconhecido pelo gestor: catálogo de atividades econômicas (CNAE IBGE) com hierarquia e regras de RT e multiplicador usadas na viabilidade; mantido por tela própria. TD=15 (código, denominação, código da seção, descrição da seção, código da divisão, descrição da divisão, código do grupo, descrição do grupo, código da classe, descrição da classe, situação, exige RT, exige RT se alto risco, exige fator multiplicador, exige detalhamento do multiplicador). TR=1 (CNAE). Recontagem 16/10/2026: mantida (linha 168 da contagem de 01/10/2026).
A14: =IF(H14="",IF(C14="",A13,A13+1),A13) | B14: =IF(A14=A13,"",CONCATENATE("F",A14)) | C14: Dados - Classificação de risco municipal | H14: ALI | I14: I | J14: 5 | K14: 1 | L14: =CONCATENATE(H14,M14) | M14: =IF(OR(ISBLANK(J14),ISBLANK(K14)),IF(OR(H14="ALI",H14="AIE"),"L",IF(ISBLANK(H14),"","A")),IF(H14="EE",IF(K14>=3,IF(J14>=5,"H","A"),IF(K14>=2,IF(J14>=16,"H",IF(J14<=4,"L","A")),IF(J14<=15,"L","A"))),IF(OR(H14="SE",H14="CE"),IF(K14>=4,IF(J14>=6,"H","A"),IF(K14>=2,IF(J14>=20,"H",IF(J14<=5,"L","A")),IF(J14<=19,"L","A"))),IF(OR(H14="ALI",H14="AIE"),IF(K14>=6,IF(J14>=20,"H","A"),IF(K14>=2,IF(J14>=51,"H",IF(J14<=19,"L","A")),IF(J14<=50,"L","A"))))))) | N14: =IF(M14="L","Baixa",IF(M14="A","Média",IF(M14="","","Alta"))) | O14: =IF(ISBLANK(H14),"",IF(H14="ALI",IF(M14="L",7,IF(M14="A",10,15)),IF(H14="AIE",IF(M14="L",5,IF(M14="A",7,10)),IF(H14="SE",IF(M14="L",4,IF(M14="A",5,7)),IF(OR(H14="EE",H14="CE"),IF(M14="L",3,IF(M14="A",4,6))))))) | P14: =IF(I14="I",O14*Contagem!$W$15,IF(I14="E",O14*Contagem!$W$17,IF(I14="A",O14*Contagem!$W$16,IF(I14="T",O14*Contagem!$W$18,"")))) | Q14: Prova: Model RiskClassification (HasAuditoria); migration 2026_06_14_014716_create_risk_classifications_table (chave versão de regras + CNAE). Mantida pelo gestor no cadastro de CNAEs: CnaeController@store e update gravam o grau de risco municipal da versão vigente (updateOrCreate), transações contadas na área de CNAEs (CNAEs - incluir e CNAEs - alterar, que já citam este arquivo como FTR). A carga oficial RiscoMunicipalImportService só roda pelo RiscoMunicipalSeeder (carga técnica). O comando risco:classificar (RiscoClassificarCommand) só lê e imprime a classificação no console para conferência técnica: não mantém o arquivo nem é função do usuário. Lida pelo motor de risco (RiscoClassificationService) e pelas consultas de viabilidade. Arquivo lógico: tabela legal versionada (Decreto 32.636/2020) reconhecida pelo gestor; o grau de risco decide o fluxo e não é substituível por descrição, logo não é dado de código. Teste: tests/Feature/Cnae/CnaeCrudTest.php::test_criar_cnae_grava_classificacao_de_risco_municipal_direto. TD=5 (CNAE, risco municipal, condicionantes, observação, versão de regras). TR=1 (Classificação de risco municipal). Recontagem 16/10/2026: mantida (linha 497 da contagem de 01/10/2026).
A15: =IF(H15="",IF(C15="",A14,A14+1),A14) | B15: =IF(A15=A14,"",CONCATENATE("F",A15)) | C15: CNAEs - consultar | H15: CE | I15: I | J15: 6 | K15: 1 | L15: =CONCATENATE(H15,M15) | M15: =IF(OR(ISBLANK(J15),ISBLANK(K15)),IF(OR(H15="ALI",H15="AIE"),"L",IF(ISBLANK(H15),"","A")),IF(H15="EE",IF(K15>=3,IF(J15>=5,"H","A"),IF(K15>=2,IF(J15>=16,"H",IF(J15<=4,"L","A")),IF(J15<=15,"L","A"))),IF(OR(H15="SE",H15="CE"),IF(K15>=4,IF(J15>=6,"H","A"),IF(K15>=2,IF(J15>=20,"H",IF(J15<=5,"L","A")),IF(J15<=19,"L","A"))),IF(OR(H15="ALI",H15="AIE"),IF(K15>=6,IF(J15>=20,"H","A"),IF(K15>=2,IF(J15>=51,"H",IF(J15<=19,"L","A")),IF(J15<=50,"L","A"))))))) | N15: =IF(M15="L","Baixa",IF(M15="A","Média",IF(M15="","","Alta"))) | O15: =IF(ISBLANK(H15),"",IF(H15="ALI",IF(M15="L",7,IF(M15="A",10,15)),IF(H15="AIE",IF(M15="L",5,IF(M15="A",7,10)),IF(H15="SE",IF(M15="L",4,IF(M15="A",5,7)),IF(OR(H15="EE",H15="CE"),IF(M15="L",3,IF(M15="A",4,6))))))) | P15: =IF(I15="I",O15*Contagem!$W$15,IF(I15="E",O15*Contagem!$W$17,IF(I15="A",O15*Contagem!$W$16,IF(I15="T",O15*Contagem!$W$18,"")))) | Q15: Prova: Rota GET /gestao/cnaes (permissão consultar-cnaes). Tela: gestao/cnaes/index. O gestor pesquisa por código (prefixo de dígitos) ou denominação, filtra por situação e ordena. Lê CNAE; não grava. A exportação (?formato=csv/xlsx/pdf, ReportExporter) não tem botão nesta tela (a página não usa ExportMenu; só é alcançável digitando a URL) e não é contada como função; a consulta da tela não grava Trilha de auditoria (o log só ocorre no ramo ?formato=), por isso continua sem FTR de registro. Teste: tests/Feature/Cnae/CnaeCrudTest.php::test_busca_filtra_por_codigo_ou_denominacao. Processo elementar independente: menor unidade com significado para o gestor; completa por si (informa filtro e recebe a lista); deixa o negócio consistente (nada é gravado); lógica única (busca por prefixo de dígitos ou denominação). Classificação: recuperação sem cálculo nem dado derivado, CE (§5.5.3). TD=6 (código, denominação, situação, classe, busca por código ou denominação, ação pesquisar). O filtro de situação é o mesmo campo da coluna situação e conta uma vez (DER único); ordenação e paginação não contam. AR=1 (CNAE). Recontagem 16/10/2026: alterada (linha 169 da contagem de 01/10/2026: "CNAEs - consultar", CE Baixa 3 PF, TD 7, AR 1). Motivo: TD 7→6: situação e filtro de situação eram contados como dois DER; são o mesmo campo. PF inalterado (CE Baixa).
A16: =IF(H16="",IF(C16="",A15,A15+1),A15) | B16: =IF(A16=A15,"",CONCATENATE("F",A16)) | C16: CNAEs - incluir | H16: EE | I16: I | J16: 18 | K16: 3 | L16: =CONCATENATE(H16,M16) | M16: =IF(OR(ISBLANK(J16),ISBLANK(K16)),IF(OR(H16="ALI",H16="AIE"),"L",IF(ISBLANK(H16),"","A")),IF(H16="EE",IF(K16>=3,IF(J16>=5,"H","A"),IF(K16>=2,IF(J16>=16,"H",IF(J16<=4,"L","A")),IF(J16<=15,"L","A"))),IF(OR(H16="SE",H16="CE"),IF(K16>=4,IF(J16>=6,"H","A"),IF(K16>=2,IF(J16>=20,"H",IF(J16<=5,"L","A")),IF(J16<=19,"L","A"))),IF(OR(H16="ALI",H16="AIE"),IF(K16>=6,IF(J16>=20,"H","A"),IF(K16>=2,IF(J16>=51,"H",IF(J16<=19,"L","A")),IF(J16<=50,"L","A"))))))) | N16: =IF(M16="L","Baixa",IF(M16="A","Média",IF(M16="","","Alta"))) | O16: =IF(ISBLANK(H16),"",IF(H16="ALI",IF(M16="L",7,IF(M16="A",10,15)),IF(H16="AIE",IF(M16="L",5,IF(M16="A",7,10)),IF(H16="SE",IF(M16="L",4,IF(M16="A",5,7)),IF(OR(H16="EE",H16="CE"),IF(M16="L",3,IF(M16="A",4,6))))))) | P16: =IF(I16="I",O16*Contagem!$W$15,IF(I16="E",O16*Contagem!$W$17,IF(I16="A",O16*Contagem!$W$16,IF(I16="T",O16*Contagem!$W$18,"")))) | Q16: Prova: Rota POST /gestao/cnaes (manter-cnaes). Tela: gestao/cnaes/criar. O gestor cadastra o CNAE e o grau de risco municipal. Lê versão vigente (subgrupo do arquivo versionado) vigente de risco municipal; grava CNAE, Classificação de risco municipal e Trilha de auditoria. Resultado: atividade disponível para viabilidade. Teste: tests/Feature/Cnae/CnaeCrudTest.php::test_criar_cnae_grava_classificacao_de_risco_municipal_direto. Processo elementar independente: menor unidade com significado para o gestor; completa por si (preenche a ficha e recebe confirmação); deixa o negócio consistente (CNAE e risco gravados na mesma transação); lógica única (exige versão vigente de risco municipal). TD=18 (código, denominação, código da seção, descrição da seção, código da divisão, descrição da divisão, código do grupo, descrição do grupo, código da classe, descrição da classe, situação, exige RT, exige RT se alto risco, exige fator multiplicador, exige detalhamento do multiplicador, grau de risco municipal, mensagem, ação salvar). AR=3 (CNAE, Classificação de risco municipal, Trilha de auditoria). Registros automáticos contados como FTR (premissa P4): Trilha de auditoria. Recontagem (catálogo): Versão de regras deixou de ser arquivo lógico próprio e é subgrupo de arquivo já listado no AR; AR ajustado. Recontagem 16/10/2026: alterada (linha 170 da contagem de 01/10/2026: "CNAEs - incluir", EE Alta 6 PF, TD 18, AR 4). Motivo: Catálogo: retirado Versão de regras (subgrupo de outro arquivo).
A17: =IF(H17="",IF(C17="",A16,A16+1),A16) | B17: =IF(A17=A16,"",CONCATENATE("F",A17)) | C17: CNAEs - alterar | H17: EE | I17: I | J17: 18 | K17: 4 | L17: =CONCATENATE(H17,M17) | M17: =IF(OR(ISBLANK(J17),ISBLANK(K17)),IF(OR(H17="ALI",H17="AIE"),"L",IF(ISBLANK(H17),"","A")),IF(H17="EE",IF(K17>=3,IF(J17>=5,"H","A"),IF(K17>=2,IF(J17>=16,"H",IF(J17<=4,"L","A")),IF(J17<=15,"L","A"))),IF(OR(H17="SE",H17="CE"),IF(K17>=4,IF(J17>=6,"H","A"),IF(K17>=2,IF(J17>=20,"H",IF(J17<=5,"L","A")),IF(J17<=19,"L","A"))),IF(OR(H17="ALI",H17="AIE"),IF(K17>=6,IF(J17>=20,"H","A"),IF(K17>=2,IF(J17>=51,"H",IF(J17<=19,"L","A")),IF(J17<=50,"L","A"))))))) | N17: =IF(M17="L","Baixa",IF(M17="A","Média",IF(M17="","","Alta"))) | O17: =IF(ISBLANK(H17),"",IF(H17="ALI",IF(M17="L",7,IF(M17="A",10,15)),IF(H17="AIE",IF(M17="L",5,IF(M17="A",7,10)),IF(H17="SE",IF(M17="L",4,IF(M17="A",5,7)),IF(OR(H17="EE",H17="CE"),IF(M17="L",3,IF(M17="A",4,6))))))) | P17: =IF(I17="I",O17*Contagem!$W$15,IF(I17="E",O17*Contagem!$W$17,IF(I17="A",O17*Contagem!$W$16,IF(I17="T",O17*Contagem!$W$18,"")))) | Q17: Prova: Rota PUT /gestao/cnaes/{cnae} (manter-cnaes). Tela: gestao/cnaes/editar. O gestor altera a ficha do CNAE. Lê versão vigente (subgrupo do arquivo versionado); grava CNAE e Classificação de risco municipal; ao mudar o código, atualiza o código em Atividade permitida em escritório virtual e nas tabelas de apoio carregadas por seeder, que não são arquivo lógico e não entram no AR; grava Trilha. Teste: tests/Feature/Cnae/CnaeCrudTest.php::test_edicao_atualiza_codigo_hierarquia_e_dados. Processo elementar independente: menor unidade com significado para o gestor; completa por si (edita e recebe confirmação); deixa o negócio consistente (regras acompanham a troca de código); lógica única (realocação do código nas tabelas de regras). TD=18 (código, denominação, código da seção, descrição da seção, código da divisão, descrição da divisão, código do grupo, descrição do grupo, código da classe, descrição da classe, situação, exige RT, exige RT se alto risco, exige fator multiplicador, exige detalhamento do multiplicador, grau de risco municipal, mensagem, ação salvar). AR=4 (CNAE, Classificação de risco municipal, Atividade permitida em escritório virtual, Trilha de auditoria). Registros automáticos contados como FTR (premissa P4): Trilha de auditoria. Recontagem (catálogo): Versão de regras deixou de ser arquivo lógico próprio e é subgrupo de arquivo já listado no AR; AR ajustado. Recontagem 16/10/2026: alterada (linha 171 da contagem de 01/10/2026: "CNAEs - alterar", EE Alta 6 PF, TD 18, AR 5). Motivo: Catálogo: retirado Versão de regras (subgrupo de outro arquivo).
A18: =IF(H18="",IF(C18="",A17,A17+1),A17) | B18: =IF(A18=A17,"",CONCATENATE("F",A18)) | C18: CNAEs - alterar situação | H18: EE | I18: I | J18: 3 | K18: 2 | L18: =CONCATENATE(H18,M18) | M18: =IF(OR(ISBLANK(J18),ISBLANK(K18)),IF(OR(H18="ALI",H18="AIE"),"L",IF(ISBLANK(H18),"","A")),IF(H18="EE",IF(K18>=3,IF(J18>=5,"H","A"),IF(K18>=2,IF(J18>=16,"H",IF(J18<=4,"L","A")),IF(J18<=15,"L","A"))),IF(OR(H18="SE",H18="CE"),IF(K18>=4,IF(J18>=6,"H","A"),IF(K18>=2,IF(J18>=20,"H",IF(J18<=5,"L","A")),IF(J18<=19,"L","A"))),IF(OR(H18="ALI",H18="AIE"),IF(K18>=6,IF(J18>=20,"H","A"),IF(K18>=2,IF(J18>=51,"H",IF(J18<=19,"L","A")),IF(J18<=50,"L","A"))))))) | N18: =IF(M18="L","Baixa",IF(M18="A","Média",IF(M18="","","Alta"))) | O18: =IF(ISBLANK(H18),"",IF(H18="ALI",IF(M18="L",7,IF(M18="A",10,15)),IF(H18="AIE",IF(M18="L",5,IF(M18="A",7,10)),IF(H18="SE",IF(M18="L",4,IF(M18="A",5,7)),IF(OR(H18="EE",H18="CE"),IF(M18="L",3,IF(M18="A",4,6))))))) | P18: =IF(I18="I",O18*Contagem!$W$15,IF(I18="E",O18*Contagem!$W$17,IF(I18="A",O18*Contagem!$W$16,IF(I18="T",O18*Contagem!$W$18,"")))) | Q18: Prova: Rota PUT /gestao/cnaes/{cnae}/situacao (manter-cnaes). Tela: gestao/cnaes/index. O gestor ativa ou desativa o CNAE na lista. Grava a situação do CNAE e Trilha de auditoria. Resultado: atividade deixa ou volta a ser aceita. Teste: tests/Feature/Cnae/CnaeCrudTest.php::test_toggle_de_situacao_funciona_com_payload_minimo. Processo elementar independente: menor unidade com significado para o gestor; completa por si (um clique e confirmação); deixa o negócio consistente (só a situação muda); lógica única (payload mínimo sem regras de risco, distinta do alterar). TD=3 (situação, mensagem, ação ativar/desativar). AR=2 (CNAE, Trilha de auditoria). Registros automáticos contados como FTR (premissa P4): Trilha de auditoria. Recontagem 16/10/2026: mantida (linha 172 da contagem de 01/10/2026).
A19: =IF(H19="",IF(C19="",A18,A18+1),A18) | B19: =IF(A19=A18,"",CONCATENATE("F",A19)) | C19: CNAEs - excluir | H19: EE | I19: I | J19: 3 | K19: 3 | L19: =CONCATENATE(H19,M19) | M19: =IF(OR(ISBLANK(J19),ISBLANK(K19)),IF(OR(H19="ALI",H19="AIE"),"L",IF(ISBLANK(H19),"","A")),IF(H19="EE",IF(K19>=3,IF(J19>=5,"H","A"),IF(K19>=2,IF(J19>=16,"H",IF(J19<=4,"L","A")),IF(J19<=15,"L","A"))),IF(OR(H19="SE",H19="CE"),IF(K19>=4,IF(J19>=6,"H","A"),IF(K19>=2,IF(J19>=20,"H",IF(J19<=5,"L","A")),IF(J19<=19,"L","A"))),IF(OR(H19="ALI",H19="AIE"),IF(K19>=6,IF(J19>=20,"H","A"),IF(K19>=2,IF(J19>=51,"H",IF(J19<=19,"L","A")),IF(J19<=50,"L","A"))))))) | N19: =IF(M19="L","Baixa",IF(M19="A","Média",IF(M19="","","Alta"))) | O19: =IF(ISBLANK(H19),"",IF(H19="ALI",IF(M19="L",7,IF(M19="A",10,15)),IF(H19="AIE",IF(M19="L",5,IF(M19="A",7,10)),IF(H19="SE",IF(M19="L",4,IF(M19="A",5,7)),IF(OR(H19="EE",H19="CE"),IF(M19="L",3,IF(M19="A",4,6))))))) | P19: =IF(I19="I",O19*Contagem!$W$15,IF(I19="E",O19*Contagem!$W$17,IF(I19="A",O19*Contagem!$W$16,IF(I19="T",O19*Contagem!$W$18,"")))) | Q19: Prova: Rota DELETE /gestao/cnaes/{cnae} (manter-cnaes). Tela: gestao/cnaes/index. O gestor exclui o CNAE. Lê Empresa (vínculo company_cnae) para bloquear; exclui CNAE e grava Trilha de auditoria. Resultado: CNAE sem uso removido. Teste: tests/Feature/Cnae/CnaeCrudTest.php::test_exclusao_de_cnae_vinculado_a_empresa_e_bloqueada. Processo elementar independente: menor unidade com significado para o gestor; completa por si (confirma e recebe resultado); deixa o negócio consistente (não exclui CNAE em uso); lógica única (bloqueio por vínculo com empresa). TD=3 (CNAE selecionado, mensagem, ação excluir). AR=3 (CNAE, Empresa, Trilha de auditoria). Registros automáticos contados como FTR (premissa P4): Trilha de auditoria. Recontagem 16/10/2026: mantida (linha 173 da contagem de 01/10/2026).
A20: =IF(H20="",IF(C20="",A19,A19+1),A19) | B20: =IF(A20=A19,"",CONCATENATE("F",A20)) | L20: =CONCATENATE(H20,M20) | M20: =IF(OR(ISBLANK(J20),ISBLANK(K20)),IF(OR(H20="ALI",H20="AIE"),"L",IF(ISBLANK(H20),"","A")),IF(H20="EE",IF(K20>=3,IF(J20>=5,"H","A"),IF(K20>=2,IF(J20>=16,"H",IF(J20<=4,"L","A")),IF(J20<=15,"L","A"))),IF(OR(H20="SE",H20="CE"),IF(K20>=4,IF(J20>=6,"H","A"),IF(K20>=2,IF(J20>=20,"H",IF(J20<=5,"L","A")),IF(J20<=19,"L","A"))),IF(OR(H20="ALI",H20="AIE"),IF(K20>=6,IF(J20>=20,"H","A"),IF(K20>=2,IF(J20>=51,"H",IF(J20<=19,"L","A")),IF(J20<=50,"L","A"))))))) | N20: =IF(M20="L","Baixa",IF(M20="A","Média",IF(M20="","","Alta"))) | O20: =IF(ISBLANK(H20),"",IF(H20="ALI",IF(M20="L",7,IF(M20="A",10,15)),IF(H20="AIE",IF(M20="L",5,IF(M20="A",7,10)),IF(H20="SE",IF(M20="L",4,IF(M20="A",5,7)),IF(OR(H20="EE",H20="CE"),IF(M20="L",3,IF(M20="A",4,6))))))) | P20: =IF(I20="I",O20*Contagem!$W$15,IF(I20="E",O20*Contagem!$W$17,IF(I20="A",O20*Contagem!$W$16,IF(I20="T",O20*Contagem!$W$18,""))))
A21: =IF(H21="",IF(C21="",A20,A20+1),A20) | B21: =IF(A21=A20,"",CONCATENATE("F",A21)) | C21: Requisitos documentais | L21: =CONCATENATE(H21,M21) | M21: =IF(OR(ISBLANK(J21),ISBLANK(K21)),IF(OR(H21="ALI",H21="AIE"),"L",IF(ISBLANK(H21),"","A")),IF(H21="EE",IF(K21>=3,IF(J21>=5,"H","A"),IF(K21>=2,IF(J21>=16,"H",IF(J21<=4,"L","A")),IF(J21<=15,"L","A"))),IF(OR(H21="SE",H21="CE"),IF(K21>=4,IF(J21>=6,"H","A"),IF(K21>=2,IF(J21>=20,"H",IF(J21<=5,"L","A")),IF(J21<=19,"L","A"))),IF(OR(H21="ALI",H21="AIE"),IF(K21>=6,IF(J21>=20,"H","A"),IF(K21>=2,IF(J21>=51,"H",IF(J21<=19,"L","A")),IF(J21<=50,"L","A"))))))) | N21: =IF(M21="L","Baixa",IF(M21="A","Média",IF(M21="","","Alta"))) | O21: =IF(ISBLANK(H21),"",IF(H21="ALI",IF(M21="L",7,IF(M21="A",10,15)),IF(H21="AIE",IF(M21="L",5,IF(M21="A",7,10)),IF(H21="SE",IF(M21="L",4,IF(M21="A",5,7)),IF(OR(H21="EE",H21="CE"),IF(M21="L",3,IF(M21="A",4,6))))))) | P21: =IF(I21="I",O21*Contagem!$W$15,IF(I21="E",O21*Contagem!$W$17,IF(I21="A",O21*Contagem!$W$16,IF(I21="T",O21*Contagem!$W$18,""))))
A22: =IF(H22="",IF(C22="",A21,A21+1),A21) | B22: =IF(A22=A21,"",CONCATENATE("F",A22)) | C22: Dados - Requisito documental | H22: ALI | I22: I | J22: 7 | K22: 1 | L22: =CONCATENATE(H22,M22) | M22: =IF(OR(ISBLANK(J22),ISBLANK(K22)),IF(OR(H22="ALI",H22="AIE"),"L",IF(ISBLANK(H22),"","A")),IF(H22="EE",IF(K22>=3,IF(J22>=5,"H","A"),IF(K22>=2,IF(J22>=16,"H",IF(J22<=4,"L","A")),IF(J22<=15,"L","A"))),IF(OR(H22="SE",H22="CE"),IF(K22>=4,IF(J22>=6,"H","A"),IF(K22>=2,IF(J22>=20,"H",IF(J22<=5,"L","A")),IF(J22<=19,"L","A"))),IF(OR(H22="ALI",H22="AIE"),IF(K22>=6,IF(J22>=20,"H","A"),IF(K22>=2,IF(J22>=51,"H",IF(J22<=19,"L","A")),IF(J22<=50,"L","A"))))))) | N22: =IF(M22="L","Baixa",IF(M22="A","Média",IF(M22="","","Alta"))) | O22: =IF(ISBLANK(H22),"",IF(H22="ALI",IF(M22="L",7,IF(M22="A",10,15)),IF(H22="AIE",IF(M22="L",5,IF(M22="A",7,10)),IF(H22="SE",IF(M22="L",4,IF(M22="A",5,7)),IF(OR(H22="EE",H22="CE"),IF(M22="L",3,IF(M22="A",4,6))))))) | P22: =IF(I22="I",O22*Contagem!$W$15,IF(I22="E",O22*Contagem!$W$17,IF(I22="A",O22*Contagem!$W$16,IF(I22="T",O22*Contagem!$W$18,"")))) | Q22: Prova: Model app/Models/DocumentRequirement.php; migrations database/migrations/2026_06_14_104827_create_document_requirements_table.php e 2026_06_14_104828_create_cnae_document_requirement_table.php (vínculo N:N com CNAE, sem atributos próprios). Mantido por DocumentRequirementController (store, update, toggle, syncCnaes). Teste: tests/Feature/Solicitacao/DocumentRequirementCrudTest.php::test_cria_requisito_e_audita. Arquivo lógico: Grupo lógico reconhecido pelo gestor: o catálogo de documentos exigidos na solicitação e a obrigatoriedade por CNAE, mantido por tela e consumido pela validação documental. TD=7 (código, nome, descrição, obrigatório, situação (ativo), instruções de validação, CNAEs vinculados). TR=1 (Requisito documental). Recontagem 16/10/2026: mantida (linha 128 da contagem de 01/10/2026).
A23: =IF(H23="",IF(C23="",A22,A22+1),A22) | B23: =IF(A23=A22,"",CONCATENATE("F",A23)) | C23: Requisitos documentais - consultar | H23: CE | I23: I | J23: 10 | K23: 2 | L23: =CONCATENATE(H23,M23) | M23: =IF(OR(ISBLANK(J23),ISBLANK(K23)),IF(OR(H23="ALI",H23="AIE"),"L",IF(ISBLANK(H23),"","A")),IF(H23="EE",IF(K23>=3,IF(J23>=5,"H","A"),IF(K23>=2,IF(J23>=16,"H",IF(J23<=4,"L","A")),IF(J23<=15,"L","A"))),IF(OR(H23="SE",H23="CE"),IF(K23>=4,IF(J23>=6,"H","A"),IF(K23>=2,IF(J23>=20,"H",IF(J23<=5,"L","A")),IF(J23<=19,"L","A"))),IF(OR(H23="ALI",H23="AIE"),IF(K23>=6,IF(J23>=20,"H","A"),IF(K23>=2,IF(J23>=51,"H",IF(J23<=19,"L","A")),IF(J23<=50,"L","A"))))))) | N23: =IF(M23="L","Baixa",IF(M23="A","Média",IF(M23="","","Alta"))) | O23: =IF(ISBLANK(H23),"",IF(H23="ALI",IF(M23="L",7,IF(M23="A",10,15)),IF(H23="AIE",IF(M23="L",5,IF(M23="A",7,10)),IF(H23="SE",IF(M23="L",4,IF(M23="A",5,7)),IF(OR(H23="EE",H23="CE"),IF(M23="L",3,IF(M23="A",4,6))))))) | P23: =IF(I23="I",O23*Contagem!$W$15,IF(I23="E",O23*Contagem!$W$17,IF(I23="A",O23*Contagem!$W$16,IF(I23="T",O23*Contagem!$W$18,"")))) | Q23: Prova: Rota GET /gestao/requisitos-documentais (permissão manter-requisitos-documentais). Tela: gestao/requisitos-documentais/index. O gestor busca e filtra por situação. Lê Requisito documental e CNAE; não grava. Resultado: lista paginada dos requisitos com CNAEs vinculados. Teste: tests/Feature/Solicitacao/DocumentRequirementCrudTest.php::test_administrador_lista_requisitos. Processo elementar independente: menor unidade com significado para o gestor; completa por si (filtro até a lista exibida); deixa o negócio consistente (nada muda); lógica única (recuperação de requisitos com CNAEs vinculados, sem cálculo). TD=10 (código, nome, descrição, obrigatório, situação, instruções de validação, código do CNAE vinculado, descrição do CNAE vinculado, busca por código/nome, ação de consultar). AR=2 (Requisito documental, CNAE). Recontagem 16/10/2026: mantida (linha 129 da contagem de 01/10/2026).
A24: =IF(H24="",IF(C24="",A23,A23+1),A23) | B24: =IF(A24=A23,"",CONCATENATE("F",A24)) | C24: Requisitos documentais - incluir | H24: EE | I24: I | J24: 7 | K24: 2 | L24: =CONCATENATE(H24,M24) | M24: =IF(OR(ISBLANK(J24),ISBLANK(K24)),IF(OR(H24="ALI",H24="AIE"),"L",IF(ISBLANK(H24),"","A")),IF(H24="EE",IF(K24>=3,IF(J24>=5,"H","A"),IF(K24>=2,IF(J24>=16,"H",IF(J24<=4,"L","A")),IF(J24<=15,"L","A"))),IF(OR(H24="SE",H24="CE"),IF(K24>=4,IF(J24>=6,"H","A"),IF(K24>=2,IF(J24>=20,"H",IF(J24<=5,"L","A")),IF(J24<=19,"L","A"))),IF(OR(H24="ALI",H24="AIE"),IF(K24>=6,IF(J24>=20,"H","A"),IF(K24>=2,IF(J24>=51,"H",IF(J24<=19,"L","A")),IF(J24<=50,"L","A"))))))) | N24: =IF(M24="L","Baixa",IF(M24="A","Média",IF(M24="","","Alta"))) | O24: =IF(ISBLANK(H24),"",IF(H24="ALI",IF(M24="L",7,IF(M24="A",10,15)),IF(H24="AIE",IF(M24="L",5,IF(M24="A",7,10)),IF(H24="SE",IF(M24="L",4,IF(M24="A",5,7)),IF(OR(H24="EE",H24="CE"),IF(M24="L",3,IF(M24="A",4,6))))))) | P24: =IF(I24="I",O24*Contagem!$W$15,IF(I24="E",O24*Contagem!$W$17,IF(I24="A",O24*Contagem!$W$16,IF(I24="T",O24*Contagem!$W$18,"")))) | Q24: Prova: Rota POST /gestao/requisitos-documentais (permissão manter-requisitos-documentais). Tela: gestao/requisitos-documentais/index. O gestor informa o requisito; StoreDocumentRequirementRequest valida código único. Grava Requisito documental (ativo) e Trilha de auditoria (HasAuditoria). Resultado: novo documento passa a poder ser exigido. Teste: tests/Feature/Solicitacao/DocumentRequirementCrudTest.php::test_cria_requisito_e_audita. Processo elementar independente: menor unidade com significado para o gestor; completa por si (formulário até o requisito gravado); deixa o negócio consistente (requisito ativo e auditado); lógica única (inclusão com código único). TD=7 (código, nome, descrição, obrigatório, instruções de validação, mensagem de sucesso/erro, ação de salvar). AR=2 (Requisito documental, Trilha de auditoria). Registros automáticos contados como FTR (premissa P4): Trilha de auditoria. Recontagem 16/10/2026: mantida (linha 130 da contagem de 01/10/2026).
A25: =IF(H25="",IF(C25="",A24,A24+1),A24) | B25: =IF(A25=A24,"",CONCATENATE("F",A25)) | C25: Requisitos documentais - alterar | H25: EE | I25: I | J25: 7 | K25: 2 | L25: =CONCATENATE(H25,M25) | M25: =IF(OR(ISBLANK(J25),ISBLANK(K25)),IF(OR(H25="ALI",H25="AIE"),"L",IF(ISBLANK(H25),"","A")),IF(H25="EE",IF(K25>=3,IF(J25>=5,"H","A"),IF(K25>=2,IF(J25>=16,"H",IF(J25<=4,"L","A")),IF(J25<=15,"L","A"))),IF(OR(H25="SE",H25="CE"),IF(K25>=4,IF(J25>=6,"H","A"),IF(K25>=2,IF(J25>=20,"H",IF(J25<=5,"L","A")),IF(J25<=19,"L","A"))),IF(OR(H25="ALI",H25="AIE"),IF(K25>=6,IF(J25>=20,"H","A"),IF(K25>=2,IF(J25>=51,"H",IF(J25<=19,"L","A")),IF(J25<=50,"L","A"))))))) | N25: =IF(M25="L","Baixa",IF(M25="A","Média",IF(M25="","","Alta"))) | O25: =IF(ISBLANK(H25),"",IF(H25="ALI",IF(M25="L",7,IF(M25="A",10,15)),IF(H25="AIE",IF(M25="L",5,IF(M25="A",7,10)),IF(H25="SE",IF(M25="L",4,IF(M25="A",5,7)),IF(OR(H25="EE",H25="CE"),IF(M25="L",3,IF(M25="A",4,6))))))) | P25: =IF(I25="I",O25*Contagem!$W$15,IF(I25="E",O25*Contagem!$W$17,IF(I25="A",O25*Contagem!$W$16,IF(I25="T",O25*Contagem!$W$18,"")))) | Q25: Prova: Rota PUT /gestao/requisitos-documentais/{requirement} (permissão manter-requisitos-documentais). Tela: gestao/requisitos-documentais/index. O gestor edita nome, descrição, obrigatoriedade e instruções; o código fica imutável. Grava Requisito documental e Trilha de auditoria. Resultado: nova regra documental vale para as próximas solicitações. Teste: tests/Feature/Solicitacao/DocumentRequirementCrudTest.php::test_code_unico_e_imutavel_na_edicao. Processo elementar independente: menor unidade com significado para o gestor; completa por si (edição até a gravação); deixa o negócio consistente (requisito alterado e auditado); lógica única (alteração sem mudar o código). TD=7 (código (identificação, imutável), nome, descrição, obrigatório, instruções de validação, mensagem de sucesso/erro, ação de salvar). AR=2 (Requisito documental, Trilha de auditoria). Registros automáticos contados como FTR (premissa P4): Trilha de auditoria. Recontagem 16/10/2026: mantida (linha 131 da contagem de 01/10/2026).
A26: =IF(H26="",IF(C26="",A25,A25+1),A25) | B26: =IF(A26=A25,"",CONCATENATE("F",A26)) | C26: Requisitos documentais - ativar ou inativar | H26: EE | I26: I | J26: 4 | K26: 2 | L26: =CONCATENATE(H26,M26) | M26: =IF(OR(ISBLANK(J26),ISBLANK(K26)),IF(OR(H26="ALI",H26="AIE"),"L",IF(ISBLANK(H26),"","A")),IF(H26="EE",IF(K26>=3,IF(J26>=5,"H","A"),IF(K26>=2,IF(J26>=16,"H",IF(J26<=4,"L","A")),IF(J26<=15,"L","A"))),IF(OR(H26="SE",H26="CE"),IF(K26>=4,IF(J26>=6,"H","A"),IF(K26>=2,IF(J26>=20,"H",IF(J26<=5,"L","A")),IF(J26<=19,"L","A"))),IF(OR(H26="ALI",H26="AIE"),IF(K26>=6,IF(J26>=20,"H","A"),IF(K26>=2,IF(J26>=51,"H",IF(J26<=19,"L","A")),IF(J26<=50,"L","A"))))))) | N26: =IF(M26="L","Baixa",IF(M26="A","Média",IF(M26="","","Alta"))) | O26: =IF(ISBLANK(H26),"",IF(H26="ALI",IF(M26="L",7,IF(M26="A",10,15)),IF(H26="AIE",IF(M26="L",5,IF(M26="A",7,10)),IF(H26="SE",IF(M26="L",4,IF(M26="A",5,7)),IF(OR(H26="EE",H26="CE"),IF(M26="L",3,IF(M26="A",4,6))))))) | P26: =IF(I26="I",O26*Contagem!$W$15,IF(I26="E",O26*Contagem!$W$17,IF(I26="A",O26*Contagem!$W$16,IF(I26="T",O26*Contagem!$W$18,"")))) | Q26: Prova: Rota PUT /gestao/requisitos-documentais/{requirement}/toggle (permissão manter-requisitos-documentais). Tela: gestao/requisitos-documentais/index. O gestor ativa ou inativa sem excluir. Grava Requisito documental e Trilha de auditoria. Resultado: requisito deixa de ser exigido ou volta a ser. Teste: tests/Feature/Solicitacao/DocumentRequirementCrudTest.php::test_desativar_preserva_o_registro. Processo elementar independente: menor unidade com significado para o gestor; completa por si (clique até a nova situação); deixa o negócio consistente (registro preservado, situação trocada); lógica única (alternância de situação, distinta da edição). TD=4 (código do requisito, situação, mensagem de sucesso, ação de ativar/inativar). AR=2 (Requisito documental, Trilha de auditoria). Registros automáticos contados como FTR (premissa P4): Trilha de auditoria. Recontagem 16/10/2026: mantida (linha 132 da contagem de 01/10/2026).
A27: =IF(H27="",IF(C27="",A26,A26+1),A26) | B27: =IF(A27=A26,"",CONCATENATE("F",A27)) | C27: Requisitos documentais - vincular CNAEs | H27: EE | I27: I | J27: 4 | K27: 3 | L27: =CONCATENATE(H27,M27) | M27: =IF(OR(ISBLANK(J27),ISBLANK(K27)),IF(OR(H27="ALI",H27="AIE"),"L",IF(ISBLANK(H27),"","A")),IF(H27="EE",IF(K27>=3,IF(J27>=5,"H","A"),IF(K27>=2,IF(J27>=16,"H",IF(J27<=4,"L","A")),IF(J27<=15,"L","A"))),IF(OR(H27="SE",H27="CE"),IF(K27>=4,IF(J27>=6,"H","A"),IF(K27>=2,IF(J27>=20,"H",IF(J27<=5,"L","A")),IF(J27<=19,"L","A"))),IF(OR(H27="ALI",H27="AIE"),IF(K27>=6,IF(J27>=20,"H","A"),IF(K27>=2,IF(J27>=51,"H",IF(J27<=19,"L","A")),IF(J27<=50,"L","A"))))))) | N27: =IF(M27="L","Baixa",IF(M27="A","Média",IF(M27="","","Alta"))) | O27: =IF(ISBLANK(H27),"",IF(H27="ALI",IF(M27="L",7,IF(M27="A",10,15)),IF(H27="AIE",IF(M27="L",5,IF(M27="A",7,10)),IF(H27="SE",IF(M27="L",4,IF(M27="A",5,7)),IF(OR(H27="EE",H27="CE"),IF(M27="L",3,IF(M27="A",4,6))))))) | P27: =IF(I27="I",O27*Contagem!$W$15,IF(I27="E",O27*Contagem!$W$17,IF(I27="A",O27*Contagem!$W$16,IF(I27="T",O27*Contagem!$W$18,"")))) | Q27: Prova: Rota PUT /gestao/requisitos-documentais/{requirement}/cnaes (permissão manter-requisitos-documentais). Tela: gestao/requisitos-documentais/index. O gestor marca os CNAEs; só CNAE ativo é aceito. Lê CNAE; grava o vínculo do Requisito documental (sync exato) e Trilha de auditoria com antes/depois. Resultado: muda a obrigatoriedade por atividade. Teste: tests/Feature/Solicitacao/DocumentRequirementCrudTest.php::test_vincula_cnaes_por_sync_exato_e_audita. Processo elementar independente: menor unidade com significado para o gestor; completa por si (seleção até o vínculo gravado); deixa o negócio consistente (conjunto exato de CNAEs auditado); lógica única (sincronização N:N com validação de CNAE ativo). TD=4 (código do requisito, CNAEs marcados, mensagem de sucesso/erro, ação de salvar vínculo). AR=3 (Requisito documental, CNAE, Trilha de auditoria). Registros automáticos contados como FTR (premissa P4): Trilha de auditoria. Recontagem 16/10/2026: mantida (linha 133 da contagem de 01/10/2026).
A28: =IF(H28="",IF(C28="",A27,A27+1),A27) | B28: =IF(A28=A27,"",CONCATENATE("F",A28)) | L28: =CONCATENATE(H28,M28) | M28: =IF(OR(ISBLANK(J28),ISBLANK(K28)),IF(OR(H28="ALI",H28="AIE"),"L",IF(ISBLANK(H28),"","A")),IF(H28="EE",IF(K28>=3,IF(J28>=5,"H","A"),IF(K28>=2,IF(J28>=16,"H",IF(J28<=4,"L","A")),IF(J28<=15,"L","A"))),IF(OR(H28="SE",H28="CE"),IF(K28>=4,IF(J28>=6,"H","A"),IF(K28>=2,IF(J28>=20,"H",IF(J28<=5,"L","A")),IF(J28<=19,"L","A"))),IF(OR(H28="ALI",H28="AIE"),IF(K28>=6,IF(J28>=20,"H","A"),IF(K28>=2,IF(J28>=51,"H",IF(J28<=19,"L","A")),IF(J28<=50,"L","A"))))))) | N28: =IF(M28="L","Baixa",IF(M28="A","Média",IF(M28="","","Alta"))) | O28: =IF(ISBLANK(H28),"",IF(H28="ALI",IF(M28="L",7,IF(M28="A",10,15)),IF(H28="AIE",IF(M28="L",5,IF(M28="A",7,10)),IF(H28="SE",IF(M28="L",4,IF(M28="A",5,7)),IF(OR(H28="EE",H28="CE"),IF(M28="L",3,IF(M28="A",4,6))))))) | P28: =IF(I28="I",O28*Contagem!$W$15,IF(I28="E",O28*Contagem!$W$17,IF(I28="A",O28*Contagem!$W$16,IF(I28="T",O28*Contagem!$W$18,""))))
A29: =IF(H29="",IF(C29="",A28,A28+1),A28) | B29: =IF(A29=A28,"",CONCATENATE("F",A29)) | C29: Setores | L29: =CONCATENATE(H29,M29) | M29: =IF(OR(ISBLANK(J29),ISBLANK(K29)),IF(OR(H29="ALI",H29="AIE"),"L",IF(ISBLANK(H29),"","A")),IF(H29="EE",IF(K29>=3,IF(J29>=5,"H","A"),IF(K29>=2,IF(J29>=16,"H",IF(J29<=4,"L","A")),IF(J29<=15,"L","A"))),IF(OR(H29="SE",H29="CE"),IF(K29>=4,IF(J29>=6,"H","A"),IF(K29>=2,IF(J29>=20,"H",IF(J29<=5,"L","A")),IF(J29<=19,"L","A"))),IF(OR(H29="ALI",H29="AIE"),IF(K29>=6,IF(J29>=20,"H","A"),IF(K29>=2,IF(J29>=51,"H",IF(J29<=19,"L","A")),IF(J29<=50,"L","A"))))))) | N29: =IF(M29="L","Baixa",IF(M29="A","Média",IF(M29="","","Alta"))) | O29: =IF(ISBLANK(H29),"",IF(H29="ALI",IF(M29="L",7,IF(M29="A",10,15)),IF(H29="AIE",IF(M29="L",5,IF(M29="A",7,10)),IF(H29="SE",IF(M29="L",4,IF(M29="A",5,7)),IF(OR(H29="EE",H29="CE"),IF(M29="L",3,IF(M29="A",4,6))))))) | P29: =IF(I29="I",O29*Contagem!$W$15,IF(I29="E",O29*Contagem!$W$17,IF(I29="A",O29*Contagem!$W$16,IF(I29="T",O29*Contagem!$W$18,""))))
A30: =IF(H30="",IF(C30="",A29,A29+1),A29) | B30: =IF(A30=A29,"",CONCATENATE("F",A30)) | C30: Dados - Setor | H30: ALI | I30: I | J30: 4 | K30: 1 | L30: =CONCATENATE(H30,M30) | M30: =IF(OR(ISBLANK(J30),ISBLANK(K30)),IF(OR(H30="ALI",H30="AIE"),"L",IF(ISBLANK(H30),"","A")),IF(H30="EE",IF(K30>=3,IF(J30>=5,"H","A"),IF(K30>=2,IF(J30>=16,"H",IF(J30<=4,"L","A")),IF(J30<=15,"L","A"))),IF(OR(H30="SE",H30="CE"),IF(K30>=4,IF(J30>=6,"H","A"),IF(K30>=2,IF(J30>=20,"H",IF(J30<=5,"L","A")),IF(J30<=19,"L","A"))),IF(OR(H30="ALI",H30="AIE"),IF(K30>=6,IF(J30>=20,"H","A"),IF(K30>=2,IF(J30>=51,"H",IF(J30<=19,"L","A")),IF(J30<=50,"L","A"))))))) | N30: =IF(M30="L","Baixa",IF(M30="A","Média",IF(M30="","","Alta"))) | O30: =IF(ISBLANK(H30),"",IF(H30="ALI",IF(M30="L",7,IF(M30="A",10,15)),IF(H30="AIE",IF(M30="L",5,IF(M30="A",7,10)),IF(H30="SE",IF(M30="L",4,IF(M30="A",5,7)),IF(OR(H30="EE",H30="CE"),IF(M30="L",3,IF(M30="A",4,6))))))) | P30: =IF(I30="I",O30*Contagem!$W$15,IF(I30="E",O30*Contagem!$W$17,IF(I30="A",O30*Contagem!$W$16,IF(I30="T",O30*Contagem!$W$18,"")))) | Q30: Prova: Model app/Models/Sector.php; migrations database/migrations/2026_06_14_215040_create_sectors_table.php, 2026_06_14_215041_create_sector_user_table.php e 2026_09_24_222200_add_sector_code_and_user_sector_assignments.php (coluna code = CEIN_NUMERO institucional). Mantido por Setores - incluir, alterar, ativar ou inativar e vincular analistas (SectorController) e pela sincronização da lotação no login AD (UserSectorAssignmentSync). Teste: tests/Feature/Analise/SectorCrudTest.php::test_vincula_e_desvincula_analistas_auditado. Arquivo lógico: o setor é a caixa de análise da distribuição, com analistas vinculados (N:N) e processos distribuídos a ele; a situação decide se recebe novas distribuições. Não é dado de código (Parte 1 §5.4.2 d; Parte 3 Cap. 1): além de código e nome, mantém relacionamento de negócio com analistas e processos, que não se substitui pela descrição. O vínculo sector_user só tem chaves e entra como DER (analista vinculado), não como TR. TD=4 (código institucional (CEIN), nome, situação, analista vinculado). TR=1 (Setor). Recontagem 16/10/2026: alterada (linha 176 da contagem de 01/10/2026: "Dados - Setor", ALI Baixa 7 PF, TD 3, AR 1). Motivo: TD 3→4: migration 2026_09_24_222200 incluiu o código institucional do setor (CEIN), usado para casar a lotação vinda do AD. PF inalterado (ALI Baixa).
A31: =IF(H31="",IF(C31="",A30,A30+1),A30) | B31: =IF(A31=A30,"",CONCATENATE("F",A31)) | C31: Setores - consultar | H31: SE | I31: I | J31: 7 | K31: 3 | L31: =CONCATENATE(H31,M31) | M31: =IF(OR(ISBLANK(J31),ISBLANK(K31)),IF(OR(H31="ALI",H31="AIE"),"L",IF(ISBLANK(H31),"","A")),IF(H31="EE",IF(K31>=3,IF(J31>=5,"H","A"),IF(K31>=2,IF(J31>=16,"H",IF(J31<=4,"L","A")),IF(J31<=15,"L","A"))),IF(OR(H31="SE",H31="CE"),IF(K31>=4,IF(J31>=6,"H","A"),IF(K31>=2,IF(J31>=20,"H",IF(J31<=5,"L","A")),IF(J31<=19,"L","A"))),IF(OR(H31="ALI",H31="AIE"),IF(K31>=6,IF(J31>=20,"H","A"),IF(K31>=2,IF(J31>=51,"H",IF(J31<=19,"L","A")),IF(J31<=50,"L","A"))))))) | N31: =IF(M31="L","Baixa",IF(M31="A","Média",IF(M31="","","Alta"))) | O31: =IF(ISBLANK(H31),"",IF(H31="ALI",IF(M31="L",7,IF(M31="A",10,15)),IF(H31="AIE",IF(M31="L",5,IF(M31="A",7,10)),IF(H31="SE",IF(M31="L",4,IF(M31="A",5,7)),IF(OR(H31="EE",H31="CE"),IF(M31="L",3,IF(M31="A",4,6))))))) | P31: =IF(I31="I",O31*Contagem!$W$15,IF(I31="E",O31*Contagem!$W$17,IF(I31="A",O31*Contagem!$W$16,IF(I31="T",O31*Contagem!$W$18,"")))) | Q31: Prova: Rota GET /gestao/setores (permissão manter-setores). Tela: gestao/setores/index. O gestor lista setores com busca por nome e filtro de situação. Lê Setor, Usuário (analistas) e Solicitação de viabilidade (contagem de processos); não grava. Teste: tests/Feature/Analise/SectorCrudTest.php::test_administrador_lista_setores. Processo elementar independente: menor unidade com significado para o gestor; completa por si (filtra e recebe a lista); deixa o negócio consistente (nada é alterado); lógica única (setores com contagem de analistas e processos). Classificação: exibe contagens calculadas por setor (withCount de analistas e processos), dado derivado: SE, não CE (§5.5.3). TD=7 (busca por nome, situação, nome, quantidade de analistas, quantidade de processos, analistas vinculados, ação de consultar). O filtro de situação é o mesmo campo da coluna situação e conta uma vez (DER único); ordenação e paginação não contam. AR=3 (Setor, Usuário, Solicitação de viabilidade). Recontagem 16/10/2026: alterada (linha 177 da contagem de 01/10/2026: "Setores - consultar", SE Média 5 PF, TD 9, AR 3). Motivo: TD 9→7: ordenação e filtro de situação duplicado não contam; a lista de analistas disponíveis é apoio do formulário de vínculo. PF inalterado (SE Média).
A32: =IF(H32="",IF(C32="",A31,A31+1),A31) | B32: =IF(A32=A31,"",CONCATENATE("F",A32)) | C32: Setores - incluir | H32: EE | I32: I | J32: 4 | K32: 2 | L32: =CONCATENATE(H32,M32) | M32: =IF(OR(ISBLANK(J32),ISBLANK(K32)),IF(OR(H32="ALI",H32="AIE"),"L",IF(ISBLANK(H32),"","A")),IF(H32="EE",IF(K32>=3,IF(J32>=5,"H","A"),IF(K32>=2,IF(J32>=16,"H",IF(J32<=4,"L","A")),IF(J32<=15,"L","A"))),IF(OR(H32="SE",H32="CE"),IF(K32>=4,IF(J32>=6,"H","A"),IF(K32>=2,IF(J32>=20,"H",IF(J32<=5,"L","A")),IF(J32<=19,"L","A"))),IF(OR(H32="ALI",H32="AIE"),IF(K32>=6,IF(J32>=20,"H","A"),IF(K32>=2,IF(J32>=51,"H",IF(J32<=19,"L","A")),IF(J32<=50,"L","A"))))))) | N32: =IF(M32="L","Baixa",IF(M32="A","Média",IF(M32="","","Alta"))) | O32: =IF(ISBLANK(H32),"",IF(H32="ALI",IF(M32="L",7,IF(M32="A",10,15)),IF(H32="AIE",IF(M32="L",5,IF(M32="A",7,10)),IF(H32="SE",IF(M32="L",4,IF(M32="A",5,7)),IF(OR(H32="EE",H32="CE"),IF(M32="L",3,IF(M32="A",4,6))))))) | P32: =IF(I32="I",O32*Contagem!$W$15,IF(I32="E",O32*Contagem!$W$17,IF(I32="A",O32*Contagem!$W$16,IF(I32="T",O32*Contagem!$W$18,"")))) | Q32: Prova: Rota POST /gestao/setores (permissão manter-setores). Tela: gestao/setores/index. O gestor cadastra o setor (SectorRequest, nome único). Grava Setor e Trilha de auditoria (AuditService, ação criar). Resultado: nova caixa de análise disponível. Teste: tests/Feature/Analise/SectorCrudTest.php::test_cria_setor_auditado. Processo elementar independente: menor unidade com significado para o gestor; completa por si (informa nome e situação e recebe a confirmação); deixa o negócio consistente (setor único gravado e auditado); lógica única (inclusão com unicidade de nome). Classificação: mantém ALI, EE. TD=4 (nome, situação, mensagem, ação salvar). AR=2 (Setor, Trilha de auditoria). Registros automáticos contados como FTR (premissa P4): Trilha de auditoria. Recontagem 16/10/2026: alterada (linha 178 da contagem de 01/10/2026: "Setores - incluir", EE Baixa 3 PF, TD 4, AR 1). Motivo: AR 1→2: o controller grava a Trilha de auditoria explicitamente (AuditService). PF inalterado (EE Baixa).
A33: =IF(H33="",IF(C33="",A32,A32+1),A32) | B33: =IF(A33=A32,"",CONCATENATE("F",A33)) | C33: Setores - alterar | H33: EE | I33: I | J33: 4 | K33: 2 | L33: =CONCATENATE(H33,M33) | M33: =IF(OR(ISBLANK(J33),ISBLANK(K33)),IF(OR(H33="ALI",H33="AIE"),"L",IF(ISBLANK(H33),"","A")),IF(H33="EE",IF(K33>=3,IF(J33>=5,"H","A"),IF(K33>=2,IF(J33>=16,"H",IF(J33<=4,"L","A")),IF(J33<=15,"L","A"))),IF(OR(H33="SE",H33="CE"),IF(K33>=4,IF(J33>=6,"H","A"),IF(K33>=2,IF(J33>=20,"H",IF(J33<=5,"L","A")),IF(J33<=19,"L","A"))),IF(OR(H33="ALI",H33="AIE"),IF(K33>=6,IF(J33>=20,"H","A"),IF(K33>=2,IF(J33>=51,"H",IF(J33<=19,"L","A")),IF(J33<=50,"L","A"))))))) | N33: =IF(M33="L","Baixa",IF(M33="A","Média",IF(M33="","","Alta"))) | O33: =IF(ISBLANK(H33),"",IF(H33="ALI",IF(M33="L",7,IF(M33="A",10,15)),IF(H33="AIE",IF(M33="L",5,IF(M33="A",7,10)),IF(H33="SE",IF(M33="L",4,IF(M33="A",5,7)),IF(OR(H33="EE",H33="CE"),IF(M33="L",3,IF(M33="A",4,6))))))) | P33: =IF(I33="I",O33*Contagem!$W$15,IF(I33="E",O33*Contagem!$W$17,IF(I33="A",O33*Contagem!$W$16,IF(I33="T",O33*Contagem!$W$18,"")))) | Q33: Prova: Rota PUT /gestao/setores/{sector} (permissão manter-setores). Tela: gestao/setores/index. O gestor edita nome e situação. Grava Setor e Trilha de auditoria (AuditService, ação atualizar). Teste: tests/Feature/Analise/SectorCrudTest.php::test_edita_nome_e_situacao. Processo elementar independente: menor unidade com significado para o gestor; completa por si (altera os dados e recebe a confirmação); deixa o negócio consistente (nome continua único); lógica única (alteração do setor existente). Classificação: mantém ALI, EE. TD=4 (nome, situação, mensagem, ação salvar). AR=2 (Setor, Trilha de auditoria). Registros automáticos contados como FTR (premissa P4): Trilha de auditoria. Recontagem 16/10/2026: alterada (linha 179 da contagem de 01/10/2026: "Setores - alterar", EE Baixa 3 PF, TD 4, AR 1). Motivo: AR 1→2: o controller grava a Trilha de auditoria explicitamente (AuditService). PF inalterado (EE Baixa).
A34: =IF(H34="",IF(C34="",A33,A33+1),A33) | B34: =IF(A34=A33,"",CONCATENATE("F",A34)) | C34: Setores - ativar ou inativar | H34: EE | I34: I | J34: 4 | K34: 3 | L34: =CONCATENATE(H34,M34) | M34: =IF(OR(ISBLANK(J34),ISBLANK(K34)),IF(OR(H34="ALI",H34="AIE"),"L",IF(ISBLANK(H34),"","A")),IF(H34="EE",IF(K34>=3,IF(J34>=5,"H","A"),IF(K34>=2,IF(J34>=16,"H",IF(J34<=4,"L","A")),IF(J34<=15,"L","A"))),IF(OR(H34="SE",H34="CE"),IF(K34>=4,IF(J34>=6,"H","A"),IF(K34>=2,IF(J34>=20,"H",IF(J34<=5,"L","A")),IF(J34<=19,"L","A"))),IF(OR(H34="ALI",H34="AIE"),IF(K34>=6,IF(J34>=20,"H","A"),IF(K34>=2,IF(J34>=51,"H",IF(J34<=19,"L","A")),IF(J34<=50,"L","A"))))))) | N34: =IF(M34="L","Baixa",IF(M34="A","Média",IF(M34="","","Alta"))) | O34: =IF(ISBLANK(H34),"",IF(H34="ALI",IF(M34="L",7,IF(M34="A",10,15)),IF(H34="AIE",IF(M34="L",5,IF(M34="A",7,10)),IF(H34="SE",IF(M34="L",4,IF(M34="A",5,7)),IF(OR(H34="EE",H34="CE"),IF(M34="L",3,IF(M34="A",4,6))))))) | P34: =IF(I34="I",O34*Contagem!$W$15,IF(I34="E",O34*Contagem!$W$17,IF(I34="A",O34*Contagem!$W$16,IF(I34="T",O34*Contagem!$W$18,"")))) | Q34: Prova: Rota PUT /gestao/setores/{sector}/ativacao (permissão manter-setores). Tela: gestao/setores/index. O gestor liga ou desliga o setor. Conta processos em análise ou em pendência do setor, grava a situação e a Trilha de auditoria; avisa sem bloquear. Teste: tests/Feature/Analise/SectorCrudTest.php::test_inativar_setor_com_processo_em_aberto_avisa_mas_nao_bloqueia. Processo elementar independente: menor unidade com significado para o gestor; completa por si (alterna e recebe confirmação e aviso); deixa o negócio consistente (setor preservado, sem exclusão); lógica única (inativação com aviso de processos em aberto, distinta da edição). Classificação: mantém ALI, EE. TD=4 (setor, situação, mensagem (inclui o aviso com a quantidade de processos em aberto), ação ativar/inativar). AR=3 (Setor, Solicitação de viabilidade, Trilha de auditoria). Registros automáticos contados como FTR (premissa P4): Trilha de auditoria. Recontagem 16/10/2026: alterada (linha 180 da contagem de 01/10/2026: "Setores - ativar ou inativar", EE Média 4 PF, TD 5, AR 2). Motivo: TD 5→4: o aviso de processos em aberto é parte da mensagem (mensagens = 1 DER). AR 2→3: inclui a Trilha de auditoria gravada pelo controller. PF inalterado (EE Média).
A35: =IF(H35="",IF(C35="",A34,A34+1),A34) | B35: =IF(A35=A34,"",CONCATENATE("F",A35)) | C35: Setores - vincular analistas | H35: EE | I35: I | J35: 4 | K35: 3 | L35: =CONCATENATE(H35,M35) | M35: =IF(OR(ISBLANK(J35),ISBLANK(K35)),IF(OR(H35="ALI",H35="AIE"),"L",IF(ISBLANK(H35),"","A")),IF(H35="EE",IF(K35>=3,IF(J35>=5,"H","A"),IF(K35>=2,IF(J35>=16,"H",IF(J35<=4,"L","A")),IF(J35<=15,"L","A"))),IF(OR(H35="SE",H35="CE"),IF(K35>=4,IF(J35>=6,"H","A"),IF(K35>=2,IF(J35>=20,"H",IF(J35<=5,"L","A")),IF(J35<=19,"L","A"))),IF(OR(H35="ALI",H35="AIE"),IF(K35>=6,IF(J35>=20,"H","A"),IF(K35>=2,IF(J35>=51,"H",IF(J35<=19,"L","A")),IF(J35<=50,"L","A"))))))) | N35: =IF(M35="L","Baixa",IF(M35="A","Média",IF(M35="","","Alta"))) | O35: =IF(ISBLANK(H35),"",IF(H35="ALI",IF(M35="L",7,IF(M35="A",10,15)),IF(H35="AIE",IF(M35="L",5,IF(M35="A",7,10)),IF(H35="SE",IF(M35="L",4,IF(M35="A",5,7)),IF(OR(H35="EE",H35="CE"),IF(M35="L",3,IF(M35="A",4,6))))))) | P35: =IF(I35="I",O35*Contagem!$W$15,IF(I35="E",O35*Contagem!$W$17,IF(I35="A",O35*Contagem!$W$16,IF(I35="T",O35*Contagem!$W$18,"")))) | Q35: Prova: Rota PUT /gestao/setores/{sector}/analistas (permissão manter-setores). Tela: gestao/setores/index. O gestor define o conjunto exato de analistas do setor, escolhidos entre usuários ativos com perfil que concede analisar-processos. Valida os usuários, grava o vínculo N:N em transação e a Trilha de auditoria com antes e depois. Teste: tests/Feature/Analise/SectorCrudTest.php::test_vincula_e_desvincula_analistas_auditado. Processo elementar independente: menor unidade com significado para o gestor; completa por si (marca analistas e recebe a confirmação); deixa o negócio consistente (vínculo sincronizado sem afetar outros setores); lógica única (sincroniza vínculo analista-setor). Classificação: mantém ALI, EE. TD=4 (setor, analistas, mensagem, ação salvar vínculo). AR=3 (Setor, Usuário, Trilha de auditoria). Registros automáticos contados como FTR (premissa P4): Trilha de auditoria. Recontagem 16/10/2026: alterada (linha 181 da contagem de 01/10/2026: "Setores - vincular analistas", EE Baixa 3 PF, TD 4, AR 2). Motivo: AR 2→3: inclui a Trilha de auditoria gravada com antes/depois do vínculo. PF 3→4 (EE Média).
A36: =IF(H36="",IF(C36="",A35,A35+1),A35) | B36: =IF(A36=A35,"",CONCATENATE("F",A36)) | L36: =CONCATENATE(H36,M36) | M36: =IF(OR(ISBLANK(J36),ISBLANK(K36)),IF(OR(H36="ALI",H36="AIE"),"L",IF(ISBLANK(H36),"","A")),IF(H36="EE",IF(K36>=3,IF(J36>=5,"H","A"),IF(K36>=2,IF(J36>=16,"H",IF(J36<=4,"L","A")),IF(J36<=15,"L","A"))),IF(OR(H36="SE",H36="CE"),IF(K36>=4,IF(J36>=6,"H","A"),IF(K36>=2,IF(J36>=20,"H",IF(J36<=5,"L","A")),IF(J36<=19,"L","A"))),IF(OR(H36="ALI",H36="AIE"),IF(K36>=6,IF(J36>=20,"H","A"),IF(K36>=2,IF(J36>=51,"H",IF(J36<=19,"L","A")),IF(J36<=50,"L","A"))))))) | N36: =IF(M36="L","Baixa",IF(M36="A","Média",IF(M36="","","Alta"))) | O36: =IF(ISBLANK(H36),"",IF(H36="ALI",IF(M36="L",7,IF(M36="A",10,15)),IF(H36="AIE",IF(M36="L",5,IF(M36="A",7,10)),IF(H36="SE",IF(M36="L",4,IF(M36="A",5,7)),IF(OR(H36="EE",H36="CE"),IF(M36="L",3,IF(M36="A",4,6))))))) | P36: =IF(I36="I",O36*Contagem!$W$15,IF(I36="E",O36*Contagem!$W$17,IF(I36="A",O36*Contagem!$W$16,IF(I36="T",O36*Contagem!$W$18,""))))
A37: =IF(H37="",IF(C37="",A36,A36+1),A36) | B37: =IF(A37=A36,"",CONCATENATE("F",A37)) | C37: Perfis de acesso | L37: =CONCATENATE(H37,M37) | M37: =IF(OR(ISBLANK(J37),ISBLANK(K37)),IF(OR(H37="ALI",H37="AIE"),"L",IF(ISBLANK(H37),"","A")),IF(H37="EE",IF(K37>=3,IF(J37>=5,"H","A"),IF(K37>=2,IF(J37>=16,"H",IF(J37<=4,"L","A")),IF(J37<=15,"L","A"))),IF(OR(H37="SE",H37="CE"),IF(K37>=4,IF(J37>=6,"H","A"),IF(K37>=2,IF(J37>=20,"H",IF(J37<=5,"L","A")),IF(J37<=19,"L","A"))),IF(OR(H37="ALI",H37="AIE"),IF(K37>=6,IF(J37>=20,"H","A"),IF(K37>=2,IF(J37>=51,"H",IF(J37<=19,"L","A")),IF(J37<=50,"L","A"))))))) | N37: =IF(M37="L","Baixa",IF(M37="A","Média",IF(M37="","","Alta"))) | O37: =IF(ISBLANK(H37),"",IF(H37="ALI",IF(M37="L",7,IF(M37="A",10,15)),IF(H37="AIE",IF(M37="L",5,IF(M37="A",7,10)),IF(H37="SE",IF(M37="L",4,IF(M37="A",5,7)),IF(OR(H37="EE",H37="CE"),IF(M37="L",3,IF(M37="A",4,6))))))) | P37: =IF(I37="I",O37*Contagem!$W$15,IF(I37="E",O37*Contagem!$W$17,IF(I37="A",O37*Contagem!$W$16,IF(I37="T",O37*Contagem!$W$18,""))))
A38: =IF(H38="",IF(C38="",A37,A37+1),A37) | B38: =IF(A38=A37,"",CONCATENATE("F",A38)) | C38: Dados - Perfil de acesso | H38: ALI | I38: I | J38: 3 | K38: 1 | L38: =CONCATENATE(H38,M38) | M38: =IF(OR(ISBLANK(J38),ISBLANK(K38)),IF(OR(H38="ALI",H38="AIE"),"L",IF(ISBLANK(H38),"","A")),IF(H38="EE",IF(K38>=3,IF(J38>=5,"H","A"),IF(K38>=2,IF(J38>=16,"H",IF(J38<=4,"L","A")),IF(J38<=15,"L","A"))),IF(OR(H38="SE",H38="CE"),IF(K38>=4,IF(J38>=6,"H","A"),IF(K38>=2,IF(J38>=20,"H",IF(J38<=5,"L","A")),IF(J38<=19,"L","A"))),IF(OR(H38="ALI",H38="AIE"),IF(K38>=6,IF(J38>=20,"H","A"),IF(K38>=2,IF(J38>=51,"H",IF(J38<=19,"L","A")),IF(J38<=50,"L","A"))))))) | N38: =IF(M38="L","Baixa",IF(M38="A","Média",IF(M38="","","Alta"))) | O38: =IF(ISBLANK(H38),"",IF(H38="ALI",IF(M38="L",7,IF(M38="A",10,15)),IF(H38="AIE",IF(M38="L",5,IF(M38="A",7,10)),IF(H38="SE",IF(M38="L",4,IF(M38="A",5,7)),IF(OR(H38="EE",H38="CE"),IF(M38="L",3,IF(M38="A",4,6))))))) | P38: =IF(I38="I",O38*Contagem!$W$15,IF(I38="E",O38*Contagem!$W$17,IF(I38="A",O38*Contagem!$W$16,IF(I38="T",O38*Contagem!$W$18,"")))) | Q38: Prova: tabelas roles e role_has_permissions (Spatie) da migration database/migrations/2026_06_09_234627_create_permission_tables.php e coluna protegido da migration database/migrations/2026_10_14_090000_add_protegido_to_roles_table.php; regras em app/Support/RoleProtection.php e app/Support/PerfisSolicitaveis.php. Mantido por Perfis de acesso - incluir, alterar e excluir (Gestao\RoleController). Teste: tests/Feature/Roles/ManageRolesTest.php::test_permissoes_de_perfil_novo_tem_efeito_imediato. Arquivo lógico: desde 14/10/2026 (commits 4e7e897f, a61f229c, 0872c807, 23ee97e1) o comportamento da gestão depende só das permissões marcadas no perfil: abas de usuários (acessar-gestao), candidatos a analista do setor (analisar-processos), escalonamento e perfis que o servidor pode solicitar no primeiro acesso AD. O administrador cria, renomeia, ajusta permissões e exclui perfis pela tela; o perfil existe sem usuário vinculado (exclusão só é barrada quando há vínculo), logo passa no teste de independência e não é subgrupo de Usuário. Não é dado de código: o conjunto de permissões muda o que cada conta pode fazer e não se substitui pelo nome. O catálogo de permissões (tabela permissions, descrição e grupo em app/Support/PermissionCatalog.php) é carregado por seeder e não é mantido pelo usuário: dado de código, não conta. role_has_permissions só tem chaves e entra como DER (permissões concedidas). TD=3 (nome do perfil, permissões concedidas, protegido). TR=1 (Perfil de acesso). Recontagem 16/10/2026: nova (não constava da contagem de 01/10/2026).
A39: =IF(H39="",IF(C39="",A38,A38+1),A38) | B39: =IF(A39=A38,"",CONCATENATE("F",A39)) | C39: Perfis de acesso - consultar | H39: SE | I39: I | J39: 8 | K39: 3 | L39: =CONCATENATE(H39,M39) | M39: =IF(OR(ISBLANK(J39),ISBLANK(K39)),IF(OR(H39="ALI",H39="AIE"),"L",IF(ISBLANK(H39),"","A")),IF(H39="EE",IF(K39>=3,IF(J39>=5,"H","A"),IF(K39>=2,IF(J39>=16,"H",IF(J39<=4,"L","A")),IF(J39<=15,"L","A"))),IF(OR(H39="SE",H39="CE"),IF(K39>=4,IF(J39>=6,"H","A"),IF(K39>=2,IF(J39>=20,"H",IF(J39<=5,"L","A")),IF(J39<=19,"L","A"))),IF(OR(H39="ALI",H39="AIE"),IF(K39>=6,IF(J39>=20,"H","A"),IF(K39>=2,IF(J39>=51,"H",IF(J39<=19,"L","A")),IF(J39<=50,"L","A"))))))) | N39: =IF(M39="L","Baixa",IF(M39="A","Média",IF(M39="","","Alta"))) | O39: =IF(ISBLANK(H39),"",IF(H39="ALI",IF(M39="L",7,IF(M39="A",10,15)),IF(H39="AIE",IF(M39="L",5,IF(M39="A",7,10)),IF(H39="SE",IF(M39="L",4,IF(M39="A",5,7)),IF(OR(H39="EE",H39="CE"),IF(M39="L",3,IF(M39="A",4,6))))))) | P39: =IF(I39="I",O39*Contagem!$W$15,IF(I39="E",O39*Contagem!$W$17,IF(I39="A",O39*Contagem!$W$16,IF(I39="T",O39*Contagem!$W$18,"")))) | Q39: Prova: Rota GET /gestao/perfis (permissão manter-perfis). Tela: gestao/perfis/index. O administrador busca perfis por nome. Lê perfis com permissões, conta usuários vinculados (withCount) e marca os protegidos (coluna protegido ou perfil apontado pelo parâmetro portal.perfil_cidadao). Não grava. A exportação (?formato=csv/xlsx/pdf, ReportExporter) não tem botão nesta tela (a página não usa ExportMenu; só é alcançável digitando a URL) e não é contada como função; a consulta da tela não grava Trilha de auditoria (o log só ocorre no ramo ?formato=), por isso continua sem FTR de registro. Teste: tests/Feature/Roles/ManageRolesTest.php::test_administrador_lista_perfis_com_permissoes_e_vinculos e ::test_listagem_marca_protegido_no_campo_structural. Processo elementar independente: menor unidade com significado para o administrador; completa por si (busca até a lista); deixa o negócio consistente (nada muda); lógica única (perfis com contagem de usuários e indicação de protegido). Classificação: exibe quantidade de usuários por perfil, dado derivado: SE, não CE (§5.5.3). TD=8 (busca por nome, nome do perfil, permissões, quantidade de usuários vinculados, protegido, descrição da permissão, grupo da permissão, ação de consultar). AR=3 (Perfil de acesso, Usuário, Parâmetro). Recontagem 16/10/2026: alterada (linha 209 da contagem de 01/10/2026: "Perfis de acesso - consultar", SE Baixa 4 PF, TD 7, AR 1). Motivo: TD 7→8: busca por nome passou a ser server-driven. AR 1→3: o perfil virou ALI próprio (Perfil de acesso); a contagem de usuários lê Usuário e a marca de protegido lê o parâmetro portal.perfil_cidadao (Parâmetro). PF 4→5 (SE Média).
A40: =IF(H40="",IF(C40="",A39,A39+1),A39) | B40: =IF(A40=A39,"",CONCATENATE("F",A40)) | C40: Perfis de acesso - incluir | H40: EE | I40: I | J40: 4 | K40: 2 | L40: =CONCATENATE(H40,M40) | M40: =IF(OR(ISBLANK(J40),ISBLANK(K40)),IF(OR(H40="ALI",H40="AIE"),"L",IF(ISBLANK(H40),"","A")),IF(H40="EE",IF(K40>=3,IF(J40>=5,"H","A"),IF(K40>=2,IF(J40>=16,"H",IF(J40<=4,"L","A")),IF(J40<=15,"L","A"))),IF(OR(H40="SE",H40="CE"),IF(K40>=4,IF(J40>=6,"H","A"),IF(K40>=2,IF(J40>=20,"H",IF(J40<=5,"L","A")),IF(J40<=19,"L","A"))),IF(OR(H40="ALI",H40="AIE"),IF(K40>=6,IF(J40>=20,"H","A"),IF(K40>=2,IF(J40>=51,"H",IF(J40<=19,"L","A")),IF(J40<=50,"L","A"))))))) | N40: =IF(M40="L","Baixa",IF(M40="A","Média",IF(M40="","","Alta"))) | O40: =IF(ISBLANK(H40),"",IF(H40="ALI",IF(M40="L",7,IF(M40="A",10,15)),IF(H40="AIE",IF(M40="L",5,IF(M40="A",7,10)),IF(H40="SE",IF(M40="L",4,IF(M40="A",5,7)),IF(OR(H40="EE",H40="CE"),IF(M40="L",3,IF(M40="A",4,6))))))) | P40: =IF(I40="I",O40*Contagem!$W$15,IF(I40="E",O40*Contagem!$W$17,IF(I40="A",O40*Contagem!$W$16,IF(I40="T",O40*Contagem!$W$18,"")))) | Q40: Prova: Rota POST /gestao/perfis (permissão manter-perfis). Tela: gestao/perfis/index. O administrador cria o perfil e marca permissões; StoreRoleRequest rejeita nome duplicado e permissão inexistente. Grava Perfil de acesso (roles e role_has_permissions) e Trilha de auditoria (perfil-criado). Resultado: permissões valem de imediato. Teste: tests/Feature/Roles/ManageRolesTest.php::test_cria_perfil_com_permissoes_granulares. Processo elementar independente: menor unidade com significado para o administrador; completa por si (formulário até o perfil gravado); deixa o negócio consistente (perfil com permissões, auditado); lógica única (inclusão com sincronização de permissões). Classificação: mantém ALI, EE. TD=4 (nome do perfil, permissões marcadas, mensagem de sucesso/erro, ação de salvar). AR=2 (Perfil de acesso, Trilha de auditoria). Registros automáticos contados como FTR (premissa P4): Trilha de auditoria. Recontagem 16/10/2026: mantida (linha 210 da contagem de 01/10/2026).
A41: =IF(H41="",IF(C41="",A40,A40+1),A40) | B41: =IF(A41=A40,"",CONCATENATE("F",A41)) | C41: Perfis de acesso - alterar | H41: EE | I41: I | J41: 4 | K41: 3 | L41: =CONCATENATE(H41,M41) | M41: =IF(OR(ISBLANK(J41),ISBLANK(K41)),IF(OR(H41="ALI",H41="AIE"),"L",IF(ISBLANK(H41),"","A")),IF(H41="EE",IF(K41>=3,IF(J41>=5,"H","A"),IF(K41>=2,IF(J41>=16,"H",IF(J41<=4,"L","A")),IF(J41<=15,"L","A"))),IF(OR(H41="SE",H41="CE"),IF(K41>=4,IF(J41>=6,"H","A"),IF(K41>=2,IF(J41>=20,"H",IF(J41<=5,"L","A")),IF(J41<=19,"L","A"))),IF(OR(H41="ALI",H41="AIE"),IF(K41>=6,IF(J41>=20,"H","A"),IF(K41>=2,IF(J41>=51,"H",IF(J41<=19,"L","A")),IF(J41<=50,"L","A"))))))) | N41: =IF(M41="L","Baixa",IF(M41="A","Média",IF(M41="","","Alta"))) | O41: =IF(ISBLANK(H41),"",IF(H41="ALI",IF(M41="L",7,IF(M41="A",10,15)),IF(H41="AIE",IF(M41="L",5,IF(M41="A",7,10)),IF(H41="SE",IF(M41="L",4,IF(M41="A",5,7)),IF(OR(H41="EE",H41="CE"),IF(M41="L",3,IF(M41="A",4,6))))))) | P41: =IF(I41="I",O41*Contagem!$W$15,IF(I41="E",O41*Contagem!$W$17,IF(I41="A",O41*Contagem!$W$16,IF(I41="T",O41*Contagem!$W$18,"")))) | Q41: Prova: Rota PUT /gestao/perfis/{role} (permissão manter-perfis). Tela: gestao/perfis/index. O administrador ajusta nome e permissões; perfil protegido (coluna protegido ou perfil apontado por portal.perfil_cidadao) não é renomeado e o administrador não perde acessar-gestao (UpdateRoleRequest::after). Grava Perfil de acesso e Trilha de auditoria com antes/depois. Resultado: acesso das contas muda. Teste: tests/Feature/Roles/ManageRolesTest.php::test_perfil_apontado_pelo_parametro_do_cidadao_nao_pode_ser_excluido_nem_renomeado. Processo elementar independente: menor unidade com significado para o administrador; completa por si (edição até a gravação); deixa o negócio consistente (permissões sincronizadas, perfil protegido preservado, auditado); lógica única (alteração com proteção). Classificação: mantém ALI, EE. TD=4 (nome do perfil, permissões marcadas, mensagem de sucesso/erro, ação de salvar). AR=3 (Perfil de acesso, Parâmetro, Trilha de auditoria). Registros automáticos contados como FTR (premissa P4): Trilha de auditoria. Recontagem 16/10/2026: alterada (linha 211 da contagem de 01/10/2026: "Perfis de acesso - alterar", EE Baixa 3 PF, TD 4, AR 2). Motivo: AR 2→3: grava Perfil de acesso (antes Usuário) e lê o parâmetro portal.perfil_cidadao para impedir renomear o perfil do cidadão (commit 78cf5671). PF 3→4 (EE Média).
A42: =IF(H42="",IF(C42="",A41,A41+1),A41) | B42: =IF(A42=A41,"",CONCATENATE("F",A42)) | C42: Perfis de acesso - excluir | H42: EE | I42: I | J42: 3 | K42: 4 | L42: =CONCATENATE(H42,M42) | M42: =IF(OR(ISBLANK(J42),ISBLANK(K42)),IF(OR(H42="ALI",H42="AIE"),"L",IF(ISBLANK(H42),"","A")),IF(H42="EE",IF(K42>=3,IF(J42>=5,"H","A"),IF(K42>=2,IF(J42>=16,"H",IF(J42<=4,"L","A")),IF(J42<=15,"L","A"))),IF(OR(H42="SE",H42="CE"),IF(K42>=4,IF(J42>=6,"H","A"),IF(K42>=2,IF(J42>=20,"H",IF(J42<=5,"L","A")),IF(J42<=19,"L","A"))),IF(OR(H42="ALI",H42="AIE"),IF(K42>=6,IF(J42>=20,"H","A"),IF(K42>=2,IF(J42>=51,"H",IF(J42<=19,"L","A")),IF(J42<=50,"L","A"))))))) | N42: =IF(M42="L","Baixa",IF(M42="A","Média",IF(M42="","","Alta"))) | O42: =IF(ISBLANK(H42),"",IF(H42="ALI",IF(M42="L",7,IF(M42="A",10,15)),IF(H42="AIE",IF(M42="L",5,IF(M42="A",7,10)),IF(H42="SE",IF(M42="L",4,IF(M42="A",5,7)),IF(OR(H42="EE",H42="CE"),IF(M42="L",3,IF(M42="A",4,6))))))) | P42: =IF(I42="I",O42*Contagem!$W$15,IF(I42="E",O42*Contagem!$W$17,IF(I42="A",O42*Contagem!$W$16,IF(I42="T",O42*Contagem!$W$18,"")))) | Q42: Prova: Rota DELETE /gestao/perfis/{role} (permissão manter-perfis). Tela: gestao/perfis/index. O administrador exclui perfil comum; perfil protegido (coluna protegido ou apontado por portal.perfil_cidadao) ou com usuários vinculados é barrado com mensagem. Lê Usuário e Parâmetro; exclui Perfil de acesso; grava Trilha de auditoria (perfil-excluido). Teste: tests/Feature/Roles/ManageRolesTest.php::test_exclusao_bloqueada_com_usuarios_vinculados. Processo elementar independente: menor unidade com significado para o administrador; completa por si (confirmação até a remoção); deixa o negócio consistente (nenhuma conta fica sem perfil); lógica única (exclusão com bloqueio por proteção e por vínculo). Classificação: mantém ALI, EE. TD=3 (perfil, mensagem de sucesso/erro, ação de excluir). AR=4 (Perfil de acesso, Usuário, Parâmetro, Trilha de auditoria). Registros automáticos contados como FTR (premissa P4): Trilha de auditoria. Recontagem 16/10/2026: alterada (linha 212 da contagem de 01/10/2026: "Perfis de acesso - excluir", EE Baixa 3 PF, TD 3, AR 2). Motivo: AR 2→4: exclui de Perfil de acesso, lê Usuário (vínculo) e Parâmetro (perfil do cidadão protegido) e grava a Trilha. PF 3→4 (EE Média).
A43: =IF(H43="",IF(C43="",A42,A42+1),A42) | B43: =IF(A43=A42,"",CONCATENATE("F",A43)) | L43: =CONCATENATE(H43,M43) | M43: =IF(OR(ISBLANK(J43),ISBLANK(K43)),IF(OR(H43="ALI",H43="AIE"),"L",IF(ISBLANK(H43),"","A")),IF(H43="EE",IF(K43>=3,IF(J43>=5,"H","A"),IF(K43>=2,IF(J43>=16,"H",IF(J43<=4,"L","A")),IF(J43<=15,"L","A"))),IF(OR(H43="SE",H43="CE"),IF(K43>=4,IF(J43>=6,"H","A"),IF(K43>=2,IF(J43>=20,"H",IF(J43<=5,"L","A")),IF(J43<=19,"L","A"))),IF(OR(H43="ALI",H43="AIE"),IF(K43>=6,IF(J43>=20,"H","A"),IF(K43>=2,IF(J43>=51,"H",IF(J43<=19,"L","A")),IF(J43<=50,"L","A"))))))) | N43: =IF(M43="L","Baixa",IF(M43="A","Média",IF(M43="","","Alta"))) | O43: =IF(ISBLANK(H43),"",IF(H43="ALI",IF(M43="L",7,IF(M43="A",10,15)),IF(H43="AIE",IF(M43="L",5,IF(M43="A",7,10)),IF(H43="SE",IF(M43="L",4,IF(M43="A",5,7)),IF(OR(H43="EE",H43="CE"),IF(M43="L",3,IF(M43="A",4,6))))))) | P43: =IF(I43="I",O43*Contagem!$W$15,IF(I43="E",O43*Contagem!$W$17,IF(I43="A",O43*Contagem!$W$16,IF(I43="T",O43*Contagem!$W$18,""))))
A44: =IF(H44="",IF(C44="",A43,A43+1),A43) | B44: =IF(A44=A43,"",CONCATENATE("F",A44)) | C44: Usuários e solicitações de acesso | L44: =CONCATENATE(H44,M44) | M44: =IF(OR(ISBLANK(J44),ISBLANK(K44)),IF(OR(H44="ALI",H44="AIE"),"L",IF(ISBLANK(H44),"","A")),IF(H44="EE",IF(K44>=3,IF(J44>=5,"H","A"),IF(K44>=2,IF(J44>=16,"H",IF(J44<=4,"L","A")),IF(J44<=15,"L","A"))),IF(OR(H44="SE",H44="CE"),IF(K44>=4,IF(J44>=6,"H","A"),IF(K44>=2,IF(J44>=20,"H",IF(J44<=5,"L","A")),IF(J44<=19,"L","A"))),IF(OR(H44="ALI",H44="AIE"),IF(K44>=6,IF(J44>=20,"H","A"),IF(K44>=2,IF(J44>=51,"H",IF(J44<=19,"L","A")),IF(J44<=50,"L","A"))))))) | N44: =IF(M44="L","Baixa",IF(M44="A","Média",IF(M44="","","Alta"))) | O44: =IF(ISBLANK(H44),"",IF(H44="ALI",IF(M44="L",7,IF(M44="A",10,15)),IF(H44="AIE",IF(M44="L",5,IF(M44="A",7,10)),IF(H44="SE",IF(M44="L",4,IF(M44="A",5,7)),IF(OR(H44="EE",H44="CE"),IF(M44="L",3,IF(M44="A",4,6))))))) | P44: =IF(I44="I",O44*Contagem!$W$15,IF(I44="E",O44*Contagem!$W$17,IF(I44="A",O44*Contagem!$W$16,IF(I44="T",O44*Contagem!$W$18,""))))
A45: =IF(H45="",IF(C45="",A44,A44+1),A44) | B45: =IF(A45=A44,"",CONCATENATE("F",A45)) | C45: Dados - Usuário | H45: ALI | I45: I | J45: 26 | K45: 4 | L45: =CONCATENATE(H45,M45) | M45: =IF(OR(ISBLANK(J45),ISBLANK(K45)),IF(OR(H45="ALI",H45="AIE"),"L",IF(ISBLANK(H45),"","A")),IF(H45="EE",IF(K45>=3,IF(J45>=5,"H","A"),IF(K45>=2,IF(J45>=16,"H",IF(J45<=4,"L","A")),IF(J45<=15,"L","A"))),IF(OR(H45="SE",H45="CE"),IF(K45>=4,IF(J45>=6,"H","A"),IF(K45>=2,IF(J45>=20,"H",IF(J45<=5,"L","A")),IF(J45<=19,"L","A"))),IF(OR(H45="ALI",H45="AIE"),IF(K45>=6,IF(J45>=20,"H","A"),IF(K45>=2,IF(J45>=51,"H",IF(J45<=19,"L","A")),IF(J45<=50,"L","A"))))))) | N45: =IF(M45="L","Baixa",IF(M45="A","Média",IF(M45="","","Alta"))) | O45: =IF(ISBLANK(H45),"",IF(H45="ALI",IF(M45="L",7,IF(M45="A",10,15)),IF(H45="AIE",IF(M45="L",5,IF(M45="A",7,10)),IF(H45="SE",IF(M45="L",4,IF(M45="A",5,7)),IF(OR(H45="EE",H45="CE"),IF(M45="L",3,IF(M45="A",4,6))))))) | P45: =IF(I45="I",O45*Contagem!$W$15,IF(I45="E",O45*Contagem!$W$17,IF(I45="A",O45*Contagem!$W$16,IF(I45="T",O45*Contagem!$W$18,"")))) | Q45: Prova: Model app/Models/User.php; migrations 0001_01_01_000000_create_users_table, 2026_06_09_234617_add_two_factor_columns_to_users_table, 2026_06_10_020811_add_cpf_and_phone_to_users_table, 2026_06_10_141715_add_inactivated_at_to_users_table, 2026_09_24_183700_add_auth_columns_to_users_table, 2026_06_12_151920_create_gov_br_accounts_table, 2026_10_14_173252_create_access_requests_table (Model AccessRequest) e 2026_06_10_022241_create_legal_term_acceptances_table (Model LegalTermAcceptance). Mantido por autocadastro, perfil, login gov.br e AD, gestão de usuários, solicitação de acesso e aceite do termo LGPD. Teste: tests/Feature/Users/SolicitacaoAcessoTest.php::test_administrador_aprova_com_outro_perfil. Arquivo lógico: a conta de acesso com dados pessoais, perfil, forma de autenticação, pedidos de acesso e consentimentos. Teste de independência: a solicitação de acesso (user_id com cascadeOnDelete, várias por conta após recusa) e o aceite de termo (associativa usuário x termo, cascadeOnDelete, com IP, navegador e data) só existem com a conta e têm atributos não-chave: são RLR de Usuário, não ALI separados (Parte 1 §5.4.2; Parte 3 Cap. 2). O vínculo gov.br é subtipo opcional da conta com atributos próprios. O histórico de lotação (user_sector_assignments) é controle interno de vigência gravado no login AD e não é exibido em nenhuma tela: não é reconhecido pelo usuário e não conta. TD=26 (nome, e-mail, CPF, telefone, senha, e-mail verificado em, autenticação em dois fatores, forma de autenticação, usuário AD, inativado em, perfil de acesso, setores, nível de confiabilidade gov.br, vinculado ao gov.br em, última autenticação gov.br, perfil solicitado, justificativa da solicitação, situação da solicitação, solicitada em, decidida por, decidida em, motivo da recusa, termo aceito (tipo e versão), IP do aceite, navegador do aceite, aceito em). TR=4 (conta, vínculo gov.br, solicitação de acesso, aceite de termo legal). Recontagem 16/10/2026: alterada (linha 505 da contagem de 01/10/2026: "Dados - Usuário", ALI Baixa 7 PF, TD 15, AR 2). Motivo: TD 15→26 e TR 2→4: entram os subgrupos Solicitação de acesso (access_requests, criada em 14/10/2026) e Aceite de termo legal (antes ALI próprio, linha 502), ambos dependentes da conta e com atributos não-chave. PF 7→10 (ALI Média).
A46: =IF(H46="",IF(C46="",A45,A45+1),A45) | B46: =IF(A46=A45,"",CONCATENATE("F",A46)) | C46: Usuários - consultar | H46: SE | I46: I | J46: 11 | K46: 2 | L46: =CONCATENATE(H46,M46) | M46: =IF(OR(ISBLANK(J46),ISBLANK(K46)),IF(OR(H46="ALI",H46="AIE"),"L",IF(ISBLANK(H46),"","A")),IF(H46="EE",IF(K46>=3,IF(J46>=5,"H","A"),IF(K46>=2,IF(J46>=16,"H",IF(J46<=4,"L","A")),IF(J46<=15,"L","A"))),IF(OR(H46="SE",H46="CE"),IF(K46>=4,IF(J46>=6,"H","A"),IF(K46>=2,IF(J46>=20,"H",IF(J46<=5,"L","A")),IF(J46<=19,"L","A"))),IF(OR(H46="ALI",H46="AIE"),IF(K46>=6,IF(J46>=20,"H","A"),IF(K46>=2,IF(J46>=51,"H",IF(J46<=19,"L","A")),IF(J46<=50,"L","A"))))))) | N46: =IF(M46="L","Baixa",IF(M46="A","Média",IF(M46="","","Alta"))) | O46: =IF(ISBLANK(H46),"",IF(H46="ALI",IF(M46="L",7,IF(M46="A",10,15)),IF(H46="AIE",IF(M46="L",5,IF(M46="A",7,10)),IF(H46="SE",IF(M46="L",4,IF(M46="A",5,7)),IF(OR(H46="EE",H46="CE"),IF(M46="L",3,IF(M46="A",4,6))))))) | P46: =IF(I46="I",O46*Contagem!$W$15,IF(I46="E",O46*Contagem!$W$17,IF(I46="A",O46*Contagem!$W$16,IF(I46="T",O46*Contagem!$W$18,"")))) | Q46: Prova: Rota GET /gestao/usuarios (permissão manter-usuarios). Tela: gestao/usuarios/index. O gestor busca por nome ou e-mail e alterna as abas equipe SEDUR e portal. Lê Usuário e Perfil de acesso (escopos equipeSedur e usuarioPortal pela permissão acessar-gestao; conta AD sempre na equipe); não grava. A exportação (?formato=csv/xlsx/pdf, ReportExporter) não tem botão nesta tela (a página não usa ExportMenu; só é alcançável digitando a URL) e não é contada como função; a consulta da tela não grava Trilha de auditoria (o log só ocorre no ramo ?formato=), por isso continua sem FTR de registro. Teste: tests/Feature/Users/ManageUsersTest.php::test_conta_ad_sem_papel_conta_como_equipe_sedur_e_nunca_como_portal. Processo elementar independente: menor unidade com significado para o gestor; completa por si (do filtro à lista); deixa o negócio consistente (nada muda); lógica única (separa equipe e portal, mascara CPF e totaliza por aba). A lista de solicitações pendentes da mesma tela é processo distinto (outros DER e outra lógica). Classificação: mostra dado derivado (total por aba, CPF mascarado): SE, não CE (§5.5.3). TD=11 (busca por nome ou e-mail, aba, nome, e-mail, perfil, inativado em, CPF mascarado, forma de autenticação, usuário AD, total por aba, ação de consultar). AR=2 (Usuário, Perfil de acesso). Recontagem 16/10/2026: alterada (linha 218 da contagem de 01/10/2026: "Usuários - consultar", SE Baixa 4 PF, TD 10, AR 1). Motivo: TD 10→11: +1 DER de ação. AR 1→2: a separação das abas lê as permissões do perfil (acessar-gestao), agora no ALI Perfil de acesso. PF 4→5 (SE Média).
A47: =IF(H47="",IF(C47="",A46,A46+1),A46) | B47: =IF(A47=A46,"",CONCATENATE("F",A47)) | C47: Usuários - ativar ou inativar | H47: EE | I47: I | J47: 4 | K47: 2 | L47: =CONCATENATE(H47,M47) | M47: =IF(OR(ISBLANK(J47),ISBLANK(K47)),IF(OR(H47="ALI",H47="AIE"),"L",IF(ISBLANK(H47),"","A")),IF(H47="EE",IF(K47>=3,IF(J47>=5,"H","A"),IF(K47>=2,IF(J47>=16,"H",IF(J47<=4,"L","A")),IF(J47<=15,"L","A"))),IF(OR(H47="SE",H47="CE"),IF(K47>=4,IF(J47>=6,"H","A"),IF(K47>=2,IF(J47>=20,"H",IF(J47<=5,"L","A")),IF(J47<=19,"L","A"))),IF(OR(H47="ALI",H47="AIE"),IF(K47>=6,IF(J47>=20,"H","A"),IF(K47>=2,IF(J47>=51,"H",IF(J47<=19,"L","A")),IF(J47<=50,"L","A"))))))) | N47: =IF(M47="L","Baixa",IF(M47="A","Média",IF(M47="","","Alta"))) | O47: =IF(ISBLANK(H47),"",IF(H47="ALI",IF(M47="L",7,IF(M47="A",10,15)),IF(H47="AIE",IF(M47="L",5,IF(M47="A",7,10)),IF(H47="SE",IF(M47="L",4,IF(M47="A",5,7)),IF(OR(H47="EE",H47="CE"),IF(M47="L",3,IF(M47="A",4,6))))))) | P47: =IF(I47="I",O47*Contagem!$W$15,IF(I47="E",O47*Contagem!$W$17,IF(I47="A",O47*Contagem!$W$16,IF(I47="T",O47*Contagem!$W$18,"")))) | Q47: Prova: Rota PUT /gestao/usuarios/{user}/inativacao (permissão manter-usuarios). Tela: gestao/usuarios/index. O gestor ativa ou inativa a conta. Grava inactivated_at em Usuário e a trilha de auditoria (dado pessoal). Resultado: conta inativa não entra mais. Teste: tests/Feature/Users/ManageUsersTest.php::test_inativacao_pela_interface_bloqueia_o_login_de_verdade. Processo elementar independente: menor unidade com significado para o gestor; completa por si (do clique à conta alterada); deixa o negócio consistente (conta ativa ou inativa, auditada); lógica única (alterna a situação e impede a autoinativação). TD=4 (usuário, situação da conta, mensagem, ação). AR=2 (Usuário, Trilha de auditoria). Registros automáticos contados como FTR (premissa P4): Trilha de auditoria. Recontagem 16/10/2026: mantida (linha 219 da contagem de 01/10/2026).
A48: =IF(H48="",IF(C48="",A47,A47+1),A47) | B48: =IF(A48=A47,"",CONCATENATE("F",A48)) | C48: Usuários - alterar perfil de acesso | H48: EE | I48: I | J48: 4 | K48: 3 | L48: =CONCATENATE(H48,M48) | M48: =IF(OR(ISBLANK(J48),ISBLANK(K48)),IF(OR(H48="ALI",H48="AIE"),"L",IF(ISBLANK(H48),"","A")),IF(H48="EE",IF(K48>=3,IF(J48>=5,"H","A"),IF(K48>=2,IF(J48>=16,"H",IF(J48<=4,"L","A")),IF(J48<=15,"L","A"))),IF(OR(H48="SE",H48="CE"),IF(K48>=4,IF(J48>=6,"H","A"),IF(K48>=2,IF(J48>=20,"H",IF(J48<=5,"L","A")),IF(J48<=19,"L","A"))),IF(OR(H48="ALI",H48="AIE"),IF(K48>=6,IF(J48>=20,"H","A"),IF(K48>=2,IF(J48>=51,"H",IF(J48<=19,"L","A")),IF(J48<=50,"L","A"))))))) | N48: =IF(M48="L","Baixa",IF(M48="A","Média",IF(M48="","","Alta"))) | O48: =IF(ISBLANK(H48),"",IF(H48="ALI",IF(M48="L",7,IF(M48="A",10,15)),IF(H48="AIE",IF(M48="L",5,IF(M48="A",7,10)),IF(H48="SE",IF(M48="L",4,IF(M48="A",5,7)),IF(OR(H48="EE",H48="CE"),IF(M48="L",3,IF(M48="A",4,6))))))) | P48: =IF(I48="I",O48*Contagem!$W$15,IF(I48="E",O48*Contagem!$W$17,IF(I48="A",O48*Contagem!$W$16,IF(I48="T",O48*Contagem!$W$18,"")))) | Q48: Prova: Rota PUT /gestao/usuarios/{user}/papel (permissão manter-usuarios). Tela: gestao/usuarios/index. O gestor escolhe o perfil; UpdateUserRoleRequest valida que o perfil existe. Lê Perfil de acesso; grava o perfil da conta em Usuário (syncRoles) e a Trilha de auditoria com o perfil anterior e o novo. Resultado: as permissões da conta mudam. Teste: tests/Feature/Users/ManageUsersTest.php::test_altera_papel_do_usuario_com_auditoria. Processo elementar independente: menor unidade com significado para o gestor; completa por si (escolha do perfil até a gravação); deixa o negócio consistente (um perfil por conta, auditado); lógica única (substitui o perfil e registra anterior e novo). Classificação: mantém ALI, EE. TD=4 (usuário, perfil de acesso, mensagem, ação). AR=3 (Usuário, Perfil de acesso, Trilha de auditoria). Registros automáticos contados como FTR (premissa P4): Trilha de auditoria. Recontagem 16/10/2026: alterada (linha 220 da contagem de 01/10/2026: "Usuários - alterar perfil de acesso", EE Baixa 3 PF, TD 4, AR 2). Motivo: AR 2→3: o perfil escolhido é validado contra o ALI Perfil de acesso (antes embutido em Usuário). PF 3→4 (EE Média).
A49: =IF(H49="",IF(C49="",A48,A48+1),A48) | B49: =IF(A49=A48,"",CONCATENATE("F",A49)) | C49: Usuários - alterar forma de autenticação | H49: EE | I49: I | J49: 5 | K49: 3 | L49: =CONCATENATE(H49,M49) | M49: =IF(OR(ISBLANK(J49),ISBLANK(K49)),IF(OR(H49="ALI",H49="AIE"),"L",IF(ISBLANK(H49),"","A")),IF(H49="EE",IF(K49>=3,IF(J49>=5,"H","A"),IF(K49>=2,IF(J49>=16,"H",IF(J49<=4,"L","A")),IF(J49<=15,"L","A"))),IF(OR(H49="SE",H49="CE"),IF(K49>=4,IF(J49>=6,"H","A"),IF(K49>=2,IF(J49>=20,"H",IF(J49<=5,"L","A")),IF(J49<=19,"L","A"))),IF(OR(H49="ALI",H49="AIE"),IF(K49>=6,IF(J49>=20,"H","A"),IF(K49>=2,IF(J49>=51,"H",IF(J49<=19,"L","A")),IF(J49<=50,"L","A"))))))) | N49: =IF(M49="L","Baixa",IF(M49="A","Média",IF(M49="","","Alta"))) | O49: =IF(ISBLANK(H49),"",IF(H49="ALI",IF(M49="L",7,IF(M49="A",10,15)),IF(H49="AIE",IF(M49="L",5,IF(M49="A",7,10)),IF(H49="SE",IF(M49="L",4,IF(M49="A",5,7)),IF(OR(H49="EE",H49="CE"),IF(M49="L",3,IF(M49="A",4,6))))))) | P49: =IF(I49="I",O49*Contagem!$W$15,IF(I49="E",O49*Contagem!$W$17,IF(I49="A",O49*Contagem!$W$16,IF(I49="T",O49*Contagem!$W$18,"")))) | Q49: Prova: Rota PUT /gestao/usuarios/{user}/autenticacao (permissão manter-usuarios). Tela: gestao/usuarios/index. O gestor define AD ou local. Grava auth_type e ad_username em Usuário e invalida a senha anterior; se a conta passa de AD para local, gera o link de nova senha e grava o Registro de envio de e-mail; grava Trilha de auditoria. O envio em si é efeito automático e não é função à parte. Teste: tests/Feature/Gestao/UserAuthTypeTest.php::test_conversao_para_local_envia_link_para_definir_nova_senha. Processo elementar independente: menor unidade com significado para o gestor; completa por si (do formulário à conta convertida); deixa o negócio consistente (credencial anterior inutilizada); lógica única (troca o mecanismo de autenticação). Classificação: mantém ALI, EE. TD=5 (usuário, forma de autenticação, usuário AD, mensagem, ação). AR=3 (Usuário, Registro de envio de e-mail, Trilha de auditoria). Registros automáticos contados como FTR (premissa P4): Registro de envio de e-mail, Trilha de auditoria. Recontagem 16/10/2026: alterada (linha 221 da contagem de 01/10/2026: "Usuários - alterar forma de autenticação", EE Média 4 PF, TD 5, AR 2). Motivo: AR 2→3: ao converter conta AD em local, o processo grava o Registro de envio de e-mail do link de nova senha (User::sendGestaoPasswordResetNotification cria EmailLog). PF 4→6 (EE Alta).
A50: =IF(H50="",IF(C50="",A49,A49+1),A49) | B50: =IF(A50=A49,"",CONCATENATE("F",A50)) | C50: Solicitação de acesso - solicitar perfil | H50: EE | I50: I | J50: 4 | K50: 3 | L50: =CONCATENATE(H50,M50) | M50: =IF(OR(ISBLANK(J50),ISBLANK(K50)),IF(OR(H50="ALI",H50="AIE"),"L",IF(ISBLANK(H50),"","A")),IF(H50="EE",IF(K50>=3,IF(J50>=5,"H","A"),IF(K50>=2,IF(J50>=16,"H",IF(J50<=4,"L","A")),IF(J50<=15,"L","A"))),IF(OR(H50="SE",H50="CE"),IF(K50>=4,IF(J50>=6,"H","A"),IF(K50>=2,IF(J50>=20,"H",IF(J50<=5,"L","A")),IF(J50<=19,"L","A"))),IF(OR(H50="ALI",H50="AIE"),IF(K50>=6,IF(J50>=20,"H","A"),IF(K50>=2,IF(J50>=51,"H",IF(J50<=19,"L","A")),IF(J50<=50,"L","A"))))))) | N50: =IF(M50="L","Baixa",IF(M50="A","Média",IF(M50="","","Alta"))) | O50: =IF(ISBLANK(H50),"",IF(H50="ALI",IF(M50="L",7,IF(M50="A",10,15)),IF(H50="AIE",IF(M50="L",5,IF(M50="A",7,10)),IF(H50="SE",IF(M50="L",4,IF(M50="A",5,7)),IF(OR(H50="EE",H50="CE"),IF(M50="L",3,IF(M50="A",4,6))))))) | P50: =IF(I50="I",O50*Contagem!$W$15,IF(I50="E",O50*Contagem!$W$17,IF(I50="A",O50*Contagem!$W$16,IF(I50="T",O50*Contagem!$W$18,"")))) | Q50: Prova: Rota POST /gestao/solicitacao-acesso (auth:gestao, servidor sem perfil). Tela: gestao/dashboard (bloco de primeiro acesso). O servidor que entrou pelo AD sem perfil escolhe um perfil solicitável e escreve a justificativa (StoreAccessRequestRequest: perfil na lista de PerfisSolicitaveis, justificativa de 10 a 500 caracteres). Lê Usuário (já tem perfil? já há pedido pendente?) e Perfil de acesso; grava a solicitação (subgrupo de Usuário) com situação pendente e a Trilha de auditoria. Teste: tests/Feature/Users/SolicitacaoAcessoTest.php::test_servidor_solicita_um_perfil e ::test_segunda_solicitacao_pendente_e_barrada. Processo elementar independente: menor unidade com significado para o servidor; completa por si (formulário até o pedido registrado); deixa o negócio consistente (um pedido pendente por conta); lógica única (criação do pedido, distinta da decisão do administrador). Classificação: intenção primária é manter Usuário (subgrupo solicitação), EE (§5.5.3). TD=4 (perfil solicitado, justificativa, mensagem, ação enviar). AR=3 (Usuário, Perfil de acesso, Trilha de auditoria). Registros automáticos contados como FTR (premissa P4): Trilha de auditoria. Recontagem 16/10/2026: nova (não constava da contagem de 01/10/2026).
A51: =IF(H51="",IF(C51="",A50,A50+1),A50) | B51: =IF(A51=A50,"",CONCATENATE("F",A51)) | C51: Solicitação de acesso - consultar situação do pedido | H51: CE | I51: I | J51: 6 | K51: 2 | L51: =CONCATENATE(H51,M51) | M51: =IF(OR(ISBLANK(J51),ISBLANK(K51)),IF(OR(H51="ALI",H51="AIE"),"L",IF(ISBLANK(H51),"","A")),IF(H51="EE",IF(K51>=3,IF(J51>=5,"H","A"),IF(K51>=2,IF(J51>=16,"H",IF(J51<=4,"L","A")),IF(J51<=15,"L","A"))),IF(OR(H51="SE",H51="CE"),IF(K51>=4,IF(J51>=6,"H","A"),IF(K51>=2,IF(J51>=20,"H",IF(J51<=5,"L","A")),IF(J51<=19,"L","A"))),IF(OR(H51="ALI",H51="AIE"),IF(K51>=6,IF(J51>=20,"H","A"),IF(K51>=2,IF(J51>=51,"H",IF(J51<=19,"L","A")),IF(J51<=50,"L","A"))))))) | N51: =IF(M51="L","Baixa",IF(M51="A","Média",IF(M51="","","Alta"))) | O51: =IF(ISBLANK(H51),"",IF(H51="ALI",IF(M51="L",7,IF(M51="A",10,15)),IF(H51="AIE",IF(M51="L",5,IF(M51="A",7,10)),IF(H51="SE",IF(M51="L",4,IF(M51="A",5,7)),IF(OR(H51="EE",H51="CE"),IF(M51="L",3,IF(M51="A",4,6))))))) | P51: =IF(I51="I",O51*Contagem!$W$15,IF(I51="E",O51*Contagem!$W$17,IF(I51="A",O51*Contagem!$W$16,IF(I51="T",O51*Contagem!$W$18,"")))) | Q51: Prova: Rota GET /gestao (DashboardController::acessoPendente, só para servidor sem perfil). Tela: gestao/dashboard. O servidor vê os perfis que pode pedir e o estado do último pedido: pendente, ou recusado com o motivo, podendo pedir de novo. Lê Usuário (último pedido) e Perfil de acesso; não grava. Teste: tests/Feature/Users/SolicitacaoAcessoTest.php::test_painel_mostra_a_recusa_e_permite_pedir_de_novo. Processo elementar independente: menor unidade com significado para o servidor; completa por si (abre o painel e recebe o estado do pedido); deixa o negócio consistente (nada muda); lógica única (último pedido da própria conta), distinta dos indicadores do painel, que não aparecem para conta sem perfil. Classificação: recuperação sem cálculo nem derivação, CE (§5.5.3). TD=6 (perfis solicitáveis, situação da solicitação, perfil solicitado, justificativa, motivo da recusa, ação de abrir o painel). AR=2 (Usuário, Perfil de acesso). Recontagem 16/10/2026: nova (não constava da contagem de 01/10/2026).
A52: =IF(H52="",IF(C52="",A51,A51+1),A51) | B52: =IF(A52=A51,"",CONCATENATE("F",A52)) | C52: Solicitações de acesso - consultar pendentes | H52: CE | I52: I | J52: 7 | K52: 2 | L52: =CONCATENATE(H52,M52) | M52: =IF(OR(ISBLANK(J52),ISBLANK(K52)),IF(OR(H52="ALI",H52="AIE"),"L",IF(ISBLANK(H52),"","A")),IF(H52="EE",IF(K52>=3,IF(J52>=5,"H","A"),IF(K52>=2,IF(J52>=16,"H",IF(J52<=4,"L","A")),IF(J52<=15,"L","A"))),IF(OR(H52="SE",H52="CE"),IF(K52>=4,IF(J52>=6,"H","A"),IF(K52>=2,IF(J52>=20,"H",IF(J52<=5,"L","A")),IF(J52<=19,"L","A"))),IF(OR(H52="ALI",H52="AIE"),IF(K52>=6,IF(J52>=20,"H","A"),IF(K52>=2,IF(J52>=51,"H",IF(J52<=19,"L","A")),IF(J52<=50,"L","A"))))))) | N52: =IF(M52="L","Baixa",IF(M52="A","Média",IF(M52="","","Alta"))) | O52: =IF(ISBLANK(H52),"",IF(H52="ALI",IF(M52="L",7,IF(M52="A",10,15)),IF(H52="AIE",IF(M52="L",5,IF(M52="A",7,10)),IF(H52="SE",IF(M52="L",4,IF(M52="A",5,7)),IF(OR(H52="EE",H52="CE"),IF(M52="L",3,IF(M52="A",4,6))))))) | P52: =IF(I52="I",O52*Contagem!$W$15,IF(I52="E",O52*Contagem!$W$17,IF(I52="A",O52*Contagem!$W$16,IF(I52="T",O52*Contagem!$W$18,"")))) | Q52: Prova: Rota GET /gestao/usuarios (permissão manter-usuarios), prop solicitacoes de UserManagementController@index. Tela: gestao/usuarios/index (quadro de solicitações pendentes). O administrador vê os pedidos pendentes, do mais antigo ao mais novo, com quem pediu, o perfil e a justificativa. Lê Usuário (solicitações pendentes e dados do servidor) e Perfil de acesso; não grava. Teste: tests/Feature/Users/SolicitacaoAcessoTest.php::test_administrador_ve_as_solicitacoes_pendentes_em_usuarios. Processo elementar independente: menor unidade com significado para o administrador (fila de pedidos a decidir); completa por si; deixa o negócio consistente (nada muda); lógica única (só pendentes, sem aba nem busca), com DER diferentes da lista de usuários, por isso não se confunde com Usuários - consultar (§5.5.2.2). Classificação: recuperação sem cálculo, CE (§5.5.3). TD=7 (nome, e-mail, usuário AD, perfil solicitado, justificativa, data da solicitação, ação de consultar). AR=2 (Usuário, Perfil de acesso). Recontagem 16/10/2026: nova (não constava da contagem de 01/10/2026).
A53: =IF(H53="",IF(C53="",A52,A52+1),A52) | B53: =IF(A53=A52,"",CONCATENATE("F",A53)) | C53: Solicitações de acesso - aprovar | H53: EE | I53: I | J53: 4 | K53: 3 | L53: =CONCATENATE(H53,M53) | M53: =IF(OR(ISBLANK(J53),ISBLANK(K53)),IF(OR(H53="ALI",H53="AIE"),"L",IF(ISBLANK(H53),"","A")),IF(H53="EE",IF(K53>=3,IF(J53>=5,"H","A"),IF(K53>=2,IF(J53>=16,"H",IF(J53<=4,"L","A")),IF(J53<=15,"L","A"))),IF(OR(H53="SE",H53="CE"),IF(K53>=4,IF(J53>=6,"H","A"),IF(K53>=2,IF(J53>=20,"H",IF(J53<=5,"L","A")),IF(J53<=19,"L","A"))),IF(OR(H53="ALI",H53="AIE"),IF(K53>=6,IF(J53>=20,"H","A"),IF(K53>=2,IF(J53>=51,"H",IF(J53<=19,"L","A")),IF(J53<=50,"L","A"))))))) | N53: =IF(M53="L","Baixa",IF(M53="A","Média",IF(M53="","","Alta"))) | O53: =IF(ISBLANK(H53),"",IF(H53="ALI",IF(M53="L",7,IF(M53="A",10,15)),IF(H53="AIE",IF(M53="L",5,IF(M53="A",7,10)),IF(H53="SE",IF(M53="L",4,IF(M53="A",5,7)),IF(OR(H53="EE",H53="CE"),IF(M53="L",3,IF(M53="A",4,6))))))) | P53: =IF(I53="I",O53*Contagem!$W$15,IF(I53="E",O53*Contagem!$W$17,IF(I53="A",O53*Contagem!$W$16,IF(I53="T",O53*Contagem!$W$18,"")))) | Q53: Prova: Rota PUT /gestao/usuarios/solicitacoes/{accessRequest}/aprovar (permissão manter-usuarios). Tela: gestao/usuarios/index. O administrador aprova com o perfil pedido ou outro (UpdateUserRoleRequest). Recusa pedido já decidido. Em transação, atribui o perfil à conta (syncRoles) e grava a solicitação como aprovada com quem decidiu e quando; grava Trilha de auditoria com perfil solicitado e concedido. Teste: tests/Feature/Users/SolicitacaoAcessoTest.php::test_administrador_aprova_com_outro_perfil e ::test_solicitacao_decidida_nao_e_decidida_de_novo. Processo elementar independente: menor unidade com significado para o administrador; completa por si (decisão até a conta liberada); deixa o negócio consistente (perfil e decisão gravados juntos). Aprovar e recusar são processos distintos: DER diferentes (perfil concedido x motivo), FTR diferentes (aprovar lê Perfil de acesso e muda o perfil da conta) e lógica diferente (§5.5.2.2). Classificação: mantém Usuário, EE. TD=4 (solicitação (servidor), perfil concedido, mensagem, ação aprovar). AR=3 (Usuário, Perfil de acesso, Trilha de auditoria). Registros automáticos contados como FTR (premissa P4): Trilha de auditoria. Recontagem 16/10/2026: nova (não constava da contagem de 01/10/2026).
A54: =IF(H54="",IF(C54="",A53,A53+1),A53) | B54: =IF(A54=A53,"",CONCATENATE("F",A54)) | C54: Solicitações de acesso - recusar | H54: EE | I54: I | J54: 4 | K54: 2 | L54: =CONCATENATE(H54,M54) | M54: =IF(OR(ISBLANK(J54),ISBLANK(K54)),IF(OR(H54="ALI",H54="AIE"),"L",IF(ISBLANK(H54),"","A")),IF(H54="EE",IF(K54>=3,IF(J54>=5,"H","A"),IF(K54>=2,IF(J54>=16,"H",IF(J54<=4,"L","A")),IF(J54<=15,"L","A"))),IF(OR(H54="SE",H54="CE"),IF(K54>=4,IF(J54>=6,"H","A"),IF(K54>=2,IF(J54>=20,"H",IF(J54<=5,"L","A")),IF(J54<=19,"L","A"))),IF(OR(H54="ALI",H54="AIE"),IF(K54>=6,IF(J54>=20,"H","A"),IF(K54>=2,IF(J54>=51,"H",IF(J54<=19,"L","A")),IF(J54<=50,"L","A"))))))) | N54: =IF(M54="L","Baixa",IF(M54="A","Média",IF(M54="","","Alta"))) | O54: =IF(ISBLANK(H54),"",IF(H54="ALI",IF(M54="L",7,IF(M54="A",10,15)),IF(H54="AIE",IF(M54="L",5,IF(M54="A",7,10)),IF(H54="SE",IF(M54="L",4,IF(M54="A",5,7)),IF(OR(H54="EE",H54="CE"),IF(M54="L",3,IF(M54="A",4,6))))))) | P54: =IF(I54="I",O54*Contagem!$W$15,IF(I54="E",O54*Contagem!$W$17,IF(I54="A",O54*Contagem!$W$16,IF(I54="T",O54*Contagem!$W$18,"")))) | Q54: Prova: Rota PUT /gestao/usuarios/solicitacoes/{accessRequest}/recusar (permissão manter-usuarios). Tela: gestao/usuarios/index. O administrador recusa informando o motivo obrigatório (RejectAccessRequestRequest, até 300 caracteres). Recusa pedido já decidido. Grava a solicitação como recusada com quem decidiu, quando e o motivo, que aparece ao servidor no painel; grava Trilha de auditoria. A conta continua sem perfil. Teste: tests/Feature/Users/SolicitacaoAcessoTest.php::test_administrador_recusa_com_motivo_obrigatorio. Processo elementar independente: menor unidade com significado para o administrador; completa por si (motivo até o pedido encerrado); deixa o negócio consistente (pedido decidido uma vez só); lógica única (recusa sem alterar o perfil, distinta da aprovação). Classificação: mantém Usuário, EE. TD=4 (solicitação (servidor), motivo da recusa, mensagem, ação recusar). AR=2 (Usuário, Trilha de auditoria). Registros automáticos contados como FTR (premissa P4): Trilha de auditoria. Recontagem 16/10/2026: nova (não constava da contagem de 01/10/2026).
A55: =IF(H55="",IF(C55="",A54,A54+1),A54) | B55: =IF(A55=A54,"",CONCATENATE("F",A55)) | L55: =CONCATENATE(H55,M55) | M55: =IF(OR(ISBLANK(J55),ISBLANK(K55)),IF(OR(H55="ALI",H55="AIE"),"L",IF(ISBLANK(H55),"","A")),IF(H55="EE",IF(K55>=3,IF(J55>=5,"H","A"),IF(K55>=2,IF(J55>=16,"H",IF(J55<=4,"L","A")),IF(J55<=15,"L","A"))),IF(OR(H55="SE",H55="CE"),IF(K55>=4,IF(J55>=6,"H","A"),IF(K55>=2,IF(J55>=20,"H",IF(J55<=5,"L","A")),IF(J55<=19,"L","A"))),IF(OR(H55="ALI",H55="AIE"),IF(K55>=6,IF(J55>=20,"H","A"),IF(K55>=2,IF(J55>=51,"H",IF(J55<=19,"L","A")),IF(J55<=50,"L","A"))))))) | N55: =IF(M55="L","Baixa",IF(M55="A","Média",IF(M55="","","Alta"))) | O55: =IF(ISBLANK(H55),"",IF(H55="ALI",IF(M55="L",7,IF(M55="A",10,15)),IF(H55="AIE",IF(M55="L",5,IF(M55="A",7,10)),IF(H55="SE",IF(M55="L",4,IF(M55="A",5,7)),IF(OR(H55="EE",H55="CE"),IF(M55="L",3,IF(M55="A",4,6))))))) | P55: =IF(I55="I",O55*Contagem!$W$15,IF(I55="E",O55*Contagem!$W$17,IF(I55="A",O55*Contagem!$W$16,IF(I55="T",O55*Contagem!$W$18,""))))
A56: =IF(H56="",IF(C56="",A55,A55+1),A55) | B56: =IF(A56=A55,"",CONCATENATE("F",A56)) | C56: Feriados | L56: =CONCATENATE(H56,M56) | M56: =IF(OR(ISBLANK(J56),ISBLANK(K56)),IF(OR(H56="ALI",H56="AIE"),"L",IF(ISBLANK(H56),"","A")),IF(H56="EE",IF(K56>=3,IF(J56>=5,"H","A"),IF(K56>=2,IF(J56>=16,"H",IF(J56<=4,"L","A")),IF(J56<=15,"L","A"))),IF(OR(H56="SE",H56="CE"),IF(K56>=4,IF(J56>=6,"H","A"),IF(K56>=2,IF(J56>=20,"H",IF(J56<=5,"L","A")),IF(J56<=19,"L","A"))),IF(OR(H56="ALI",H56="AIE"),IF(K56>=6,IF(J56>=20,"H","A"),IF(K56>=2,IF(J56>=51,"H",IF(J56<=19,"L","A")),IF(J56<=50,"L","A"))))))) | N56: =IF(M56="L","Baixa",IF(M56="A","Média",IF(M56="","","Alta"))) | O56: =IF(ISBLANK(H56),"",IF(H56="ALI",IF(M56="L",7,IF(M56="A",10,15)),IF(H56="AIE",IF(M56="L",5,IF(M56="A",7,10)),IF(H56="SE",IF(M56="L",4,IF(M56="A",5,7)),IF(OR(H56="EE",H56="CE"),IF(M56="L",3,IF(M56="A",4,6))))))) | P56: =IF(I56="I",O56*Contagem!$W$15,IF(I56="E",O56*Contagem!$W$17,IF(I56="A",O56*Contagem!$W$16,IF(I56="T",O56*Contagem!$W$18,""))))
A57: =IF(H57="",IF(C57="",A56,A56+1),A56) | B57: =IF(A57=A56,"",CONCATENATE("F",A57)) | C57: Dados - Feriado | H57: ALI | I57: I | J57: 4 | K57: 1 | L57: =CONCATENATE(H57,M57) | M57: =IF(OR(ISBLANK(J57),ISBLANK(K57)),IF(OR(H57="ALI",H57="AIE"),"L",IF(ISBLANK(H57),"","A")),IF(H57="EE",IF(K57>=3,IF(J57>=5,"H","A"),IF(K57>=2,IF(J57>=16,"H",IF(J57<=4,"L","A")),IF(J57<=15,"L","A"))),IF(OR(H57="SE",H57="CE"),IF(K57>=4,IF(J57>=6,"H","A"),IF(K57>=2,IF(J57>=20,"H",IF(J57<=5,"L","A")),IF(J57<=19,"L","A"))),IF(OR(H57="ALI",H57="AIE"),IF(K57>=6,IF(J57>=20,"H","A"),IF(K57>=2,IF(J57>=51,"H",IF(J57<=19,"L","A")),IF(J57<=50,"L","A"))))))) | N57: =IF(M57="L","Baixa",IF(M57="A","Média",IF(M57="","","Alta"))) | O57: =IF(ISBLANK(H57),"",IF(H57="ALI",IF(M57="L",7,IF(M57="A",10,15)),IF(H57="AIE",IF(M57="L",5,IF(M57="A",7,10)),IF(H57="SE",IF(M57="L",4,IF(M57="A",5,7)),IF(OR(H57="EE",H57="CE"),IF(M57="L",3,IF(M57="A",4,6))))))) | P57: =IF(I57="I",O57*Contagem!$W$15,IF(I57="E",O57*Contagem!$W$17,IF(I57="A",O57*Contagem!$W$16,IF(I57="T",O57*Contagem!$W$18,"")))) | Q57: Prova: Model app/Models/Holiday.php; migration database/migrations/2026_06_15_000003_create_holidays_table.php. Mantido por Feriados - incluir, alterar e ativar ou inativar (HolidayController), auditados via HasAuditoria; lido pelo BusinessDeadlineCalculator. Teste: tests/Feature/Relatorios/HolidayCadastroTest.php::test_criacao_de_feriado_e_auditada. Arquivo lógico: não é dado de código (Parte 1 §5.4.2 d; Parte 3 Cap. 1): a data não se substitui pela descrição e entra no cálculo de prazo (dado de referência). Grupo lógico reconhecido pelo gestor: calendário de feriados descontado no cálculo de prazo em dias úteis; mantido por tela própria. TD=4 (data, nome, recorrência anual, situação). TR=1 (Feriado). Regra de negócio que o tira de dado de código: todo prazo em dias úteis (pendência do requerente, SLA da análise, convite) desconta os feriados ativos deste cadastro (BusinessDeadlineCalculator); incluir ou inativar um feriado muda o vencimento dos processos. Recontagem 16/10/2026: mantida (linha 143 da contagem de 01/10/2026).
A58: =IF(H58="",IF(C58="",A57,A57+1),A57) | B58: =IF(A58=A57,"",CONCATENATE("F",A58)) | C58: Feriados - consultar | H58: CE | I58: I | J58: 6 | K58: 1 | L58: =CONCATENATE(H58,M58) | M58: =IF(OR(ISBLANK(J58),ISBLANK(K58)),IF(OR(H58="ALI",H58="AIE"),"L",IF(ISBLANK(H58),"","A")),IF(H58="EE",IF(K58>=3,IF(J58>=5,"H","A"),IF(K58>=2,IF(J58>=16,"H",IF(J58<=4,"L","A")),IF(J58<=15,"L","A"))),IF(OR(H58="SE",H58="CE"),IF(K58>=4,IF(J58>=6,"H","A"),IF(K58>=2,IF(J58>=20,"H",IF(J58<=5,"L","A")),IF(J58<=19,"L","A"))),IF(OR(H58="ALI",H58="AIE"),IF(K58>=6,IF(J58>=20,"H","A"),IF(K58>=2,IF(J58>=51,"H",IF(J58<=19,"L","A")),IF(J58<=50,"L","A"))))))) | N58: =IF(M58="L","Baixa",IF(M58="A","Média",IF(M58="","","Alta"))) | O58: =IF(ISBLANK(H58),"",IF(H58="ALI",IF(M58="L",7,IF(M58="A",10,15)),IF(H58="AIE",IF(M58="L",5,IF(M58="A",7,10)),IF(H58="SE",IF(M58="L",4,IF(M58="A",5,7)),IF(OR(H58="EE",H58="CE"),IF(M58="L",3,IF(M58="A",4,6))))))) | P58: =IF(I58="I",O58*Contagem!$W$15,IF(I58="E",O58*Contagem!$W$17,IF(I58="A",O58*Contagem!$W$16,IF(I58="T",O58*Contagem!$W$18,"")))) | Q58: Prova: Rota GET /gestao/feriados (permissão manter-parametros). Tela: gestao/feriados/index. O gestor pesquisa por nome e filtra por situação. Lê Feriado; não grava. Teste: tests/Feature/Relatorios/HolidayControllerTest.php::test_administrador_lista_feriados. Processo elementar independente: menor unidade com significado para o gestor; completa por si (filtra e recebe a lista); deixa o negócio consistente (nada é gravado); lógica única (lista ordenada por data com filtro de situação). Classificação: recuperação sem cálculo, CE (§5.5.3). TD=6 (data, nome, recorrência anual, situação, busca por nome, ação pesquisar). O filtro de situação é o mesmo campo da coluna situação e conta uma vez (DER único); ordenação e paginação não contam. AR=1 (Feriado). Recontagem 16/10/2026: alterada (linha 144 da contagem de 01/10/2026: "Feriados - consultar", CE Baixa 3 PF, TD 7, AR 1). Motivo: TD 7→6: situação e filtro de situação eram contados como dois DER. PF inalterado (CE Baixa).
A59: =IF(H59="",IF(C59="",A58,A58+1),A58) | B59: =IF(A59=A58,"",CONCATENATE("F",A59)) | C59: Feriados - incluir | H59: EE | I59: I | J59: 6 | K59: 2 | L59: =CONCATENATE(H59,M59) | M59: =IF(OR(ISBLANK(J59),ISBLANK(K59)),IF(OR(H59="ALI",H59="AIE"),"L",IF(ISBLANK(H59),"","A")),IF(H59="EE",IF(K59>=3,IF(J59>=5,"H","A"),IF(K59>=2,IF(J59>=16,"H",IF(J59<=4,"L","A")),IF(J59<=15,"L","A"))),IF(OR(H59="SE",H59="CE"),IF(K59>=4,IF(J59>=6,"H","A"),IF(K59>=2,IF(J59>=20,"H",IF(J59<=5,"L","A")),IF(J59<=19,"L","A"))),IF(OR(H59="ALI",H59="AIE"),IF(K59>=6,IF(J59>=20,"H","A"),IF(K59>=2,IF(J59>=51,"H",IF(J59<=19,"L","A")),IF(J59<=50,"L","A"))))))) | N59: =IF(M59="L","Baixa",IF(M59="A","Média",IF(M59="","","Alta"))) | O59: =IF(ISBLANK(H59),"",IF(H59="ALI",IF(M59="L",7,IF(M59="A",10,15)),IF(H59="AIE",IF(M59="L",5,IF(M59="A",7,10)),IF(H59="SE",IF(M59="L",4,IF(M59="A",5,7)),IF(OR(H59="EE",H59="CE"),IF(M59="L",3,IF(M59="A",4,6))))))) | P59: =IF(I59="I",O59*Contagem!$W$15,IF(I59="E",O59*Contagem!$W$17,IF(I59="A",O59*Contagem!$W$16,IF(I59="T",O59*Contagem!$W$18,"")))) | Q59: Prova: Rota POST /gestao/feriados (manter-parametros). Tela: gestao/feriados/index. O gestor cadastra o feriado. Valida data única; grava Feriado e Trilha de auditoria. Resultado: prazos passam a descontar a data. Teste: tests/Feature/Relatorios/HolidayControllerTest.php::test_cria_feriado_auditado. Processo elementar independente: menor unidade com significado para o gestor; completa por si (preenche e recebe confirmação); deixa o negócio consistente (sem data duplicada); lógica única (inclusão com unicidade de data). TD=6 (data, nome, recorrência anual, situação, mensagem, ação salvar). AR=2 (Feriado, Trilha de auditoria). Registros automáticos contados como FTR (premissa P4): Trilha de auditoria. Recontagem 16/10/2026: mantida (linha 145 da contagem de 01/10/2026).
A60: =IF(H60="",IF(C60="",A59,A59+1),A59) | B60: =IF(A60=A59,"",CONCATENATE("F",A60)) | C60: Feriados - alterar | H60: EE | I60: I | J60: 6 | K60: 2 | L60: =CONCATENATE(H60,M60) | M60: =IF(OR(ISBLANK(J60),ISBLANK(K60)),IF(OR(H60="ALI",H60="AIE"),"L",IF(ISBLANK(H60),"","A")),IF(H60="EE",IF(K60>=3,IF(J60>=5,"H","A"),IF(K60>=2,IF(J60>=16,"H",IF(J60<=4,"L","A")),IF(J60<=15,"L","A"))),IF(OR(H60="SE",H60="CE"),IF(K60>=4,IF(J60>=6,"H","A"),IF(K60>=2,IF(J60>=20,"H",IF(J60<=5,"L","A")),IF(J60<=19,"L","A"))),IF(OR(H60="ALI",H60="AIE"),IF(K60>=6,IF(J60>=20,"H","A"),IF(K60>=2,IF(J60>=51,"H",IF(J60<=19,"L","A")),IF(J60<=50,"L","A"))))))) | N60: =IF(M60="L","Baixa",IF(M60="A","Média",IF(M60="","","Alta"))) | O60: =IF(ISBLANK(H60),"",IF(H60="ALI",IF(M60="L",7,IF(M60="A",10,15)),IF(H60="AIE",IF(M60="L",5,IF(M60="A",7,10)),IF(H60="SE",IF(M60="L",4,IF(M60="A",5,7)),IF(OR(H60="EE",H60="CE"),IF(M60="L",3,IF(M60="A",4,6))))))) | P60: =IF(I60="I",O60*Contagem!$W$15,IF(I60="E",O60*Contagem!$W$17,IF(I60="A",O60*Contagem!$W$16,IF(I60="T",O60*Contagem!$W$18,"")))) | Q60: Prova: Rota PUT /gestao/feriados/{holiday} (manter-parametros). Tela: gestao/feriados/index. O gestor altera o feriado. Valida data única ignorando o próprio; grava Feriado e Trilha de auditoria. Resultado: calendário corrigido. Teste: tests/Feature/Relatorios/HolidayControllerTest.php::test_edita_feriado. Processo elementar independente: menor unidade com significado para o gestor; completa por si (edita e recebe confirmação); deixa o negócio consistente (sem colisão de data); lógica única (alteração do registro existente). TD=6 (data, nome, recorrência anual, situação, mensagem, ação salvar). AR=2 (Feriado, Trilha de auditoria). Registros automáticos contados como FTR (premissa P4): Trilha de auditoria. Recontagem 16/10/2026: mantida (linha 146 da contagem de 01/10/2026).
A61: =IF(H61="",IF(C61="",A60,A60+1),A60) | B61: =IF(A61=A60,"",CONCATENATE("F",A61)) | C61: Feriados - ativar ou inativar | H61: EE | I61: I | J61: 3 | K61: 2 | L61: =CONCATENATE(H61,M61) | M61: =IF(OR(ISBLANK(J61),ISBLANK(K61)),IF(OR(H61="ALI",H61="AIE"),"L",IF(ISBLANK(H61),"","A")),IF(H61="EE",IF(K61>=3,IF(J61>=5,"H","A"),IF(K61>=2,IF(J61>=16,"H",IF(J61<=4,"L","A")),IF(J61<=15,"L","A"))),IF(OR(H61="SE",H61="CE"),IF(K61>=4,IF(J61>=6,"H","A"),IF(K61>=2,IF(J61>=20,"H",IF(J61<=5,"L","A")),IF(J61<=19,"L","A"))),IF(OR(H61="ALI",H61="AIE"),IF(K61>=6,IF(J61>=20,"H","A"),IF(K61>=2,IF(J61>=51,"H",IF(J61<=19,"L","A")),IF(J61<=50,"L","A"))))))) | N61: =IF(M61="L","Baixa",IF(M61="A","Média",IF(M61="","","Alta"))) | O61: =IF(ISBLANK(H61),"",IF(H61="ALI",IF(M61="L",7,IF(M61="A",10,15)),IF(H61="AIE",IF(M61="L",5,IF(M61="A",7,10)),IF(H61="SE",IF(M61="L",4,IF(M61="A",5,7)),IF(OR(H61="EE",H61="CE"),IF(M61="L",3,IF(M61="A",4,6))))))) | P61: =IF(I61="I",O61*Contagem!$W$15,IF(I61="E",O61*Contagem!$W$17,IF(I61="A",O61*Contagem!$W$16,IF(I61="T",O61*Contagem!$W$18,"")))) | Q61: Prova: Rota PUT /gestao/feriados/{holiday}/ativacao (manter-parametros). Tela: gestao/feriados/index. O gestor ativa ou inativa. Grava a situação do Feriado e Trilha de auditoria, sem excluir. Resultado: data sai ou volta ao cálculo de dias úteis. Teste: tests/Feature/Relatorios/HolidayControllerTest.php::test_toggle_inativa_sem_excluir. Processo elementar independente: menor unidade com significado para o gestor; completa por si (um clique e confirmação); deixa o negócio consistente (histórico preservado); lógica única (inversão da situação sem exclusão). TD=3 (situação, mensagem, ação ativar/inativar). AR=2 (Feriado, Trilha de auditoria). Registros automáticos contados como FTR (premissa P4): Trilha de auditoria. Recontagem 16/10/2026: mantida (linha 147 da contagem de 01/10/2026).
A62: =IF(H62="",IF(C62="",A61,A61+1),A61) | B62: =IF(A62=A61,"",CONCATENATE("F",A62)) | L62: =CONCATENATE(H62,M62) | M62: =IF(OR(ISBLANK(J62),ISBLANK(K62)),IF(OR(H62="ALI",H62="AIE"),"L",IF(ISBLANK(H62),"","A")),IF(H62="EE",IF(K62>=3,IF(J62>=5,"H","A"),IF(K62>=2,IF(J62>=16,"H",IF(J62<=4,"L","A")),IF(J62<=15,"L","A"))),IF(OR(H62="SE",H62="CE"),IF(K62>=4,IF(J62>=6,"H","A"),IF(K62>=2,IF(J62>=20,"H",IF(J62<=5,"L","A")),IF(J62<=19,"L","A"))),IF(OR(H62="ALI",H62="AIE"),IF(K62>=6,IF(J62>=20,"H","A"),IF(K62>=2,IF(J62>=51,"H",IF(J62<=19,"L","A")),IF(J62<=50,"L","A"))))))) | N62: =IF(M62="L","Baixa",IF(M62="A","Média",IF(M62="","","Alta"))) | O62: =IF(ISBLANK(H62),"",IF(H62="ALI",IF(M62="L",7,IF(M62="A",10,15)),IF(H62="AIE",IF(M62="L",5,IF(M62="A",7,10)),IF(H62="SE",IF(M62="L",4,IF(M62="A",5,7)),IF(OR(H62="EE",H62="CE"),IF(M62="L",3,IF(M62="A",4,6))))))) | P62: =IF(I62="I",O62*Contagem!$W$15,IF(I62="E",O62*Contagem!$W$17,IF(I62="A",O62*Contagem!$W$16,IF(I62="T",O62*Contagem!$W$18,""))))
A63: =IF(H63="",IF(C63="",A62,A62+1),A62) | B63: =IF(A63=A62,"",CONCATENATE("F",A63)) | C63: Tipos de imóvel | L63: =CONCATENATE(H63,M63) | M63: =IF(OR(ISBLANK(J63),ISBLANK(K63)),IF(OR(H63="ALI",H63="AIE"),"L",IF(ISBLANK(H63),"","A")),IF(H63="EE",IF(K63>=3,IF(J63>=5,"H","A"),IF(K63>=2,IF(J63>=16,"H",IF(J63<=4,"L","A")),IF(J63<=15,"L","A"))),IF(OR(H63="SE",H63="CE"),IF(K63>=4,IF(J63>=6,"H","A"),IF(K63>=2,IF(J63>=20,"H",IF(J63<=5,"L","A")),IF(J63<=19,"L","A"))),IF(OR(H63="ALI",H63="AIE"),IF(K63>=6,IF(J63>=20,"H","A"),IF(K63>=2,IF(J63>=51,"H",IF(J63<=19,"L","A")),IF(J63<=50,"L","A"))))))) | N63: =IF(M63="L","Baixa",IF(M63="A","Média",IF(M63="","","Alta"))) | O63: =IF(ISBLANK(H63),"",IF(H63="ALI",IF(M63="L",7,IF(M63="A",10,15)),IF(H63="AIE",IF(M63="L",5,IF(M63="A",7,10)),IF(H63="SE",IF(M63="L",4,IF(M63="A",5,7)),IF(OR(H63="EE",H63="CE"),IF(M63="L",3,IF(M63="A",4,6))))))) | P63: =IF(I63="I",O63*Contagem!$W$15,IF(I63="E",O63*Contagem!$W$17,IF(I63="A",O63*Contagem!$W$16,IF(I63="T",O63*Contagem!$W$18,""))))
A64: =IF(H64="",IF(C64="",A63,A63+1),A63) | B64: =IF(A64=A63,"",CONCATENATE("F",A64)) | C64: Dados - Tipo de imóvel | H64: ALI | I64: I | J64: 5 | K64: 1 | L64: =CONCATENATE(H64,M64) | M64: =IF(OR(ISBLANK(J64),ISBLANK(K64)),IF(OR(H64="ALI",H64="AIE"),"L",IF(ISBLANK(H64),"","A")),IF(H64="EE",IF(K64>=3,IF(J64>=5,"H","A"),IF(K64>=2,IF(J64>=16,"H",IF(J64<=4,"L","A")),IF(J64<=15,"L","A"))),IF(OR(H64="SE",H64="CE"),IF(K64>=4,IF(J64>=6,"H","A"),IF(K64>=2,IF(J64>=20,"H",IF(J64<=5,"L","A")),IF(J64<=19,"L","A"))),IF(OR(H64="ALI",H64="AIE"),IF(K64>=6,IF(J64>=20,"H","A"),IF(K64>=2,IF(J64>=51,"H",IF(J64<=19,"L","A")),IF(J64<=50,"L","A"))))))) | N64: =IF(M64="L","Baixa",IF(M64="A","Média",IF(M64="","","Alta"))) | O64: =IF(ISBLANK(H64),"",IF(H64="ALI",IF(M64="L",7,IF(M64="A",10,15)),IF(H64="AIE",IF(M64="L",5,IF(M64="A",7,10)),IF(H64="SE",IF(M64="L",4,IF(M64="A",5,7)),IF(OR(H64="EE",H64="CE"),IF(M64="L",3,IF(M64="A",4,6))))))) | P64: =IF(I64="I",O64*Contagem!$W$15,IF(I64="E",O64*Contagem!$W$17,IF(I64="A",O64*Contagem!$W$16,IF(I64="T",O64*Contagem!$W$18,"")))) | Q64: Prova: Models app/Models/PropertyType.php e app/Models/PropertyTypeAlias.php; migrations database/migrations/2026_09_17_150000_create_property_types_table.php (code, label, drives_rule, active) e 2026_09_17_150001_create_property_type_aliases_table.php (alias único, cascadeOnDelete). Mantido por PropertyTypeController (HasAuditoria); lido por app/Services/Risco/TipoImovelCatalog.php. Teste: tests/Feature/Risco/PropertyTypeCrudTest.php::test_cria_tipo_com_aliases_normalizados. Arquivo lógico: catálogo de tipos de imóvel do REGIN com as denominações que o motor reconhece. Não é dado de código (Parte 1 §5.4.2 d; Parte 3 Cap. 1): drives_rule decide o roteamento (TipoImovelCatalog separa dirigemRegra de ramoComum; o tipo que dirige regra injeta o gatilho dados_do_processo e tira o processo do expresso) e os aliases definem como o texto do REGIN é interpretado; o dado não se substitui pela descrição. TD=5 (código, rótulo, dirige regra, situação, denominação alternativa). TR=1 (Tipo de imóvel). Recontagem 16/10/2026: alterada (linha 249 da contagem de 01/10/2026: "Dados - Tipo de imóvel", ALI Baixa 7 PF, TD 5, AR 2). Motivo: TR 2→1: a denominação alternativa (property_type_aliases) tem um único atributo além da chave; subgrupo com 1 DER não forma RLR, entra como DER multivalorado. PF inalterado (ALI Baixa).
A65: =IF(H65="",IF(C65="",A64,A64+1),A64) | B65: =IF(A65=A64,"",CONCATENATE("F",A65)) | C65: Tipos de imóvel - consultar | H65: CE | I65: I | J65: 7 | K65: 1 | L65: =CONCATENATE(H65,M65) | M65: =IF(OR(ISBLANK(J65),ISBLANK(K65)),IF(OR(H65="ALI",H65="AIE"),"L",IF(ISBLANK(H65),"","A")),IF(H65="EE",IF(K65>=3,IF(J65>=5,"H","A"),IF(K65>=2,IF(J65>=16,"H",IF(J65<=4,"L","A")),IF(J65<=15,"L","A"))),IF(OR(H65="SE",H65="CE"),IF(K65>=4,IF(J65>=6,"H","A"),IF(K65>=2,IF(J65>=20,"H",IF(J65<=5,"L","A")),IF(J65<=19,"L","A"))),IF(OR(H65="ALI",H65="AIE"),IF(K65>=6,IF(J65>=20,"H","A"),IF(K65>=2,IF(J65>=51,"H",IF(J65<=19,"L","A")),IF(J65<=50,"L","A"))))))) | N65: =IF(M65="L","Baixa",IF(M65="A","Média",IF(M65="","","Alta"))) | O65: =IF(ISBLANK(H65),"",IF(H65="ALI",IF(M65="L",7,IF(M65="A",10,15)),IF(H65="AIE",IF(M65="L",5,IF(M65="A",7,10)),IF(H65="SE",IF(M65="L",4,IF(M65="A",5,7)),IF(OR(H65="EE",H65="CE"),IF(M65="L",3,IF(M65="A",4,6))))))) | P65: =IF(I65="I",O65*Contagem!$W$15,IF(I65="E",O65*Contagem!$W$17,IF(I65="A",O65*Contagem!$W$16,IF(I65="T",O65*Contagem!$W$18,"")))) | Q65: Prova: Rota GET /gestao/tipos-imovel (permissão manter-tipos-imovel). Tela: gestao/tipos-imovel/index. O gestor busca por código ou rótulo e filtra por situação. Lê Tipo de imóvel (com aliases); não grava. Teste: tests/Feature/Risco/PropertyTypeCrudTest.php::test_lista_exige_permissao. Processo elementar independente: menor unidade com significado para o gestor; completa por si (filtro até a lista); deixa o negócio consistente (nada muda); lógica única (tipos com denominações, sem cálculo). Classificação: CE (§5.5.3). TD=7 (código, rótulo, dirige regra, situação, denominações alternativas, busca por código/rótulo, ação de consultar). O filtro de situação é o mesmo campo da coluna situação e conta uma vez (DER único); ordenação e paginação não contam. AR=1 (Tipo de imóvel). Recontagem 16/10/2026: alterada (linha 250 da contagem de 01/10/2026: "Tipos de imóvel - consultar", CE Baixa 3 PF, TD 8, AR 1). Motivo: TD 8→7: situação e filtro de situação eram contados como dois DER. PF inalterado (CE Baixa).
A66: =IF(H66="",IF(C66="",A65,A65+1),A65) | B66: =IF(A66=A65,"",CONCATENATE("F",A66)) | C66: Tipos de imóvel - incluir | H66: EE | I66: I | J66: 7 | K66: 2 | L66: =CONCATENATE(H66,M66) | M66: =IF(OR(ISBLANK(J66),ISBLANK(K66)),IF(OR(H66="ALI",H66="AIE"),"L",IF(ISBLANK(H66),"","A")),IF(H66="EE",IF(K66>=3,IF(J66>=5,"H","A"),IF(K66>=2,IF(J66>=16,"H",IF(J66<=4,"L","A")),IF(J66<=15,"L","A"))),IF(OR(H66="SE",H66="CE"),IF(K66>=4,IF(J66>=6,"H","A"),IF(K66>=2,IF(J66>=20,"H",IF(J66<=5,"L","A")),IF(J66<=19,"L","A"))),IF(OR(H66="ALI",H66="AIE"),IF(K66>=6,IF(J66>=20,"H","A"),IF(K66>=2,IF(J66>=51,"H",IF(J66<=19,"L","A")),IF(J66<=50,"L","A"))))))) | N66: =IF(M66="L","Baixa",IF(M66="A","Média",IF(M66="","","Alta"))) | O66: =IF(ISBLANK(H66),"",IF(H66="ALI",IF(M66="L",7,IF(M66="A",10,15)),IF(H66="AIE",IF(M66="L",5,IF(M66="A",7,10)),IF(H66="SE",IF(M66="L",4,IF(M66="A",5,7)),IF(OR(H66="EE",H66="CE"),IF(M66="L",3,IF(M66="A",4,6))))))) | P66: =IF(I66="I",O66*Contagem!$W$15,IF(I66="E",O66*Contagem!$W$17,IF(I66="A",O66*Contagem!$W$16,IF(I66="T",O66*Contagem!$W$18,"")))) | Q66: Prova: Rota POST /gestao/tipos-imovel (permissão manter-tipos-imovel). Tela: gestao/tipos-imovel/index. O gestor cadastra o tipo e os aliases; alias duplicado entre tipos é rejeitado. Grava Tipo de imóvel (tipo e aliases normalizados), limpa o cache do catálogo e registra Trilha de auditoria. Resultado: o REGIN passa a reconhecer o tipo. Teste: tests/Feature/Risco/PropertyTypeCrudTest.php::test_cria_tipo_com_aliases_normalizados. Processo elementar independente: menor unidade com significado para o gestor; completa por si (formulário até a gravação); deixa o negócio consistente (aliases únicos e normalizados, auditado); lógica única (inclusão com normalização de aliases). TD=7 (código, rótulo, define regra, ativo, denominações alternativas, mensagem de sucesso/erro, ação de salvar). AR=2 (Tipo de imóvel, Trilha de auditoria). Registros automáticos contados como FTR (premissa P4): Trilha de auditoria. Recontagem 16/10/2026: mantida (linha 251 da contagem de 01/10/2026).
A67: =IF(H67="",IF(C67="",A66,A66+1),A66) | B67: =IF(A67=A66,"",CONCATENATE("F",A67)) | C67: Tipos de imóvel - alterar | H67: EE | I67: I | J67: 7 | K67: 2 | L67: =CONCATENATE(H67,M67) | M67: =IF(OR(ISBLANK(J67),ISBLANK(K67)),IF(OR(H67="ALI",H67="AIE"),"L",IF(ISBLANK(H67),"","A")),IF(H67="EE",IF(K67>=3,IF(J67>=5,"H","A"),IF(K67>=2,IF(J67>=16,"H",IF(J67<=4,"L","A")),IF(J67<=15,"L","A"))),IF(OR(H67="SE",H67="CE"),IF(K67>=4,IF(J67>=6,"H","A"),IF(K67>=2,IF(J67>=20,"H",IF(J67<=5,"L","A")),IF(J67<=19,"L","A"))),IF(OR(H67="ALI",H67="AIE"),IF(K67>=6,IF(J67>=20,"H","A"),IF(K67>=2,IF(J67>=51,"H",IF(J67<=19,"L","A")),IF(J67<=50,"L","A"))))))) | N67: =IF(M67="L","Baixa",IF(M67="A","Média",IF(M67="","","Alta"))) | O67: =IF(ISBLANK(H67),"",IF(H67="ALI",IF(M67="L",7,IF(M67="A",10,15)),IF(H67="AIE",IF(M67="L",5,IF(M67="A",7,10)),IF(H67="SE",IF(M67="L",4,IF(M67="A",5,7)),IF(OR(H67="EE",H67="CE"),IF(M67="L",3,IF(M67="A",4,6))))))) | P67: =IF(I67="I",O67*Contagem!$W$15,IF(I67="E",O67*Contagem!$W$17,IF(I67="A",O67*Contagem!$W$16,IF(I67="T",O67*Contagem!$W$18,"")))) | Q67: Prova: Rota PUT /gestao/tipos-imovel/{propertyType} (permissão manter-tipos-imovel). Tela: gestao/tipos-imovel/index. O gestor altera rótulo, regra e aliases; código imutável; alias removido é excluído e auditado. Grava Tipo de imóvel e Trilha de auditoria. Resultado: muda o roteamento expresso/análise. Teste: tests/Feature/Risco/PropertyTypeCrudTest.php::test_remocao_de_alias_e_auditada. Processo elementar independente: menor unidade com significado para o gestor; completa por si (edição até a gravação); deixa o negócio consistente (aliases sincronizados, auditado); lógica única (alteração com sincronização de aliases). TD=7 (código (identificação, imutável), rótulo, define regra, ativo, denominações alternativas, mensagem de sucesso/erro, ação de salvar). AR=2 (Tipo de imóvel, Trilha de auditoria). Registros automáticos contados como FTR (premissa P4): Trilha de auditoria. Recontagem 16/10/2026: mantida (linha 252 da contagem de 01/10/2026).
A68: =IF(H68="",IF(C68="",A67,A67+1),A67) | B68: =IF(A68=A67,"",CONCATENATE("F",A68)) | C68: Tipos de imóvel - ativar ou inativar | H68: EE | I68: I | J68: 4 | K68: 2 | L68: =CONCATENATE(H68,M68) | M68: =IF(OR(ISBLANK(J68),ISBLANK(K68)),IF(OR(H68="ALI",H68="AIE"),"L",IF(ISBLANK(H68),"","A")),IF(H68="EE",IF(K68>=3,IF(J68>=5,"H","A"),IF(K68>=2,IF(J68>=16,"H",IF(J68<=4,"L","A")),IF(J68<=15,"L","A"))),IF(OR(H68="SE",H68="CE"),IF(K68>=4,IF(J68>=6,"H","A"),IF(K68>=2,IF(J68>=20,"H",IF(J68<=5,"L","A")),IF(J68<=19,"L","A"))),IF(OR(H68="ALI",H68="AIE"),IF(K68>=6,IF(J68>=20,"H","A"),IF(K68>=2,IF(J68>=51,"H",IF(J68<=19,"L","A")),IF(J68<=50,"L","A"))))))) | N68: =IF(M68="L","Baixa",IF(M68="A","Média",IF(M68="","","Alta"))) | O68: =IF(ISBLANK(H68),"",IF(H68="ALI",IF(M68="L",7,IF(M68="A",10,15)),IF(H68="AIE",IF(M68="L",5,IF(M68="A",7,10)),IF(H68="SE",IF(M68="L",4,IF(M68="A",5,7)),IF(OR(H68="EE",H68="CE"),IF(M68="L",3,IF(M68="A",4,6))))))) | P68: =IF(I68="I",O68*Contagem!$W$15,IF(I68="E",O68*Contagem!$W$17,IF(I68="A",O68*Contagem!$W$16,IF(I68="T",O68*Contagem!$W$18,"")))) | Q68: Prova: Rota PUT /gestao/tipos-imovel/{propertyType}/ativacao (permissão manter-tipos-imovel). Tela: gestao/tipos-imovel/index. O gestor ativa ou inativa sem excluir. Grava Tipo de imóvel e Trilha de auditoria. Resultado: tipo inativo degrada para desconhecido e vai à análise. Teste: tests/Feature/Risco/PropertyTypeCrudTest.php::test_toggle_desativa_sem_excluir_e_audita. Processo elementar independente: menor unidade com significado para o gestor; completa por si (clique até a nova situação); deixa o negócio consistente (registro preservado, auditado); lógica única (alternância de situação). TD=4 (código do tipo, situação, mensagem de sucesso, ação de ativar/inativar). AR=2 (Tipo de imóvel, Trilha de auditoria). Registros automáticos contados como FTR (premissa P4): Trilha de auditoria. Recontagem 16/10/2026: mantida (linha 253 da contagem de 01/10/2026).
A69: =IF(H69="",IF(C69="",A68,A68+1),A68) | B69: =IF(A69=A68,"",CONCATENATE("F",A69)) | L69: =CONCATENATE(H69,M69) | M69: =IF(OR(ISBLANK(J69),ISBLANK(K69)),IF(OR(H69="ALI",H69="AIE"),"L",IF(ISBLANK(H69),"","A")),IF(H69="EE",IF(K69>=3,IF(J69>=5,"H","A"),IF(K69>=2,IF(J69>=16,"H",IF(J69<=4,"L","A")),IF(J69<=15,"L","A"))),IF(OR(H69="SE",H69="CE"),IF(K69>=4,IF(J69>=6,"H","A"),IF(K69>=2,IF(J69>=20,"H",IF(J69<=5,"L","A")),IF(J69<=19,"L","A"))),IF(OR(H69="ALI",H69="AIE"),IF(K69>=6,IF(J69>=20,"H","A"),IF(K69>=2,IF(J69>=51,"H",IF(J69<=19,"L","A")),IF(J69<=50,"L","A"))))))) | N69: =IF(M69="L","Baixa",IF(M69="A","Média",IF(M69="","","Alta"))) | O69: =IF(ISBLANK(H69),"",IF(H69="ALI",IF(M69="L",7,IF(M69="A",10,15)),IF(H69="AIE",IF(M69="L",5,IF(M69="A",7,10)),IF(H69="SE",IF(M69="L",4,IF(M69="A",5,7)),IF(OR(H69="EE",H69="CE"),IF(M69="L",3,IF(M69="A",4,6))))))) | P69: =IF(I69="I",O69*Contagem!$W$15,IF(I69="E",O69*Contagem!$W$17,IF(I69="A",O69*Contagem!$W$16,IF(I69="T",O69*Contagem!$W$18,""))))
A70: =IF(H70="",IF(C70="",A69,A69+1),A69) | B70: =IF(A70=A69,"",CONCATENATE("F",A70)) | C70: Termos legais | L70: =CONCATENATE(H70,M70) | M70: =IF(OR(ISBLANK(J70),ISBLANK(K70)),IF(OR(H70="ALI",H70="AIE"),"L",IF(ISBLANK(H70),"","A")),IF(H70="EE",IF(K70>=3,IF(J70>=5,"H","A"),IF(K70>=2,IF(J70>=16,"H",IF(J70<=4,"L","A")),IF(J70<=15,"L","A"))),IF(OR(H70="SE",H70="CE"),IF(K70>=4,IF(J70>=6,"H","A"),IF(K70>=2,IF(J70>=20,"H",IF(J70<=5,"L","A")),IF(J70<=19,"L","A"))),IF(OR(H70="ALI",H70="AIE"),IF(K70>=6,IF(J70>=20,"H","A"),IF(K70>=2,IF(J70>=51,"H",IF(J70<=19,"L","A")),IF(J70<=50,"L","A"))))))) | N70: =IF(M70="L","Baixa",IF(M70="A","Média",IF(M70="","","Alta"))) | O70: =IF(ISBLANK(H70),"",IF(H70="ALI",IF(M70="L",7,IF(M70="A",10,15)),IF(H70="AIE",IF(M70="L",5,IF(M70="A",7,10)),IF(H70="SE",IF(M70="L",4,IF(M70="A",5,7)),IF(OR(H70="EE",H70="CE"),IF(M70="L",3,IF(M70="A",4,6))))))) | P70: =IF(I70="I",O70*Contagem!$W$15,IF(I70="E",O70*Contagem!$W$17,IF(I70="A",O70*Contagem!$W$16,IF(I70="T",O70*Contagem!$W$18,""))))
A71: =IF(H71="",IF(C71="",A70,A70+1),A70) | B71: =IF(A71=A70,"",CONCATENATE("F",A71)) | C71: Dados - Termo legal | H71: ALI | I71: I | J71: 5 | K71: 1 | L71: =CONCATENATE(H71,M71) | M71: =IF(OR(ISBLANK(J71),ISBLANK(K71)),IF(OR(H71="ALI",H71="AIE"),"L",IF(ISBLANK(H71),"","A")),IF(H71="EE",IF(K71>=3,IF(J71>=5,"H","A"),IF(K71>=2,IF(J71>=16,"H",IF(J71<=4,"L","A")),IF(J71<=15,"L","A"))),IF(OR(H71="SE",H71="CE"),IF(K71>=4,IF(J71>=6,"H","A"),IF(K71>=2,IF(J71>=20,"H",IF(J71<=5,"L","A")),IF(J71<=19,"L","A"))),IF(OR(H71="ALI",H71="AIE"),IF(K71>=6,IF(J71>=20,"H","A"),IF(K71>=2,IF(J71>=51,"H",IF(J71<=19,"L","A")),IF(J71<=50,"L","A"))))))) | N71: =IF(M71="L","Baixa",IF(M71="A","Média",IF(M71="","","Alta"))) | O71: =IF(ISBLANK(H71),"",IF(H71="ALI",IF(M71="L",7,IF(M71="A",10,15)),IF(H71="AIE",IF(M71="L",5,IF(M71="A",7,10)),IF(H71="SE",IF(M71="L",4,IF(M71="A",5,7)),IF(OR(H71="EE",H71="CE"),IF(M71="L",3,IF(M71="A",4,6))))))) | P71: =IF(I71="I",O71*Contagem!$W$15,IF(I71="E",O71*Contagem!$W$17,IF(I71="A",O71*Contagem!$W$16,IF(I71="T",O71*Contagem!$W$18,"")))) | Q71: Prova: Model LegalTerm; migration database/migrations/2026_06_10_022240_create_legal_terms_table.php (tabela legal_terms). Mantido pelo gestor em /gestao/termos-legais (LegalTermController store, update, publicar, destroy); versão sequencial por tipo; publicado é imutável. Lido no aceite LGPD do portal e da gestão. Teste: tests/Feature/Gestao/LegalTermCrudTest.php::test_cria_rascunho_com_proxima_versao_do_tipo. Arquivo lógico: Por que é grupo lógico reconhecido pelo usuário: o gestor redige e publica versões dos termos (LGPD, uso) que o usuário aceita; mantido por processos da aplicação; registro único por versão, sem tabela filha (os aceites são subgrupo de Usuário). TD=5 (tipo, versão, título, conteúdo, publicado em). TR=1 (Termo legal). Recontagem 16/10/2026: mantida (linha 370 da contagem de 01/10/2026).
A72: =IF(H72="",IF(C72="",A71,A71+1),A71) | B72: =IF(A72=A71,"",CONCATENATE("F",A72)) | C72: Termos legais - consultar | H72: SE | I72: I | J72: 7 | K72: 1 | L72: =CONCATENATE(H72,M72) | M72: =IF(OR(ISBLANK(J72),ISBLANK(K72)),IF(OR(H72="ALI",H72="AIE"),"L",IF(ISBLANK(H72),"","A")),IF(H72="EE",IF(K72>=3,IF(J72>=5,"H","A"),IF(K72>=2,IF(J72>=16,"H",IF(J72<=4,"L","A")),IF(J72<=15,"L","A"))),IF(OR(H72="SE",H72="CE"),IF(K72>=4,IF(J72>=6,"H","A"),IF(K72>=2,IF(J72>=20,"H",IF(J72<=5,"L","A")),IF(J72<=19,"L","A"))),IF(OR(H72="ALI",H72="AIE"),IF(K72>=6,IF(J72>=20,"H","A"),IF(K72>=2,IF(J72>=51,"H",IF(J72<=19,"L","A")),IF(J72<=50,"L","A"))))))) | N72: =IF(M72="L","Baixa",IF(M72="A","Média",IF(M72="","","Alta"))) | O72: =IF(ISBLANK(H72),"",IF(H72="ALI",IF(M72="L",7,IF(M72="A",10,15)),IF(H72="AIE",IF(M72="L",5,IF(M72="A",7,10)),IF(H72="SE",IF(M72="L",4,IF(M72="A",5,7)),IF(OR(H72="EE",H72="CE"),IF(M72="L",3,IF(M72="A",4,6))))))) | P72: =IF(I72="I",O72*Contagem!$W$15,IF(I72="E",O72*Contagem!$W$17,IF(I72="A",O72*Contagem!$W$16,IF(I72="T",O72*Contagem!$W$18,"")))) | Q72: Prova: Rota GET /gestao/termos-legais (manter-parametros). Tela: gestao/termos-legais/index. O gestor vê os termos por tipo e versão; LegalTermController deriva a situação: rascunho sem publicação, vigente a última publicada do tipo, substituído as demais. Lê termo legal. Teste: tests/Feature/Gestao/LegalTermCrudTest.php::test_lista_exige_permissao. Processo elementar independente: menor unidade com significado para o gestor; completa por si (abrir a tela até a lista); deixa o negócio consistente (só leitura); lógica única (deriva qual versão está vigente por tipo). TD=7 (tipo, versão, título, conteúdo, publicado em, situação (rascunho, vigente, substituído), ação consultar). AR=1 (Termo legal). Classificação: A situação vigente ou substituída é dado derivado calculado na consulta: SE, não CE. Recontagem 16/10/2026: mantida (linha 371 da contagem de 01/10/2026).
A73: =IF(H73="",IF(C73="",A72,A72+1),A72) | B73: =IF(A73=A72,"",CONCATENATE("F",A73)) | C73: Termos legais - incluir | H73: EE | I73: I | J73: 5 | K73: 2 | L73: =CONCATENATE(H73,M73) | M73: =IF(OR(ISBLANK(J73),ISBLANK(K73)),IF(OR(H73="ALI",H73="AIE"),"L",IF(ISBLANK(H73),"","A")),IF(H73="EE",IF(K73>=3,IF(J73>=5,"H","A"),IF(K73>=2,IF(J73>=16,"H",IF(J73<=4,"L","A")),IF(J73<=15,"L","A"))),IF(OR(H73="SE",H73="CE"),IF(K73>=4,IF(J73>=6,"H","A"),IF(K73>=2,IF(J73>=20,"H",IF(J73<=5,"L","A")),IF(J73<=19,"L","A"))),IF(OR(H73="ALI",H73="AIE"),IF(K73>=6,IF(J73>=20,"H","A"),IF(K73>=2,IF(J73>=51,"H",IF(J73<=19,"L","A")),IF(J73<=50,"L","A"))))))) | N73: =IF(M73="L","Baixa",IF(M73="A","Média",IF(M73="","","Alta"))) | O73: =IF(ISBLANK(H73),"",IF(H73="ALI",IF(M73="L",7,IF(M73="A",10,15)),IF(H73="AIE",IF(M73="L",5,IF(M73="A",7,10)),IF(H73="SE",IF(M73="L",4,IF(M73="A",5,7)),IF(OR(H73="EE",H73="CE"),IF(M73="L",3,IF(M73="A",4,6))))))) | P73: =IF(I73="I",O73*Contagem!$W$15,IF(I73="E",O73*Contagem!$W$17,IF(I73="A",O73*Contagem!$W$16,IF(I73="T",O73*Contagem!$W$18,"")))) | Q73: Prova: Rota POST /gestao/termos-legais (manter-parametros). Tela: gestao/termos-legais/index. O gestor informa tipo, título e conteúdo; o sistema atribui a próxima versão do tipo e grava como rascunho (sem publicação). Grava termo legal; auditado por HasAuditoria. Teste: tests/Feature/Gestao/LegalTermCrudTest.php::test_cria_rascunho_com_proxima_versao_do_tipo. Processo elementar independente: menor unidade com significado para o gestor; completa por si (formulário até o rascunho gravado); deixa o negócio consistente (versão sequencial, vigente intacta); lógica única (inclusão com versionamento automático). TD=5 (tipo, título, conteúdo, mensagem de sucesso/erro, ação salvar). AR=2 (Termo legal, Trilha de auditoria). Registros automáticos contados como FTR (premissa P4): Trilha de auditoria. Recontagem 16/10/2026: mantida (linha 372 da contagem de 01/10/2026).
A74: =IF(H74="",IF(C74="",A73,A73+1),A73) | B74: =IF(A74=A73,"",CONCATENATE("F",A74)) | C74: Termos legais - alterar | H74: EE | I74: I | J74: 5 | K74: 2 | L74: =CONCATENATE(H74,M74) | M74: =IF(OR(ISBLANK(J74),ISBLANK(K74)),IF(OR(H74="ALI",H74="AIE"),"L",IF(ISBLANK(H74),"","A")),IF(H74="EE",IF(K74>=3,IF(J74>=5,"H","A"),IF(K74>=2,IF(J74>=16,"H",IF(J74<=4,"L","A")),IF(J74<=15,"L","A"))),IF(OR(H74="SE",H74="CE"),IF(K74>=4,IF(J74>=6,"H","A"),IF(K74>=2,IF(J74>=20,"H",IF(J74<=5,"L","A")),IF(J74<=19,"L","A"))),IF(OR(H74="ALI",H74="AIE"),IF(K74>=6,IF(J74>=20,"H","A"),IF(K74>=2,IF(J74>=51,"H",IF(J74<=19,"L","A")),IF(J74<=50,"L","A"))))))) | N74: =IF(M74="L","Baixa",IF(M74="A","Média",IF(M74="","","Alta"))) | O74: =IF(ISBLANK(H74),"",IF(H74="ALI",IF(M74="L",7,IF(M74="A",10,15)),IF(H74="AIE",IF(M74="L",5,IF(M74="A",7,10)),IF(H74="SE",IF(M74="L",4,IF(M74="A",5,7)),IF(OR(H74="EE",H74="CE"),IF(M74="L",3,IF(M74="A",4,6))))))) | P74: =IF(I74="I",O74*Contagem!$W$15,IF(I74="E",O74*Contagem!$W$17,IF(I74="A",O74*Contagem!$W$16,IF(I74="T",O74*Contagem!$W$18,"")))) | Q74: Prova: Rota PUT /gestao/termos-legais/{legalTerm} (manter-parametros). Tela: gestao/termos-legais/index. O gestor altera título e conteúdo do rascunho; termo publicado é recusado com mensagem de imutabilidade. Grava termo legal; auditado por HasAuditoria. Teste: tests/Feature/Gestao/LegalTermCrudTest.php::test_rascunho_pode_ser_editado_e_excluido. Processo elementar independente: menor unidade com significado para o gestor; completa por si (edição até a gravação); deixa o negócio consistente (publicado nunca muda); lógica única (alteração restrita a rascunho). TD=5 (termo (identificação), título, conteúdo, mensagem de sucesso/erro, ação salvar). AR=2 (Termo legal, Trilha de auditoria). Registros automáticos contados como FTR (premissa P4): Trilha de auditoria. Recontagem 16/10/2026: mantida (linha 373 da contagem de 01/10/2026).
A75: =IF(H75="",IF(C75="",A74,A74+1),A74) | B75: =IF(A75=A74,"",CONCATENATE("F",A75)) | C75: Termos legais - publicar | H75: EE | I75: I | J75: 4 | K75: 2 | L75: =CONCATENATE(H75,M75) | M75: =IF(OR(ISBLANK(J75),ISBLANK(K75)),IF(OR(H75="ALI",H75="AIE"),"L",IF(ISBLANK(H75),"","A")),IF(H75="EE",IF(K75>=3,IF(J75>=5,"H","A"),IF(K75>=2,IF(J75>=16,"H",IF(J75<=4,"L","A")),IF(J75<=15,"L","A"))),IF(OR(H75="SE",H75="CE"),IF(K75>=4,IF(J75>=6,"H","A"),IF(K75>=2,IF(J75>=20,"H",IF(J75<=5,"L","A")),IF(J75<=19,"L","A"))),IF(OR(H75="ALI",H75="AIE"),IF(K75>=6,IF(J75>=20,"H","A"),IF(K75>=2,IF(J75>=51,"H",IF(J75<=19,"L","A")),IF(J75<=50,"L","A"))))))) | N75: =IF(M75="L","Baixa",IF(M75="A","Média",IF(M75="","","Alta"))) | O75: =IF(ISBLANK(H75),"",IF(H75="ALI",IF(M75="L",7,IF(M75="A",10,15)),IF(H75="AIE",IF(M75="L",5,IF(M75="A",7,10)),IF(H75="SE",IF(M75="L",4,IF(M75="A",5,7)),IF(OR(H75="EE",H75="CE"),IF(M75="L",3,IF(M75="A",4,6))))))) | P75: =IF(I75="I",O75*Contagem!$W$15,IF(I75="E",O75*Contagem!$W$17,IF(I75="A",O75*Contagem!$W$16,IF(I75="T",O75*Contagem!$W$18,"")))) | Q75: Prova: Rota PUT /gestao/termos-legais/{legalTerm}/publicar (manter-parametros). Tela: gestao/termos-legais/index. O gestor publica o rascunho; grava published_at e a versão passa a vigente para novos aceites; republicar é recusado. Grava termo legal; auditado. Teste: tests/Feature/Gestao/LegalTermCrudTest.php::test_publicar_torna_o_termo_vigente. Processo elementar independente: menor unidade com significado para o gestor; completa por si (clique até a versão vigente); deixa o negócio consistente (novos aceites usam a versão publicada); lógica única (publicação com imutabilidade). TD=4 (termo (versão e título), publicado em, mensagem de sucesso/erro, ação publicar). AR=2 (Termo legal, Trilha de auditoria). Registros automáticos contados como FTR (premissa P4): Trilha de auditoria. Recontagem 16/10/2026: mantida (linha 374 da contagem de 01/10/2026).
A76: =IF(H76="",IF(C76="",A75,A75+1),A75) | B76: =IF(A76=A75,"",CONCATENATE("F",A76)) | C76: Termos legais - excluir | H76: EE | I76: I | J76: 3 | K76: 2 | L76: =CONCATENATE(H76,M76) | M76: =IF(OR(ISBLANK(J76),ISBLANK(K76)),IF(OR(H76="ALI",H76="AIE"),"L",IF(ISBLANK(H76),"","A")),IF(H76="EE",IF(K76>=3,IF(J76>=5,"H","A"),IF(K76>=2,IF(J76>=16,"H",IF(J76<=4,"L","A")),IF(J76<=15,"L","A"))),IF(OR(H76="SE",H76="CE"),IF(K76>=4,IF(J76>=6,"H","A"),IF(K76>=2,IF(J76>=20,"H",IF(J76<=5,"L","A")),IF(J76<=19,"L","A"))),IF(OR(H76="ALI",H76="AIE"),IF(K76>=6,IF(J76>=20,"H","A"),IF(K76>=2,IF(J76>=51,"H",IF(J76<=19,"L","A")),IF(J76<=50,"L","A"))))))) | N76: =IF(M76="L","Baixa",IF(M76="A","Média",IF(M76="","","Alta"))) | O76: =IF(ISBLANK(H76),"",IF(H76="ALI",IF(M76="L",7,IF(M76="A",10,15)),IF(H76="AIE",IF(M76="L",5,IF(M76="A",7,10)),IF(H76="SE",IF(M76="L",4,IF(M76="A",5,7)),IF(OR(H76="EE",H76="CE"),IF(M76="L",3,IF(M76="A",4,6))))))) | P76: =IF(I76="I",O76*Contagem!$W$15,IF(I76="E",O76*Contagem!$W$17,IF(I76="A",O76*Contagem!$W$16,IF(I76="T",O76*Contagem!$W$18,"")))) | Q76: Prova: Rota DELETE /gestao/termos-legais/{legalTerm} (manter-parametros). Tela: gestao/termos-legais/index. O gestor exclui um rascunho; termo publicado é recusado com mensagem. Remove termo legal; auditado por HasAuditoria. Teste: tests/Feature/Gestao/LegalTermCrudTest.php::test_rascunho_pode_ser_editado_e_excluido. Processo elementar independente: menor unidade com significado para o gestor; completa por si (confirmação até a remoção); deixa o negócio consistente (publicado preservado); lógica única (exclusão restrita a rascunho). TD=3 (termo (identificação), mensagem de sucesso/erro, ação excluir). AR=2 (Termo legal, Trilha de auditoria). Registros automáticos contados como FTR (premissa P4): Trilha de auditoria. Recontagem 16/10/2026: mantida (linha 375 da contagem de 01/10/2026).
A77: =IF(H77="",IF(C77="",A76,A76+1),A76) | B77: =IF(A77=A76,"",CONCATENATE("F",A77)) | L77: =CONCATENATE(H77,M77) | M77: =IF(OR(ISBLANK(J77),ISBLANK(K77)),IF(OR(H77="ALI",H77="AIE"),"L",IF(ISBLANK(H77),"","A")),IF(H77="EE",IF(K77>=3,IF(J77>=5,"H","A"),IF(K77>=2,IF(J77>=16,"H",IF(J77<=4,"L","A")),IF(J77<=15,"L","A"))),IF(OR(H77="SE",H77="CE"),IF(K77>=4,IF(J77>=6,"H","A"),IF(K77>=2,IF(J77>=20,"H",IF(J77<=5,"L","A")),IF(J77<=19,"L","A"))),IF(OR(H77="ALI",H77="AIE"),IF(K77>=6,IF(J77>=20,"H","A"),IF(K77>=2,IF(J77>=51,"H",IF(J77<=19,"L","A")),IF(J77<=50,"L","A"))))))) | N77: =IF(M77="L","Baixa",IF(M77="A","Média",IF(M77="","","Alta"))) | O77: =IF(ISBLANK(H77),"",IF(H77="ALI",IF(M77="L",7,IF(M77="A",10,15)),IF(H77="AIE",IF(M77="L",5,IF(M77="A",7,10)),IF(H77="SE",IF(M77="L",4,IF(M77="A",5,7)),IF(OR(H77="EE",H77="CE"),IF(M77="L",3,IF(M77="A",4,6))))))) | P77: =IF(I77="I",O77*Contagem!$W$15,IF(I77="E",O77*Contagem!$W$17,IF(I77="A",O77*Contagem!$W$16,IF(I77="T",O77*Contagem!$W$18,""))))
A78: =IF(H78="",IF(C78="",A77,A77+1),A77) | B78: =IF(A78=A77,"",CONCATENATE("F",A78)) | C78: Textos-padrão | L78: =CONCATENATE(H78,M78) | M78: =IF(OR(ISBLANK(J78),ISBLANK(K78)),IF(OR(H78="ALI",H78="AIE"),"L",IF(ISBLANK(H78),"","A")),IF(H78="EE",IF(K78>=3,IF(J78>=5,"H","A"),IF(K78>=2,IF(J78>=16,"H",IF(J78<=4,"L","A")),IF(J78<=15,"L","A"))),IF(OR(H78="SE",H78="CE"),IF(K78>=4,IF(J78>=6,"H","A"),IF(K78>=2,IF(J78>=20,"H",IF(J78<=5,"L","A")),IF(J78<=19,"L","A"))),IF(OR(H78="ALI",H78="AIE"),IF(K78>=6,IF(J78>=20,"H","A"),IF(K78>=2,IF(J78>=51,"H",IF(J78<=19,"L","A")),IF(J78<=50,"L","A"))))))) | N78: =IF(M78="L","Baixa",IF(M78="A","Média",IF(M78="","","Alta"))) | O78: =IF(ISBLANK(H78),"",IF(H78="ALI",IF(M78="L",7,IF(M78="A",10,15)),IF(H78="AIE",IF(M78="L",5,IF(M78="A",7,10)),IF(H78="SE",IF(M78="L",4,IF(M78="A",5,7)),IF(OR(H78="EE",H78="CE"),IF(M78="L",3,IF(M78="A",4,6))))))) | P78: =IF(I78="I",O78*Contagem!$W$15,IF(I78="E",O78*Contagem!$W$17,IF(I78="A",O78*Contagem!$W$16,IF(I78="T",O78*Contagem!$W$18,""))))
A79: =IF(H79="",IF(C79="",A78,A78+1),A78) | B79: =IF(A79=A78,"",CONCATENATE("F",A79)) | C79: Dados - Texto-padrão | H79: ALI | I79: I | J79: 4 | K79: 1 | L79: =CONCATENATE(H79,M79) | M79: =IF(OR(ISBLANK(J79),ISBLANK(K79)),IF(OR(H79="ALI",H79="AIE"),"L",IF(ISBLANK(H79),"","A")),IF(H79="EE",IF(K79>=3,IF(J79>=5,"H","A"),IF(K79>=2,IF(J79>=16,"H",IF(J79<=4,"L","A")),IF(J79<=15,"L","A"))),IF(OR(H79="SE",H79="CE"),IF(K79>=4,IF(J79>=6,"H","A"),IF(K79>=2,IF(J79>=20,"H",IF(J79<=5,"L","A")),IF(J79<=19,"L","A"))),IF(OR(H79="ALI",H79="AIE"),IF(K79>=6,IF(J79>=20,"H","A"),IF(K79>=2,IF(J79>=51,"H",IF(J79<=19,"L","A")),IF(J79<=50,"L","A"))))))) | N79: =IF(M79="L","Baixa",IF(M79="A","Média",IF(M79="","","Alta"))) | O79: =IF(ISBLANK(H79),"",IF(H79="ALI",IF(M79="L",7,IF(M79="A",10,15)),IF(H79="AIE",IF(M79="L",5,IF(M79="A",7,10)),IF(H79="SE",IF(M79="L",4,IF(M79="A",5,7)),IF(OR(H79="EE",H79="CE"),IF(M79="L",3,IF(M79="A",4,6))))))) | P79: =IF(I79="I",O79*Contagem!$W$15,IF(I79="E",O79*Contagem!$W$17,IF(I79="A",O79*Contagem!$W$16,IF(I79="T",O79*Contagem!$W$18,"")))) | Q79: Prova: Model StandardText; migration 2026_06_14_215047_create_standard_texts_table. Mantido por incluir, alterar (incrementa versão ao mudar conteúdo) e ativar/inativar (StandardTextController). Lido pela ficha de análise e pela minuta de parecer. Teste: tests/Feature/Analise/StandardTextCrudTest.php::test_editar_conteudo_incrementa_versao. Arquivo lógico: Grupo lógico reconhecido pelo gestor da SEDUR: biblioteca versionada de trechos pré-aprovados usados no parecer. Mantido por telas da própria aplicação. TD=4 (categoria, conteúdo, situação, versão). TR=1 (Texto-padrão). Regra de negócio que o tira de dado de código: a ficha de análise monta o parecer com os textos ativos da categoria da ficha (StandardTextComposer), preenchidos com os dados do processo; alterar o conteúdo gera nova versão do texto. Recontagem 16/10/2026: mantida (linha 383 da contagem de 01/10/2026).
A80: =IF(H80="",IF(C80="",A79,A79+1),A79) | B80: =IF(A80=A79,"",CONCATENATE("F",A80)) | C80: Textos-padrão - consultar | H80: CE | I80: I | J80: 6 | K80: 1 | L80: =CONCATENATE(H80,M80) | M80: =IF(OR(ISBLANK(J80),ISBLANK(K80)),IF(OR(H80="ALI",H80="AIE"),"L",IF(ISBLANK(H80),"","A")),IF(H80="EE",IF(K80>=3,IF(J80>=5,"H","A"),IF(K80>=2,IF(J80>=16,"H",IF(J80<=4,"L","A")),IF(J80<=15,"L","A"))),IF(OR(H80="SE",H80="CE"),IF(K80>=4,IF(J80>=6,"H","A"),IF(K80>=2,IF(J80>=20,"H",IF(J80<=5,"L","A")),IF(J80<=19,"L","A"))),IF(OR(H80="ALI",H80="AIE"),IF(K80>=6,IF(J80>=20,"H","A"),IF(K80>=2,IF(J80>=51,"H",IF(J80<=19,"L","A")),IF(J80<=50,"L","A"))))))) | N80: =IF(M80="L","Baixa",IF(M80="A","Média",IF(M80="","","Alta"))) | O80: =IF(ISBLANK(H80),"",IF(H80="ALI",IF(M80="L",7,IF(M80="A",10,15)),IF(H80="AIE",IF(M80="L",5,IF(M80="A",7,10)),IF(H80="SE",IF(M80="L",4,IF(M80="A",5,7)),IF(OR(H80="EE",H80="CE"),IF(M80="L",3,IF(M80="A",4,6))))))) | P80: =IF(I80="I",O80*Contagem!$W$15,IF(I80="E",O80*Contagem!$W$17,IF(I80="A",O80*Contagem!$W$16,IF(I80="T",O80*Contagem!$W$18,"")))) | Q80: Prova: Rota GET /gestao/textos-padrao (permissão manter-parametros). Tela: gestao/textos-padrao/index. O gestor lista com busca no conteúdo, filtro de categoria e de situação. Lê Texto-padrão; não grava. Teste: tests/Feature/Analise/StandardTextCrudTest.php::test_filtra_por_categoria. Processo elementar independente: menor unidade com significado para o gestor; completa por si (filtra e recebe a lista); deixa o negócio consistente (nada é alterado); lógica única (consulta da biblioteca de textos). Classificação: recuperação sem cálculo, CE (§5.5.3). TD=6 (busca no conteúdo, categoria, situação, conteúdo, versão, ação de consultar). Filtros de categoria e situação são os mesmos campos das colunas; ordenação não conta (a contagem anterior listava ordenação no lugar da ação; total igual). AR=1 (Texto-padrão). Recontagem 16/10/2026: mantida (linha 384 da contagem de 01/10/2026).
A81: =IF(H81="",IF(C81="",A80,A80+1),A80) | B81: =IF(A81=A80,"",CONCATENATE("F",A81)) | C81: Textos-padrão - incluir | H81: EE | I81: I | J81: 5 | K81: 2 | L81: =CONCATENATE(H81,M81) | M81: =IF(OR(ISBLANK(J81),ISBLANK(K81)),IF(OR(H81="ALI",H81="AIE"),"L",IF(ISBLANK(H81),"","A")),IF(H81="EE",IF(K81>=3,IF(J81>=5,"H","A"),IF(K81>=2,IF(J81>=16,"H",IF(J81<=4,"L","A")),IF(J81<=15,"L","A"))),IF(OR(H81="SE",H81="CE"),IF(K81>=4,IF(J81>=6,"H","A"),IF(K81>=2,IF(J81>=20,"H",IF(J81<=5,"L","A")),IF(J81<=19,"L","A"))),IF(OR(H81="ALI",H81="AIE"),IF(K81>=6,IF(J81>=20,"H","A"),IF(K81>=2,IF(J81>=51,"H",IF(J81<=19,"L","A")),IF(J81<=50,"L","A"))))))) | N81: =IF(M81="L","Baixa",IF(M81="A","Média",IF(M81="","","Alta"))) | O81: =IF(ISBLANK(H81),"",IF(H81="ALI",IF(M81="L",7,IF(M81="A",10,15)),IF(H81="AIE",IF(M81="L",5,IF(M81="A",7,10)),IF(H81="SE",IF(M81="L",4,IF(M81="A",5,7)),IF(OR(H81="EE",H81="CE"),IF(M81="L",3,IF(M81="A",4,6))))))) | P81: =IF(I81="I",O81*Contagem!$W$15,IF(I81="E",O81*Contagem!$W$17,IF(I81="A",O81*Contagem!$W$16,IF(I81="T",O81*Contagem!$W$18,"")))) | Q81: Prova: Rota POST /gestao/textos-padrao (permissão manter-parametros). Tela: gestao/textos-padrao/index. O gestor cadastra o texto (StandardTextRequest: categoria, conteúdo, situação). Grava Texto-padrão com versão 1 e a Trilha de auditoria. Teste: tests/Feature/Analise/StandardTextCrudTest.php::test_cria_texto_padrao_versao_inicial_1_auditado. Processo elementar independente: menor unidade com significado para o gestor; completa por si (informa o texto e recebe a confirmação); deixa o negócio consistente (texto disponível no parecer, auditado); lógica única (inclusão com versão inicial). Classificação: mantém ALI, EE. TD=5 (categoria, conteúdo, situação, mensagem, ação salvar). AR=2 (Texto-padrão, Trilha de auditoria). Registros automáticos contados como FTR (premissa P4): Trilha de auditoria. Recontagem 16/10/2026: alterada (linha 385 da contagem de 01/10/2026: "Textos-padrão - incluir", EE Baixa 3 PF, TD 5, AR 1). Motivo: AR 1→2: o controller grava a Trilha de auditoria (AuditService, ação criar). PF 3→4 (EE Média).
A82: =IF(H82="",IF(C82="",A81,A81+1),A81) | B82: =IF(A82=A81,"",CONCATENATE("F",A82)) | C82: Textos-padrão - alterar | H82: EE | I82: I | J82: 6 | K82: 2 | L82: =CONCATENATE(H82,M82) | M82: =IF(OR(ISBLANK(J82),ISBLANK(K82)),IF(OR(H82="ALI",H82="AIE"),"L",IF(ISBLANK(H82),"","A")),IF(H82="EE",IF(K82>=3,IF(J82>=5,"H","A"),IF(K82>=2,IF(J82>=16,"H",IF(J82<=4,"L","A")),IF(J82<=15,"L","A"))),IF(OR(H82="SE",H82="CE"),IF(K82>=4,IF(J82>=6,"H","A"),IF(K82>=2,IF(J82>=20,"H",IF(J82<=5,"L","A")),IF(J82<=19,"L","A"))),IF(OR(H82="ALI",H82="AIE"),IF(K82>=6,IF(J82>=20,"H","A"),IF(K82>=2,IF(J82>=51,"H",IF(J82<=19,"L","A")),IF(J82<=50,"L","A"))))))) | N82: =IF(M82="L","Baixa",IF(M82="A","Média",IF(M82="","","Alta"))) | O82: =IF(ISBLANK(H82),"",IF(H82="ALI",IF(M82="L",7,IF(M82="A",10,15)),IF(H82="AIE",IF(M82="L",5,IF(M82="A",7,10)),IF(H82="SE",IF(M82="L",4,IF(M82="A",5,7)),IF(OR(H82="EE",H82="CE"),IF(M82="L",3,IF(M82="A",4,6))))))) | P82: =IF(I82="I",O82*Contagem!$W$15,IF(I82="E",O82*Contagem!$W$17,IF(I82="A",O82*Contagem!$W$16,IF(I82="T",O82*Contagem!$W$18,"")))) | Q82: Prova: Rota PUT /gestao/textos-padrao/{standardText} (permissão manter-parametros). Tela: gestao/textos-padrao/index. O gestor edita o texto. Grava Texto-padrão (a versão sobe só quando o conteúdo muda) e a Trilha de auditoria. Teste: tests/Feature/Analise/StandardTextCrudTest.php::test_editar_conteudo_incrementa_versao. Processo elementar independente: menor unidade com significado para o gestor; completa por si (altera e recebe a confirmação); deixa o negócio consistente (versão rastreável); lógica única (versionamento por mudança de conteúdo). Classificação: mantém ALI, EE. TD=6 (categoria, conteúdo, situação, versão, mensagem, ação salvar). AR=2 (Texto-padrão, Trilha de auditoria). Registros automáticos contados como FTR (premissa P4): Trilha de auditoria. Recontagem 16/10/2026: alterada (linha 386 da contagem de 01/10/2026: "Textos-padrão - alterar", EE Baixa 3 PF, TD 6, AR 1). Motivo: AR 1→2: o controller grava a Trilha de auditoria (AuditService, ação atualizar). PF 3→4 (EE Média).
A83: =IF(H83="",IF(C83="",A82,A82+1),A82) | B83: =IF(A83=A82,"",CONCATENATE("F",A83)) | C83: Textos-padrão - ativar ou inativar | H83: EE | I83: I | J83: 4 | K83: 2 | L83: =CONCATENATE(H83,M83) | M83: =IF(OR(ISBLANK(J83),ISBLANK(K83)),IF(OR(H83="ALI",H83="AIE"),"L",IF(ISBLANK(H83),"","A")),IF(H83="EE",IF(K83>=3,IF(J83>=5,"H","A"),IF(K83>=2,IF(J83>=16,"H",IF(J83<=4,"L","A")),IF(J83<=15,"L","A"))),IF(OR(H83="SE",H83="CE"),IF(K83>=4,IF(J83>=6,"H","A"),IF(K83>=2,IF(J83>=20,"H",IF(J83<=5,"L","A")),IF(J83<=19,"L","A"))),IF(OR(H83="ALI",H83="AIE"),IF(K83>=6,IF(J83>=20,"H","A"),IF(K83>=2,IF(J83>=51,"H",IF(J83<=19,"L","A")),IF(J83<=50,"L","A"))))))) | N83: =IF(M83="L","Baixa",IF(M83="A","Média",IF(M83="","","Alta"))) | O83: =IF(ISBLANK(H83),"",IF(H83="ALI",IF(M83="L",7,IF(M83="A",10,15)),IF(H83="AIE",IF(M83="L",5,IF(M83="A",7,10)),IF(H83="SE",IF(M83="L",4,IF(M83="A",5,7)),IF(OR(H83="EE",H83="CE"),IF(M83="L",3,IF(M83="A",4,6))))))) | P83: =IF(I83="I",O83*Contagem!$W$15,IF(I83="E",O83*Contagem!$W$17,IF(I83="A",O83*Contagem!$W$16,IF(I83="T",O83*Contagem!$W$18,"")))) | Q83: Prova: Rota PUT /gestao/textos-padrao/{standardText}/ativacao (permissão manter-parametros). Tela: gestao/textos-padrao/index. O gestor ativa ou desativa sem excluir. Grava a situação do Texto-padrão e a Trilha de auditoria; a ficha passa a oferecer só os ativos. Teste: tests/Feature/Analise/StandardTextCrudTest.php::test_toggle_desativa_sem_excluir. Processo elementar independente: menor unidade com significado para o gestor; completa por si (alterna e recebe a confirmação); deixa o negócio consistente (texto preservado); lógica única (controle de disponibilidade na ficha). Classificação: mantém ALI, EE. TD=4 (texto-padrão, situação, mensagem, ação ativar/inativar). AR=2 (Texto-padrão, Trilha de auditoria). Registros automáticos contados como FTR (premissa P4): Trilha de auditoria. Recontagem 16/10/2026: alterada (linha 387 da contagem de 01/10/2026: "Textos-padrão - ativar ou inativar", EE Baixa 3 PF, TD 4, AR 1). Motivo: AR 1→2: o controller grava a Trilha de auditoria (AuditService, ação ativacao). PF inalterado (EE Baixa).
A84: =IF(H84="",IF(C84="",A83,A83+1),A83) | B84: =IF(A84=A83,"",CONCATENATE("F",A84)) | L84: =CONCATENATE(H84,M84) | M84: =IF(OR(ISBLANK(J84),ISBLANK(K84)),IF(OR(H84="ALI",H84="AIE"),"L",IF(ISBLANK(H84),"","A")),IF(H84="EE",IF(K84>=3,IF(J84>=5,"H","A"),IF(K84>=2,IF(J84>=16,"H",IF(J84<=4,"L","A")),IF(J84<=15,"L","A"))),IF(OR(H84="SE",H84="CE"),IF(K84>=4,IF(J84>=6,"H","A"),IF(K84>=2,IF(J84>=20,"H",IF(J84<=5,"L","A")),IF(J84<=19,"L","A"))),IF(OR(H84="ALI",H84="AIE"),IF(K84>=6,IF(J84>=20,"H","A"),IF(K84>=2,IF(J84>=51,"H",IF(J84<=19,"L","A")),IF(J84<=50,"L","A"))))))) | N84: =IF(M84="L","Baixa",IF(M84="A","Média",IF(M84="","","Alta"))) | O84: =IF(ISBLANK(H84),"",IF(H84="ALI",IF(M84="L",7,IF(M84="A",10,15)),IF(H84="AIE",IF(M84="L",5,IF(M84="A",7,10)),IF(H84="SE",IF(M84="L",4,IF(M84="A",5,7)),IF(OR(H84="EE",H84="CE"),IF(M84="L",3,IF(M84="A",4,6))))))) | P84: =IF(I84="I",O84*Contagem!$W$15,IF(I84="E",O84*Contagem!$W$17,IF(I84="A",O84*Contagem!$W$16,IF(I84="T",O84*Contagem!$W$18,""))))
A85: =IF(H85="",IF(C85="",A84,A84+1),A84) | B85: =IF(A85=A84,"",CONCATENATE("F",A85)) | C85: Textos decisórios | L85: =CONCATENATE(H85,M85) | M85: =IF(OR(ISBLANK(J85),ISBLANK(K85)),IF(OR(H85="ALI",H85="AIE"),"L",IF(ISBLANK(H85),"","A")),IF(H85="EE",IF(K85>=3,IF(J85>=5,"H","A"),IF(K85>=2,IF(J85>=16,"H",IF(J85<=4,"L","A")),IF(J85<=15,"L","A"))),IF(OR(H85="SE",H85="CE"),IF(K85>=4,IF(J85>=6,"H","A"),IF(K85>=2,IF(J85>=20,"H",IF(J85<=5,"L","A")),IF(J85<=19,"L","A"))),IF(OR(H85="ALI",H85="AIE"),IF(K85>=6,IF(J85>=20,"H","A"),IF(K85>=2,IF(J85>=51,"H",IF(J85<=19,"L","A")),IF(J85<=50,"L","A"))))))) | N85: =IF(M85="L","Baixa",IF(M85="A","Média",IF(M85="","","Alta"))) | O85: =IF(ISBLANK(H85),"",IF(H85="ALI",IF(M85="L",7,IF(M85="A",10,15)),IF(H85="AIE",IF(M85="L",5,IF(M85="A",7,10)),IF(H85="SE",IF(M85="L",4,IF(M85="A",5,7)),IF(OR(H85="EE",H85="CE"),IF(M85="L",3,IF(M85="A",4,6))))))) | P85: =IF(I85="I",O85*Contagem!$W$15,IF(I85="E",O85*Contagem!$W$17,IF(I85="A",O85*Contagem!$W$16,IF(I85="T",O85*Contagem!$W$18,""))))
A86: =IF(H86="",IF(C86="",A85,A85+1),A85) | B86: =IF(A86=A85,"",CONCATENATE("F",A86)) | C86: Dados - Texto decisório | H86: ALI | I86: I | J86: 3 | K86: 1 | L86: =CONCATENATE(H86,M86) | M86: =IF(OR(ISBLANK(J86),ISBLANK(K86)),IF(OR(H86="ALI",H86="AIE"),"L",IF(ISBLANK(H86),"","A")),IF(H86="EE",IF(K86>=3,IF(J86>=5,"H","A"),IF(K86>=2,IF(J86>=16,"H",IF(J86<=4,"L","A")),IF(J86<=15,"L","A"))),IF(OR(H86="SE",H86="CE"),IF(K86>=4,IF(J86>=6,"H","A"),IF(K86>=2,IF(J86>=20,"H",IF(J86<=5,"L","A")),IF(J86<=19,"L","A"))),IF(OR(H86="ALI",H86="AIE"),IF(K86>=6,IF(J86>=20,"H","A"),IF(K86>=2,IF(J86>=51,"H",IF(J86<=19,"L","A")),IF(J86<=50,"L","A"))))))) | N86: =IF(M86="L","Baixa",IF(M86="A","Média",IF(M86="","","Alta"))) | O86: =IF(ISBLANK(H86),"",IF(H86="ALI",IF(M86="L",7,IF(M86="A",10,15)),IF(H86="AIE",IF(M86="L",5,IF(M86="A",7,10)),IF(H86="SE",IF(M86="L",4,IF(M86="A",5,7)),IF(OR(H86="EE",H86="CE"),IF(M86="L",3,IF(M86="A",4,6))))))) | P86: =IF(I86="I",O86*Contagem!$W$15,IF(I86="E",O86*Contagem!$W$17,IF(I86="A",O86*Contagem!$W$16,IF(I86="T",O86*Contagem!$W$18,"")))) | Q86: Prova: Model app/Models/DecisionText.php (HasAuditoria); migration database/migrations/2026_09_18_163000_create_decision_texts_table.php (key, template, description). Mantido por DecisionTextController@update (sem inclusão nem exclusão por tela; as chaves vêm do motor e do seeder) e lido por app/Services/Decisao/DecisionTextCatalog.php (motor LOUOS, risco, indeferimento por prazo). Teste: tests/Feature/Decisao/DecisionTextCrudTest.php::test_edicao_do_template_persiste_e_o_motor_emite_o_novo_texto. Arquivo lógico: textos legais emitidos nas decisões e documentos oficiais (base legal, LOUOS, análise, territorial, zona, tratamento, expresso), alteráveis sem deploy. Não é dado de código (Parte 1 §5.4.2 d; Parte 3 Cap. 1): o atributo mantido é o próprio conteúdo jurídico emitido ao requerente, não a tradução de um código; alterar o texto muda o que a decisão diz. A chave é técnica e deixou de ser exibida (commit 73c9c405); o usuário reconhece o texto pelo grupo. TD=3 (grupo do texto, texto emitido, descrição e placeholders). TR=1 (Texto decisório). Recontagem 16/10/2026: mantida (linha 455 da contagem de 01/10/2026).
A87: =IF(H87="",IF(C87="",A86,A86+1),A86) | B87: =IF(A87=A86,"",CONCATENATE("F",A87)) | C87: Textos decisórios - consultar | H87: CE | I87: I | J87: 4 | K87: 1 | L87: =CONCATENATE(H87,M87) | M87: =IF(OR(ISBLANK(J87),ISBLANK(K87)),IF(OR(H87="ALI",H87="AIE"),"L",IF(ISBLANK(H87),"","A")),IF(H87="EE",IF(K87>=3,IF(J87>=5,"H","A"),IF(K87>=2,IF(J87>=16,"H",IF(J87<=4,"L","A")),IF(J87<=15,"L","A"))),IF(OR(H87="SE",H87="CE"),IF(K87>=4,IF(J87>=6,"H","A"),IF(K87>=2,IF(J87>=20,"H",IF(J87<=5,"L","A")),IF(J87<=19,"L","A"))),IF(OR(H87="ALI",H87="AIE"),IF(K87>=6,IF(J87>=20,"H","A"),IF(K87>=2,IF(J87>=51,"H",IF(J87<=19,"L","A")),IF(J87<=50,"L","A"))))))) | N87: =IF(M87="L","Baixa",IF(M87="A","Média",IF(M87="","","Alta"))) | O87: =IF(ISBLANK(H87),"",IF(H87="ALI",IF(M87="L",7,IF(M87="A",10,15)),IF(H87="AIE",IF(M87="L",5,IF(M87="A",7,10)),IF(H87="SE",IF(M87="L",4,IF(M87="A",5,7)),IF(OR(H87="EE",H87="CE"),IF(M87="L",3,IF(M87="A",4,6))))))) | P87: =IF(I87="I",O87*Contagem!$W$15,IF(I87="E",O87*Contagem!$W$17,IF(I87="A",O87*Contagem!$W$16,IF(I87="T",O87*Contagem!$W$18,"")))) | Q87: Prova: Rota GET /gestao/textos-decisao (permissão manter-parametros). Tela: gestao/textos-decisao/index. O gestor abre os textos agrupados pelo prefixo da chave, com rótulo amigável do grupo. Lê Texto decisório; não grava. Teste: tests/Feature/Decisao/DecisionTextCrudTest.php::test_lista_agrupa_os_textos_por_prefixo_da_chave. Processo elementar independente: menor unidade com significado para o gestor; completa por si (abertura até a lista agrupada); deixa o negócio consistente (nada muda); lógica única (recuperação dos textos por grupo, sem cálculo). Classificação: CE (§5.5.3). TD=4 (grupo, texto emitido, descrição e placeholders, ação de consultar). AR=1 (Texto decisório). Recontagem 16/10/2026: alterada (linha 456 da contagem de 01/10/2026: "Textos decisórios - consultar", CE Baixa 3 PF, TD 5, AR 1). Motivo: TD 5→4: a chave deixou de ser exibida (commit 73c9c405, chave técnica); o usuário vê grupo, texto e descrição. PF inalterado (CE Baixa).
A88: =IF(H88="",IF(C88="",A87,A87+1),A87) | B88: =IF(A88=A87,"",CONCATENATE("F",A88)) | C88: Textos decisórios - alterar | H88: EE | I88: I | J88: 4 | K88: 2 | L88: =CONCATENATE(H88,M88) | M88: =IF(OR(ISBLANK(J88),ISBLANK(K88)),IF(OR(H88="ALI",H88="AIE"),"L",IF(ISBLANK(H88),"","A")),IF(H88="EE",IF(K88>=3,IF(J88>=5,"H","A"),IF(K88>=2,IF(J88>=16,"H",IF(J88<=4,"L","A")),IF(J88<=15,"L","A"))),IF(OR(H88="SE",H88="CE"),IF(K88>=4,IF(J88>=6,"H","A"),IF(K88>=2,IF(J88>=20,"H",IF(J88<=5,"L","A")),IF(J88<=19,"L","A"))),IF(OR(H88="ALI",H88="AIE"),IF(K88>=6,IF(J88>=20,"H","A"),IF(K88>=2,IF(J88>=51,"H",IF(J88<=19,"L","A")),IF(J88<=50,"L","A"))))))) | N88: =IF(M88="L","Baixa",IF(M88="A","Média",IF(M88="","","Alta"))) | O88: =IF(ISBLANK(H88),"",IF(H88="ALI",IF(M88="L",7,IF(M88="A",10,15)),IF(H88="AIE",IF(M88="L",5,IF(M88="A",7,10)),IF(H88="SE",IF(M88="L",4,IF(M88="A",5,7)),IF(OR(H88="EE",H88="CE"),IF(M88="L",3,IF(M88="A",4,6))))))) | P88: =IF(I88="I",O88*Contagem!$W$15,IF(I88="E",O88*Contagem!$W$17,IF(I88="A",O88*Contagem!$W$16,IF(I88="T",O88*Contagem!$W$18,"")))) | Q88: Prova: Rota PUT /gestao/textos-decisao/{decisionText:key} (permissão manter-parametros). Tela: gestao/textos-decisao/index. O gestor altera texto e descrição (obrigatórios, UpdateDecisionTextRequest). Grava Texto decisório e Trilha de auditoria (HasAuditoria). Resultado: o motor passa a emitir o novo texto. Teste: tests/Feature/Decisao/DecisionTextCrudTest.php::test_edicao_do_template_persiste_e_o_motor_emite_o_novo_texto. Processo elementar independente: menor unidade com significado para o gestor; completa por si (edição até a gravação); deixa o negócio consistente (texto novo vigente e auditado); lógica única (alteração do texto). Classificação: mantém ALI, EE. TD=4 (texto emitido, descrição e placeholders, mensagem de sucesso/erro, ação de salvar). AR=2 (Texto decisório, Trilha de auditoria). Registros automáticos contados como FTR (premissa P4): Trilha de auditoria. Recontagem 16/10/2026: alterada (linha 457 da contagem de 01/10/2026: "Textos decisórios - alterar", EE Média 4 PF, TD 5, AR 2). Motivo: TD 5→4: a chave é identificador técnico na URL e não é exibida. PF 4→3 (EE Baixa).
A89: =IF(H89="",IF(C89="",A88,A88+1),A88) | B89: =IF(A89=A88,"",CONCATENATE("F",A89)) | L89: =CONCATENATE(H89,M89) | M89: =IF(OR(ISBLANK(J89),ISBLANK(K89)),IF(OR(H89="ALI",H89="AIE"),"L",IF(ISBLANK(H89),"","A")),IF(H89="EE",IF(K89>=3,IF(J89>=5,"H","A"),IF(K89>=2,IF(J89>=16,"H",IF(J89<=4,"L","A")),IF(J89<=15,"L","A"))),IF(OR(H89="SE",H89="CE"),IF(K89>=4,IF(J89>=6,"H","A"),IF(K89>=2,IF(J89>=20,"H",IF(J89<=5,"L","A")),IF(J89<=19,"L","A"))),IF(OR(H89="ALI",H89="AIE"),IF(K89>=6,IF(J89>=20,"H","A"),IF(K89>=2,IF(J89>=51,"H",IF(J89<=19,"L","A")),IF(J89<=50,"L","A"))))))) | N89: =IF(M89="L","Baixa",IF(M89="A","Média",IF(M89="","","Alta"))) | O89: =IF(ISBLANK(H89),"",IF(H89="ALI",IF(M89="L",7,IF(M89="A",10,15)),IF(H89="AIE",IF(M89="L",5,IF(M89="A",7,10)),IF(H89="SE",IF(M89="L",4,IF(M89="A",5,7)),IF(OR(H89="EE",H89="CE"),IF(M89="L",3,IF(M89="A",4,6))))))) | P89: =IF(I89="I",O89*Contagem!$W$15,IF(I89="E",O89*Contagem!$W$17,IF(I89="A",O89*Contagem!$W$16,IF(I89="T",O89*Contagem!$W$18,""))))
A90: =IF(H90="",IF(C90="",A89,A89+1),A89) | B90: =IF(A90=A89,"",CONCATENATE("F",A90)) | C90: Parâmetros do sistema | L90: =CONCATENATE(H90,M90) | M90: =IF(OR(ISBLANK(J90),ISBLANK(K90)),IF(OR(H90="ALI",H90="AIE"),"L",IF(ISBLANK(H90),"","A")),IF(H90="EE",IF(K90>=3,IF(J90>=5,"H","A"),IF(K90>=2,IF(J90>=16,"H",IF(J90<=4,"L","A")),IF(J90<=15,"L","A"))),IF(OR(H90="SE",H90="CE"),IF(K90>=4,IF(J90>=6,"H","A"),IF(K90>=2,IF(J90>=20,"H",IF(J90<=5,"L","A")),IF(J90<=19,"L","A"))),IF(OR(H90="ALI",H90="AIE"),IF(K90>=6,IF(J90>=20,"H","A"),IF(K90>=2,IF(J90>=51,"H",IF(J90<=19,"L","A")),IF(J90<=50,"L","A"))))))) | N90: =IF(M90="L","Baixa",IF(M90="A","Média",IF(M90="","","Alta"))) | O90: =IF(ISBLANK(H90),"",IF(H90="ALI",IF(M90="L",7,IF(M90="A",10,15)),IF(H90="AIE",IF(M90="L",5,IF(M90="A",7,10)),IF(H90="SE",IF(M90="L",4,IF(M90="A",5,7)),IF(OR(H90="EE",H90="CE"),IF(M90="L",3,IF(M90="A",4,6))))))) | P90: =IF(I90="I",O90*Contagem!$W$15,IF(I90="E",O90*Contagem!$W$17,IF(I90="A",O90*Contagem!$W$16,IF(I90="T",O90*Contagem!$W$18,""))))
A91: =IF(H91="",IF(C91="",A90,A90+1),A90) | B91: =IF(A91=A90,"",CONCATENATE("F",A91)) | C91: Dados - Parâmetro | H91: ALI | I91: I | J91: 15 | K91: 2 | L91: =CONCATENATE(H91,M91) | M91: =IF(OR(ISBLANK(J91),ISBLANK(K91)),IF(OR(H91="ALI",H91="AIE"),"L",IF(ISBLANK(H91),"","A")),IF(H91="EE",IF(K91>=3,IF(J91>=5,"H","A"),IF(K91>=2,IF(J91>=16,"H",IF(J91<=4,"L","A")),IF(J91<=15,"L","A"))),IF(OR(H91="SE",H91="CE"),IF(K91>=4,IF(J91>=6,"H","A"),IF(K91>=2,IF(J91>=20,"H",IF(J91<=5,"L","A")),IF(J91<=19,"L","A"))),IF(OR(H91="ALI",H91="AIE"),IF(K91>=6,IF(J91>=20,"H","A"),IF(K91>=2,IF(J91>=51,"H",IF(J91<=19,"L","A")),IF(J91<=50,"L","A"))))))) | N91: =IF(M91="L","Baixa",IF(M91="A","Média",IF(M91="","","Alta"))) | O91: =IF(ISBLANK(H91),"",IF(H91="ALI",IF(M91="L",7,IF(M91="A",10,15)),IF(H91="AIE",IF(M91="L",5,IF(M91="A",7,10)),IF(H91="SE",IF(M91="L",4,IF(M91="A",5,7)),IF(OR(H91="EE",H91="CE"),IF(M91="L",3,IF(M91="A",4,6))))))) | P91: =IF(I91="I",O91*Contagem!$W$15,IF(I91="E",O91*Contagem!$W$17,IF(I91="A",O91*Contagem!$W$16,IF(I91="T",O91*Contagem!$W$18,"")))) | Q91: Prova: Models Parameter e ParameterProposal; migrations 2026_06_10_141916_create_parameters_table, 2026_09_18_180000_add_governance_to_parameters_table e 2026_09_18_180001_create_parameter_proposals_table. Mantido por ParameterController@update, approve e reject (ParameterChangeService) e pelas abas de ApiIntegracaoController@update. Arquivo lógico: catálogo de parâmetros reconhecido pelo gestor, que muda prazo, taxa, interruptores e integrações sem deploy; não é dado de código porque o valor altera o comportamento do sistema. A proposta de alteração (quatro olhos) só existe com o parâmetro e tem atributos próprios: subgrupo (RLR). Parâmetros novos desde 01/10/2026 (features.geoserver_enderecamento, features.arcgis_semap, integrations.arcgis_semap.query_url e .token, features.benchmark_redesim, integrations.redesim_estatistica.base_url, portal.perfil_cidadao, integrations.regin.caminho_resposta e .codigo_area, e features.portal_servicos, commit df19754c) são linhas do mesmo grupo, não atributos: não mudam DER nem RLR. O interruptor portal_solicitacao fica só em config/viabiliza.php (variável de ambiente), fora do ALI. Teste: tests/Feature/Parameters/ManageParametersTest.php::test_atualiza_parametro_valido. TD=15 (chave, grupo, tipo, valor, valor padrão, regras de validação, sensível, descrição, exige teste de conexão, governança, valor proposto, proposto por, situação da proposta, revisado por, revisado em). TR=2 (Parâmetro, Proposta de alteração). Recontagem 16/10/2026: mantida (linha 234 da contagem de 01/10/2026).
A92: =IF(H92="",IF(C92="",A91,A91+1),A91) | B92: =IF(A92=A91,"",CONCATENATE("F",A92)) | C92: Parâmetros - consultar | H92: CE | I92: I | J92: 11 | K92: 2 | L92: =CONCATENATE(H92,M92) | M92: =IF(OR(ISBLANK(J92),ISBLANK(K92)),IF(OR(H92="ALI",H92="AIE"),"L",IF(ISBLANK(H92),"","A")),IF(H92="EE",IF(K92>=3,IF(J92>=5,"H","A"),IF(K92>=2,IF(J92>=16,"H",IF(J92<=4,"L","A")),IF(J92<=15,"L","A"))),IF(OR(H92="SE",H92="CE"),IF(K92>=4,IF(J92>=6,"H","A"),IF(K92>=2,IF(J92>=20,"H",IF(J92<=5,"L","A")),IF(J92<=19,"L","A"))),IF(OR(H92="ALI",H92="AIE"),IF(K92>=6,IF(J92>=20,"H","A"),IF(K92>=2,IF(J92>=51,"H",IF(J92<=19,"L","A")),IF(J92<=50,"L","A"))))))) | N92: =IF(M92="L","Baixa",IF(M92="A","Média",IF(M92="","","Alta"))) | O92: =IF(ISBLANK(H92),"",IF(H92="ALI",IF(M92="L",7,IF(M92="A",10,15)),IF(H92="AIE",IF(M92="L",5,IF(M92="A",7,10)),IF(H92="SE",IF(M92="L",4,IF(M92="A",5,7)),IF(OR(H92="EE",H92="CE"),IF(M92="L",3,IF(M92="A",4,6))))))) | P92: =IF(I92="I",O92*Contagem!$W$15,IF(I92="E",O92*Contagem!$W$17,IF(I92="A",O92*Contagem!$W$16,IF(I92="T",O92*Contagem!$W$18,"")))) | Q92: Prova: Rota GET /gestao/parametros (manter-parametros). Tela: gestao/parametros/index. Lista os parâmetros agrupados (grupos em abas da mesma resposta), com valor nulo quando sensível, selo de administrado e decisório, e a proposta pendente com autor. Lê Parâmetro (com propostas) e Usuário (autor). A exportação por ?formato= não tem botão na tela (ver pendências). Teste: tests/Feature/Parameters/ManageParametersTest.php::test_administrador_ve_parametros_agrupados e ParameterFourEyesTest.php::test_index_traz_governanca_proposta_e_can_approve. Processo elementar independente: menor unidade com significado para o gestor; completa por si (abre e consulta); não grava; lógica única de leitura do catálogo agrupado. Classificação: CE, só recupera e apresenta, sem cálculo nem atualização (§5.5.3). TD=11 (grupo, descrição, valor, valor padrão, administrado, decisório, valor proposto, autor da proposta, aguardando segundo aprovador, exige teste de conexão, ação). AR=2 (Parâmetro, Usuário). Recontagem 16/10/2026: alterada (linha 235 da contagem de 01/10/2026: "Parâmetros - consultar", CE Média 4 PF, TD 13, AR 2). Motivo: TD 13 para 11: a chave técnica deixou de ser exibida (commit 73c9c405, 14/10/2026) e não existe campo de busca na tela; PF inalterado.
A93: =IF(H93="",IF(C93="",A92,A92+1),A92) | B93: =IF(A93=A92,"",CONCATENATE("F",A93)) | C93: Parâmetros - alterar | H93: EE | I93: I | J93: 4 | K93: 3 | L93: =CONCATENATE(H93,M93) | M93: =IF(OR(ISBLANK(J93),ISBLANK(K93)),IF(OR(H93="ALI",H93="AIE"),"L",IF(ISBLANK(H93),"","A")),IF(H93="EE",IF(K93>=3,IF(J93>=5,"H","A"),IF(K93>=2,IF(J93>=16,"H",IF(J93<=4,"L","A")),IF(J93<=15,"L","A"))),IF(OR(H93="SE",H93="CE"),IF(K93>=4,IF(J93>=6,"H","A"),IF(K93>=2,IF(J93>=20,"H",IF(J93<=5,"L","A")),IF(J93<=19,"L","A"))),IF(OR(H93="ALI",H93="AIE"),IF(K93>=6,IF(J93>=20,"H","A"),IF(K93>=2,IF(J93>=51,"H",IF(J93<=19,"L","A")),IF(J93<=50,"L","A"))))))) | N93: =IF(M93="L","Baixa",IF(M93="A","Média",IF(M93="","","Alta"))) | O93: =IF(ISBLANK(H93),"",IF(H93="ALI",IF(M93="L",7,IF(M93="A",10,15)),IF(H93="AIE",IF(M93="L",5,IF(M93="A",7,10)),IF(H93="SE",IF(M93="L",4,IF(M93="A",5,7)),IF(OR(H93="EE",H93="CE"),IF(M93="L",3,IF(M93="A",4,6))))))) | P93: =IF(I93="I",O93*Contagem!$W$15,IF(I93="E",O93*Contagem!$W$17,IF(I93="A",O93*Contagem!$W$16,IF(I93="T",O93*Contagem!$W$18,"")))) | Q93: Prova: Rota PUT /gestao/parametros/{chave} (manter-parametros). Tela: gestao/parametros/index. O gestor altera o valor; UpdateParameterRequest valida pelas regras do catálogo e, para portal.perfil_cidadao, recusa perfil com acesso à gestão (PerfilSemAcessoAGestao lê o perfil e suas permissões); parâmetro operacional é aplicado e auditado com valor anterior e novo; parâmetro decisório vira proposta pendente (ParameterChangeService@propose). Sensível em branco mantém o valor. Teste: tests/Feature/Parameters/ManageParametersTest.php::test_alteracao_e_auditada_com_valor_anterior_e_novo e ::test_perfil_do_cidadao_com_acesso_a_gestao_e_rejeitado; ParameterFourEyesTest.php::test_put_em_decisorio_abre_proposta_sem_aplicar. Processo elementar independente: menor unidade com significado para o gestor; completa por si (edita e salva); deixa o parâmetro aplicado ou proposto; lógica única de alteração validada. Classificação: EE, intenção primária é manter o ALI Parâmetro (§5.5.3). TD=4 (parâmetro, valor, mensagem, ação). AR=3 (Parâmetro, Trilha de auditoria, Perfil de acesso). Recontagem 16/10/2026: alterada (linha 236 da contagem de 01/10/2026: "Parâmetros - alterar", EE Baixa 3 PF, TD 4, AR 2). Motivo: AR 2 para 3: desde 14/10/2026 (commit 78cf5671) a validação do parâmetro portal.perfil_cidadao lê o perfil e suas permissões (regra app/Rules/PerfilSemAcessoAGestao.php, Role::query e permissions), dado do ALI Perfil de acesso. PF 3 para 4.
A94: =IF(H94="",IF(C94="",A93,A93+1),A93) | B94: =IF(A94=A93,"",CONCATENATE("F",A94)) | C94: Parâmetros - consultar histórico | H94: CE | I94: I | J94: 6 | K94: 3 | L94: =CONCATENATE(H94,M94) | M94: =IF(OR(ISBLANK(J94),ISBLANK(K94)),IF(OR(H94="ALI",H94="AIE"),"L",IF(ISBLANK(H94),"","A")),IF(H94="EE",IF(K94>=3,IF(J94>=5,"H","A"),IF(K94>=2,IF(J94>=16,"H",IF(J94<=4,"L","A")),IF(J94<=15,"L","A"))),IF(OR(H94="SE",H94="CE"),IF(K94>=4,IF(J94>=6,"H","A"),IF(K94>=2,IF(J94>=20,"H",IF(J94<=5,"L","A")),IF(J94<=19,"L","A"))),IF(OR(H94="ALI",H94="AIE"),IF(K94>=6,IF(J94>=20,"H","A"),IF(K94>=2,IF(J94>=51,"H",IF(J94<=19,"L","A")),IF(J94<=50,"L","A"))))))) | N94: =IF(M94="L","Baixa",IF(M94="A","Média",IF(M94="","","Alta"))) | O94: =IF(ISBLANK(H94),"",IF(H94="ALI",IF(M94="L",7,IF(M94="A",10,15)),IF(H94="AIE",IF(M94="L",5,IF(M94="A",7,10)),IF(H94="SE",IF(M94="L",4,IF(M94="A",5,7)),IF(OR(H94="EE",H94="CE"),IF(M94="L",3,IF(M94="A",4,6))))))) | P94: =IF(I94="I",O94*Contagem!$W$15,IF(I94="E",O94*Contagem!$W$17,IF(I94="A",O94*Contagem!$W$16,IF(I94="T",O94*Contagem!$W$18,"")))) | Q94: Prova: Rota GET /gestao/parametros/{chave}/historico (manter-parametros). Tela: gestao/parametros/historico. O controller lê a trilha de auditoria do parâmetro e mostra valor anterior, novo (mascarados se sensível), responsável e data, sem gravar. Teste: tests/Feature/Parameters/ParameterHistoryTest.php::test_historico_exibe_anterior_novo_responsavel_e_data. Processo elementar independente: menor unidade com significado para o gestor; completa por si; não altera dados; lógica única de leitura das mudanças de um parâmetro. Classificação: CE, recupera e exibe sem cálculo nem derivação (§5.5.3). TD=6 (descrição do parâmetro, valor anterior, valor novo, responsável, data e hora, ação). AR=3 (Trilha de auditoria, Parâmetro, Usuário). Recontagem 16/10/2026: alterada (linha 237 da contagem de 01/10/2026: "Parâmetros - consultar histórico", CE Média 4 PF, TD 7, AR 3). Motivo: TD 7 para 6: a chave técnica deixou de aparecer no histórico (commit 73c9c405); PF inalterado.
A95: =IF(H95="",IF(C95="",A94,A94+1),A94) | B95: =IF(A95=A94,"",CONCATENATE("F",A95)) | C95: Parâmetros - aprovar alteração proposta | H95: EE | I95: I | J95: 3 | K95: 2 | L95: =CONCATENATE(H95,M95) | M95: =IF(OR(ISBLANK(J95),ISBLANK(K95)),IF(OR(H95="ALI",H95="AIE"),"L",IF(ISBLANK(H95),"","A")),IF(H95="EE",IF(K95>=3,IF(J95>=5,"H","A"),IF(K95>=2,IF(J95>=16,"H",IF(J95<=4,"L","A")),IF(J95<=15,"L","A"))),IF(OR(H95="SE",H95="CE"),IF(K95>=4,IF(J95>=6,"H","A"),IF(K95>=2,IF(J95>=20,"H",IF(J95<=5,"L","A")),IF(J95<=19,"L","A"))),IF(OR(H95="ALI",H95="AIE"),IF(K95>=6,IF(J95>=20,"H","A"),IF(K95>=2,IF(J95>=51,"H",IF(J95<=19,"L","A")),IF(J95<=50,"L","A"))))))) | N95: =IF(M95="L","Baixa",IF(M95="A","Média",IF(M95="","","Alta"))) | O95: =IF(ISBLANK(H95),"",IF(H95="ALI",IF(M95="L",7,IF(M95="A",10,15)),IF(H95="AIE",IF(M95="L",5,IF(M95="A",7,10)),IF(H95="SE",IF(M95="L",4,IF(M95="A",5,7)),IF(OR(H95="EE",H95="CE"),IF(M95="L",3,IF(M95="A",4,6))))))) | P95: =IF(I95="I",O95*Contagem!$W$15,IF(I95="E",O95*Contagem!$W$17,IF(I95="A",O95*Contagem!$W$16,IF(I95="T",O95*Contagem!$W$18,"")))) | Q95: Prova: Rota POST /gestao/parametros/{chave}/aprovar (manter-parametros). Tela: gestao/parametros/index (botão Aprovar, só para quem não é o autor). ParameterChangeService@approve recusa o autor (quatro olhos), aplica o valor, fecha a proposta como aprovada e audita. Teste: tests/Feature/Parameters/ParameterFourEyesTest.php::test_segundo_aprovador_aplica_e_audita e ::test_autor_nao_pode_aprovar. Processo elementar independente: menor unidade com significado para o aprovador; completa por si; deixa o parâmetro com o novo valor; lógica própria de quatro olhos. Classificação: EE, mantém o ALI Parâmetro (§5.5.3). TD=3 (proposta, mensagem, ação). AR=2 (Parâmetro, Trilha de auditoria). Recontagem 16/10/2026: mantida (linha 238 da contagem de 01/10/2026).
A96: =IF(H96="",IF(C96="",A95,A95+1),A95) | B96: =IF(A96=A95,"",CONCATENATE("F",A96)) | C96: Parâmetros - rejeitar alteração proposta | H96: EE | I96: I | J96: 3 | K96: 2 | L96: =CONCATENATE(H96,M96) | M96: =IF(OR(ISBLANK(J96),ISBLANK(K96)),IF(OR(H96="ALI",H96="AIE"),"L",IF(ISBLANK(H96),"","A")),IF(H96="EE",IF(K96>=3,IF(J96>=5,"H","A"),IF(K96>=2,IF(J96>=16,"H",IF(J96<=4,"L","A")),IF(J96<=15,"L","A"))),IF(OR(H96="SE",H96="CE"),IF(K96>=4,IF(J96>=6,"H","A"),IF(K96>=2,IF(J96>=20,"H",IF(J96<=5,"L","A")),IF(J96<=19,"L","A"))),IF(OR(H96="ALI",H96="AIE"),IF(K96>=6,IF(J96>=20,"H","A"),IF(K96>=2,IF(J96>=51,"H",IF(J96<=19,"L","A")),IF(J96<=50,"L","A"))))))) | N96: =IF(M96="L","Baixa",IF(M96="A","Média",IF(M96="","","Alta"))) | O96: =IF(ISBLANK(H96),"",IF(H96="ALI",IF(M96="L",7,IF(M96="A",10,15)),IF(H96="AIE",IF(M96="L",5,IF(M96="A",7,10)),IF(H96="SE",IF(M96="L",4,IF(M96="A",5,7)),IF(OR(H96="EE",H96="CE"),IF(M96="L",3,IF(M96="A",4,6))))))) | P96: =IF(I96="I",O96*Contagem!$W$15,IF(I96="E",O96*Contagem!$W$17,IF(I96="A",O96*Contagem!$W$16,IF(I96="T",O96*Contagem!$W$18,"")))) | Q96: Prova: Rota POST /gestao/parametros/{chave}/rejeitar (manter-parametros). Tela: gestao/parametros/index (botão Rejeitar). ParameterChangeService@reject encerra a proposta como rejeitada, preserva o valor vigente e audita. Teste: tests/Feature/Parameters/ParameterFourEyesTest.php::test_rejeitar_preserva_valor. Processo elementar independente: menor unidade com significado para o aprovador; completa por si; deixa a proposta encerrada; lógica própria de rejeição, distinta da aprovação (não aplica valor). Classificação: EE, mantém o ALI Parâmetro (§5.5.3). TD=3 (proposta, mensagem, ação). AR=2 (Parâmetro, Trilha de auditoria). Recontagem 16/10/2026: mantida (linha 239 da contagem de 01/10/2026).
A97: =IF(H97="",IF(C97="",A96,A96+1),A96) | B97: =IF(A97=A96,"",CONCATENATE("F",A97)) | L97: =CONCATENATE(H97,M97) | M97: =IF(OR(ISBLANK(J97),ISBLANK(K97)),IF(OR(H97="ALI",H97="AIE"),"L",IF(ISBLANK(H97),"","A")),IF(H97="EE",IF(K97>=3,IF(J97>=5,"H","A"),IF(K97>=2,IF(J97>=16,"H",IF(J97<=4,"L","A")),IF(J97<=15,"L","A"))),IF(OR(H97="SE",H97="CE"),IF(K97>=4,IF(J97>=6,"H","A"),IF(K97>=2,IF(J97>=20,"H",IF(J97<=5,"L","A")),IF(J97<=19,"L","A"))),IF(OR(H97="ALI",H97="AIE"),IF(K97>=6,IF(J97>=20,"H","A"),IF(K97>=2,IF(J97>=51,"H",IF(J97<=19,"L","A")),IF(J97<=50,"L","A"))))))) | N97: =IF(M97="L","Baixa",IF(M97="A","Média",IF(M97="","","Alta"))) | O97: =IF(ISBLANK(H97),"",IF(H97="ALI",IF(M97="L",7,IF(M97="A",10,15)),IF(H97="AIE",IF(M97="L",5,IF(M97="A",7,10)),IF(H97="SE",IF(M97="L",4,IF(M97="A",5,7)),IF(OR(H97="EE",H97="CE"),IF(M97="L",3,IF(M97="A",4,6))))))) | P97: =IF(I97="I",O97*Contagem!$W$15,IF(I97="E",O97*Contagem!$W$17,IF(I97="A",O97*Contagem!$W$16,IF(I97="T",O97*Contagem!$W$18,""))))
A98: =IF(H98="",IF(C98="",A97,A97+1),A97) | B98: =IF(A98=A97,"",CONCATENATE("F",A98)) | C98: Configuração das APIs | L98: =CONCATENATE(H98,M98) | M98: =IF(OR(ISBLANK(J98),ISBLANK(K98)),IF(OR(H98="ALI",H98="AIE"),"L",IF(ISBLANK(H98),"","A")),IF(H98="EE",IF(K98>=3,IF(J98>=5,"H","A"),IF(K98>=2,IF(J98>=16,"H",IF(J98<=4,"L","A")),IF(J98<=15,"L","A"))),IF(OR(H98="SE",H98="CE"),IF(K98>=4,IF(J98>=6,"H","A"),IF(K98>=2,IF(J98>=20,"H",IF(J98<=5,"L","A")),IF(J98<=19,"L","A"))),IF(OR(H98="ALI",H98="AIE"),IF(K98>=6,IF(J98>=20,"H","A"),IF(K98>=2,IF(J98>=51,"H",IF(J98<=19,"L","A")),IF(J98<=50,"L","A"))))))) | N98: =IF(M98="L","Baixa",IF(M98="A","Média",IF(M98="","","Alta"))) | O98: =IF(ISBLANK(H98),"",IF(H98="ALI",IF(M98="L",7,IF(M98="A",10,15)),IF(H98="AIE",IF(M98="L",5,IF(M98="A",7,10)),IF(H98="SE",IF(M98="L",4,IF(M98="A",5,7)),IF(OR(H98="EE",H98="CE"),IF(M98="L",3,IF(M98="A",4,6))))))) | P98: =IF(I98="I",O98*Contagem!$W$15,IF(I98="E",O98*Contagem!$W$17,IF(I98="A",O98*Contagem!$W$16,IF(I98="T",O98*Contagem!$W$18,""))))
A99: =IF(H99="",IF(C99="",A98,A98+1),A98) | B99: =IF(A99=A98,"",CONCATENATE("F",A99)) | C99: APIs - consultar configuração REGIN | H99: CE | I99: I | J99: 10 | K99: 1 | L99: =CONCATENATE(H99,M99) | M99: =IF(OR(ISBLANK(J99),ISBLANK(K99)),IF(OR(H99="ALI",H99="AIE"),"L",IF(ISBLANK(H99),"","A")),IF(H99="EE",IF(K99>=3,IF(J99>=5,"H","A"),IF(K99>=2,IF(J99>=16,"H",IF(J99<=4,"L","A")),IF(J99<=15,"L","A"))),IF(OR(H99="SE",H99="CE"),IF(K99>=4,IF(J99>=6,"H","A"),IF(K99>=2,IF(J99>=20,"H",IF(J99<=5,"L","A")),IF(J99<=19,"L","A"))),IF(OR(H99="ALI",H99="AIE"),IF(K99>=6,IF(J99>=20,"H","A"),IF(K99>=2,IF(J99>=51,"H",IF(J99<=19,"L","A")),IF(J99<=50,"L","A"))))))) | N99: =IF(M99="L","Baixa",IF(M99="A","Média",IF(M99="","","Alta"))) | O99: =IF(ISBLANK(H99),"",IF(H99="ALI",IF(M99="L",7,IF(M99="A",10,15)),IF(H99="AIE",IF(M99="L",5,IF(M99="A",7,10)),IF(H99="SE",IF(M99="L",4,IF(M99="A",5,7)),IF(OR(H99="EE",H99="CE"),IF(M99="L",3,IF(M99="A",4,6))))))) | P99: =IF(I99="I",O99*Contagem!$W$15,IF(I99="E",O99*Contagem!$W$17,IF(I99="A",O99*Contagem!$W$16,IF(I99="T",O99*Contagem!$W$18,"")))) | Q99: Prova: Rota GET /gestao/config-apis?aba=regin (manter-parametros). Tela: gestao/config-apis/index, aba REGIN (menu Configuração > APIs). O gestor abre a configuração da integração e vê os valores em uso, montados por ApiIntegracaoController@edit a partir dos parâmetros listados em ApiIntegracaoCatalog para esta integração; credenciais nunca são reexibidas. Lê Parâmetro; não grava (o método edit não chama AuditService nem altera registro). Teste: tests/Feature/Gestao/ApiIntegracaoControllerTest.php::test_administrador_ve_as_abas_sem_credencial_em_claro (confere as 8 abas e o client secret do GOV.BR só com a indicação de valor gravado). Processo elementar independente: na visão lógica do usuário (CPM Parte 1 §5.5.2.1) cada integração é um cadastro independente, consultado e mantido por si; a consulta da integração REGIN é completa por si e não altera dados. A carga conjunta das oito abas numa resposta é decisão de interface (as integrações poderiam ser itens de menu separados) e não define o processo elementar. Unicidade (§5.5.2.2): o conjunto de DER desta aba e a lógica de apresentação (campos e credenciais mascaradas próprios da integração) diferem das demais abas, logo é consulta distinta. Classificação: CE, só recupera e apresenta, sem cálculo, derivação ou atualização de ALI (§5.5.3). TD=10 (integração, descrição, usar produção, URL de homologação, URL de produção, usuário, senha (só indica se há valor gravado), CNPJ da Prefeitura, ajuda do campo, ação). AR=1 (Parâmetro). Recontagem 16/10/2026: mantida (linha 472 da contagem de 01/10/2026).
A100: =IF(H100="",IF(C100="",A99,A99+1),A99) | B100: =IF(A100=A99,"",CONCATENATE("F",A100)) | C100: APIs - consultar configuração Inscrição imobiliária | H100: CE | I100: I | J100: 8 | K100: 1 | L100: =CONCATENATE(H100,M100) | M100: =IF(OR(ISBLANK(J100),ISBLANK(K100)),IF(OR(H100="ALI",H100="AIE"),"L",IF(ISBLANK(H100),"","A")),IF(H100="EE",IF(K100>=3,IF(J100>=5,"H","A"),IF(K100>=2,IF(J100>=16,"H",IF(J100<=4,"L","A")),IF(J100<=15,"L","A"))),IF(OR(H100="SE",H100="CE"),IF(K100>=4,IF(J100>=6,"H","A"),IF(K100>=2,IF(J100>=20,"H",IF(J100<=5,"L","A")),IF(J100<=19,"L","A"))),IF(OR(H100="ALI",H100="AIE"),IF(K100>=6,IF(J100>=20,"H","A"),IF(K100>=2,IF(J100>=51,"H",IF(J100<=19,"L","A")),IF(J100<=50,"L","A"))))))) | N100: =IF(M100="L","Baixa",IF(M100="A","Média",IF(M100="","","Alta"))) | O100: =IF(ISBLANK(H100),"",IF(H100="ALI",IF(M100="L",7,IF(M100="A",10,15)),IF(H100="AIE",IF(M100="L",5,IF(M100="A",7,10)),IF(H100="SE",IF(M100="L",4,IF(M100="A",5,7)),IF(OR(H100="EE",H100="CE"),IF(M100="L",3,IF(M100="A",4,6))))))) | P100: =IF(I100="I",O100*Contagem!$W$15,IF(I100="E",O100*Contagem!$W$17,IF(I100="A",O100*Contagem!$W$16,IF(I100="T",O100*Contagem!$W$18,"")))) | Q100: Prova: Rota GET /gestao/config-apis?aba=inscricao (manter-parametros). Tela: gestao/config-apis/index, aba Inscrição imobiliária (menu Configuração > APIs). O gestor abre a configuração da integração e vê os valores em uso, montados por ApiIntegracaoController@edit a partir dos parâmetros listados em ApiIntegracaoCatalog para esta integração; credenciais nunca são reexibidas. Lê Parâmetro; não grava (o método edit não chama AuditService nem altera registro). Teste: tests/Feature/Gestao/ApiIntegracaoControllerTest.php::test_administrador_ve_as_abas_sem_credencial_em_claro (confere as 8 abas e o client secret do GOV.BR só com a indicação de valor gravado). Processo elementar independente: na visão lógica do usuário (CPM Parte 1 §5.5.2.1) cada integração é um cadastro independente, consultado e mantido por si; a consulta da integração Inscrição imobiliária é completa por si e não altera dados. A carga conjunta das oito abas numa resposta é decisão de interface (as integrações poderiam ser itens de menu separados) e não define o processo elementar. Unicidade (§5.5.2.2): o conjunto de DER desta aba e a lógica de apresentação (campos e credenciais mascaradas próprios da integração) diferem das demais abas, logo é consulta distinta. Classificação: CE, só recupera e apresenta, sem cálculo, derivação ou atualização de ALI (§5.5.3). TD=8 (integração, descrição, consulta habilitada, usar produção, URL de homologação, URL de produção, ajuda do campo, ação). AR=1 (Parâmetro). Recontagem 16/10/2026: mantida (linha 474 da contagem de 01/10/2026).
A101: =IF(H101="",IF(C101="",A100,A100+1),A100) | B101: =IF(A101=A100,"",CONCATENATE("F",A101)) | C101: APIs - consultar configuração CPF e CNPJ | H101: CE | I101: I | J101: 8 | K101: 1 | L101: =CONCATENATE(H101,M101) | M101: =IF(OR(ISBLANK(J101),ISBLANK(K101)),IF(OR(H101="ALI",H101="AIE"),"L",IF(ISBLANK(H101),"","A")),IF(H101="EE",IF(K101>=3,IF(J101>=5,"H","A"),IF(K101>=2,IF(J101>=16,"H",IF(J101<=4,"L","A")),IF(J101<=15,"L","A"))),IF(OR(H101="SE",H101="CE"),IF(K101>=4,IF(J101>=6,"H","A"),IF(K101>=2,IF(J101>=20,"H",IF(J101<=5,"L","A")),IF(J101<=19,"L","A"))),IF(OR(H101="ALI",H101="AIE"),IF(K101>=6,IF(J101>=20,"H","A"),IF(K101>=2,IF(J101>=51,"H",IF(J101<=19,"L","A")),IF(J101<=50,"L","A"))))))) | N101: =IF(M101="L","Baixa",IF(M101="A","Média",IF(M101="","","Alta"))) | O101: =IF(ISBLANK(H101),"",IF(H101="ALI",IF(M101="L",7,IF(M101="A",10,15)),IF(H101="AIE",IF(M101="L",5,IF(M101="A",7,10)),IF(H101="SE",IF(M101="L",4,IF(M101="A",5,7)),IF(OR(H101="EE",H101="CE"),IF(M101="L",3,IF(M101="A",4,6))))))) | P101: =IF(I101="I",O101*Contagem!$W$15,IF(I101="E",O101*Contagem!$W$17,IF(I101="A",O101*Contagem!$W$16,IF(I101="T",O101*Contagem!$W$18,"")))) | Q101: Prova: Rota GET /gestao/config-apis?aba=sedur_contato (manter-parametros). Tela: gestao/config-apis/index, aba CPF e CNPJ (menu Configuração > APIs). O gestor abre a configuração da integração e vê os valores em uso, montados por ApiIntegracaoController@edit a partir dos parâmetros listados em ApiIntegracaoCatalog para esta integração; credenciais nunca são reexibidas. Lê Parâmetro; não grava (o método edit não chama AuditService nem altera registro). Teste: tests/Feature/Gestao/ApiIntegracaoControllerTest.php::test_administrador_ve_as_abas_sem_credencial_em_claro (confere as 8 abas e o client secret do GOV.BR só com a indicação de valor gravado). Processo elementar independente: na visão lógica do usuário (CPM Parte 1 §5.5.2.1) cada integração é um cadastro independente, consultado e mantido por si; a consulta da integração CPF e CNPJ é completa por si e não altera dados. A carga conjunta das oito abas numa resposta é decisão de interface (as integrações poderiam ser itens de menu separados) e não define o processo elementar. Unicidade (§5.5.2.2): o conjunto de DER desta aba e a lógica de apresentação (campos e credenciais mascaradas próprios da integração) diferem das demais abas, logo é consulta distinta. Classificação: CE, só recupera e apresenta, sem cálculo, derivação ou atualização de ALI (§5.5.3). TD=8 (integração, descrição, consulta de CNPJ habilitada, usar produção, URL de homologação, URL de produção, ajuda do campo, ação). AR=1 (Parâmetro). Recontagem 16/10/2026: mantida (linha 476 da contagem de 01/10/2026).
A102: =IF(H102="",IF(C102="",A101,A101+1),A101) | B102: =IF(A102=A101,"",CONCATENATE("F",A102)) | C102: APIs - consultar configuração Autenticação SEDUR | H102: CE | I102: I | J102: 8 | K102: 1 | L102: =CONCATENATE(H102,M102) | M102: =IF(OR(ISBLANK(J102),ISBLANK(K102)),IF(OR(H102="ALI",H102="AIE"),"L",IF(ISBLANK(H102),"","A")),IF(H102="EE",IF(K102>=3,IF(J102>=5,"H","A"),IF(K102>=2,IF(J102>=16,"H",IF(J102<=4,"L","A")),IF(J102<=15,"L","A"))),IF(OR(H102="SE",H102="CE"),IF(K102>=4,IF(J102>=6,"H","A"),IF(K102>=2,IF(J102>=20,"H",IF(J102<=5,"L","A")),IF(J102<=19,"L","A"))),IF(OR(H102="ALI",H102="AIE"),IF(K102>=6,IF(J102>=20,"H","A"),IF(K102>=2,IF(J102>=51,"H",IF(J102<=19,"L","A")),IF(J102<=50,"L","A"))))))) | N102: =IF(M102="L","Baixa",IF(M102="A","Média",IF(M102="","","Alta"))) | O102: =IF(ISBLANK(H102),"",IF(H102="ALI",IF(M102="L",7,IF(M102="A",10,15)),IF(H102="AIE",IF(M102="L",5,IF(M102="A",7,10)),IF(H102="SE",IF(M102="L",4,IF(M102="A",5,7)),IF(OR(H102="EE",H102="CE"),IF(M102="L",3,IF(M102="A",4,6))))))) | P102: =IF(I102="I",O102*Contagem!$W$15,IF(I102="E",O102*Contagem!$W$17,IF(I102="A",O102*Contagem!$W$16,IF(I102="T",O102*Contagem!$W$18,"")))) | Q102: Prova: Rota GET /gestao/config-apis?aba=sedur_auth (manter-parametros). Tela: gestao/config-apis/index, aba Autenticação SEDUR (menu Configuração > APIs). O gestor abre a configuração da integração e vê os valores em uso, montados por ApiIntegracaoController@edit a partir dos parâmetros listados em ApiIntegracaoCatalog para esta integração; credenciais nunca são reexibidas. Lê Parâmetro; não grava (o método edit não chama AuditService nem altera registro). Teste: tests/Feature/Gestao/ApiIntegracaoControllerTest.php::test_administrador_ve_as_abas_sem_credencial_em_claro (confere as 8 abas e o client secret do GOV.BR só com a indicação de valor gravado). Processo elementar independente: na visão lógica do usuário (CPM Parte 1 §5.5.2.1) cada integração é um cadastro independente, consultado e mantido por si; a consulta da integração Autenticação SEDUR é completa por si e não altera dados. A carga conjunta das oito abas numa resposta é decisão de interface (as integrações poderiam ser itens de menu separados) e não define o processo elementar. Unicidade (§5.5.2.2): o conjunto de DER desta aba e a lógica de apresentação (campos e credenciais mascaradas próprios da integração) diferem das demais abas, logo é consulta distinta. Classificação: CE, só recupera e apresenta, sem cálculo, derivação ou atualização de ALI (§5.5.3). TD=8 (integração, descrição, login AD habilitado, usar produção, URL de homologação, URL de produção, ajuda do campo, ação). AR=1 (Parâmetro). Recontagem 16/10/2026: mantida (linha 478 da contagem de 01/10/2026).
A103: =IF(H103="",IF(C103="",A102,A102+1),A102) | B103: =IF(A103=A102,"",CONCATENATE("F",A103)) | C103: APIs - consultar configuração GOV.BR | H103: CE | I103: I | J103: 11 | K103: 1 | L103: =CONCATENATE(H103,M103) | M103: =IF(OR(ISBLANK(J103),ISBLANK(K103)),IF(OR(H103="ALI",H103="AIE"),"L",IF(ISBLANK(H103),"","A")),IF(H103="EE",IF(K103>=3,IF(J103>=5,"H","A"),IF(K103>=2,IF(J103>=16,"H",IF(J103<=4,"L","A")),IF(J103<=15,"L","A"))),IF(OR(H103="SE",H103="CE"),IF(K103>=4,IF(J103>=6,"H","A"),IF(K103>=2,IF(J103>=20,"H",IF(J103<=5,"L","A")),IF(J103<=19,"L","A"))),IF(OR(H103="ALI",H103="AIE"),IF(K103>=6,IF(J103>=20,"H","A"),IF(K103>=2,IF(J103>=51,"H",IF(J103<=19,"L","A")),IF(J103<=50,"L","A"))))))) | N103: =IF(M103="L","Baixa",IF(M103="A","Média",IF(M103="","","Alta"))) | O103: =IF(ISBLANK(H103),"",IF(H103="ALI",IF(M103="L",7,IF(M103="A",10,15)),IF(H103="AIE",IF(M103="L",5,IF(M103="A",7,10)),IF(H103="SE",IF(M103="L",4,IF(M103="A",5,7)),IF(OR(H103="EE",H103="CE"),IF(M103="L",3,IF(M103="A",4,6))))))) | P103: =IF(I103="I",O103*Contagem!$W$15,IF(I103="E",O103*Contagem!$W$17,IF(I103="A",O103*Contagem!$W$16,IF(I103="T",O103*Contagem!$W$18,"")))) | Q103: Prova: Rota GET /gestao/config-apis?aba=govbr (manter-parametros). Tela: gestao/config-apis/index, aba GOV.BR (menu Configuração > APIs). O gestor abre a configuração da integração e vê os valores em uso, montados por ApiIntegracaoController@edit a partir dos parâmetros listados em ApiIntegracaoCatalog para esta integração; credenciais nunca são reexibidas. Lê Parâmetro; não grava (o método edit não chama AuditService nem altera registro). Teste: tests/Feature/Gestao/ApiIntegracaoControllerTest.php::test_administrador_ve_as_abas_sem_credencial_em_claro (confere as 8 abas e o client secret do GOV.BR só com a indicação de valor gravado). Processo elementar independente: na visão lógica do usuário (CPM Parte 1 §5.5.2.1) cada integração é um cadastro independente, consultado e mantido por si; a consulta da integração GOV.BR é completa por si e não altera dados. A carga conjunta das oito abas numa resposta é decisão de interface (as integrações poderiam ser itens de menu separados) e não define o processo elementar. Unicidade (§5.5.2.2): o conjunto de DER desta aba e a lógica de apresentação (campos e credenciais mascaradas próprios da integração) diferem das demais abas, logo é consulta distinta. Classificação: CE, só recupera e apresenta, sem cálculo, derivação ou atualização de ALI (§5.5.3). TD=11 (integração, descrição, login GOV.BR habilitado, usar produção, URL de homologação, URL de produção, client ID (só indica se há valor gravado), client secret (só indica se há valor gravado), nível mínimo, ajuda do campo, ação). AR=1 (Parâmetro). Recontagem 16/10/2026: mantida (linha 480 da contagem de 01/10/2026).
A104: =IF(H104="",IF(C104="",A103,A103+1),A103) | B104: =IF(A104=A103,"",CONCATENATE("F",A104)) | C104: APIs - consultar configuração Geocodificação | H104: CE | I104: I | J104: 8 | K104: 1 | L104: =CONCATENATE(H104,M104) | M104: =IF(OR(ISBLANK(J104),ISBLANK(K104)),IF(OR(H104="ALI",H104="AIE"),"L",IF(ISBLANK(H104),"","A")),IF(H104="EE",IF(K104>=3,IF(J104>=5,"H","A"),IF(K104>=2,IF(J104>=16,"H",IF(J104<=4,"L","A")),IF(J104<=15,"L","A"))),IF(OR(H104="SE",H104="CE"),IF(K104>=4,IF(J104>=6,"H","A"),IF(K104>=2,IF(J104>=20,"H",IF(J104<=5,"L","A")),IF(J104<=19,"L","A"))),IF(OR(H104="ALI",H104="AIE"),IF(K104>=6,IF(J104>=20,"H","A"),IF(K104>=2,IF(J104>=51,"H",IF(J104<=19,"L","A")),IF(J104<=50,"L","A"))))))) | N104: =IF(M104="L","Baixa",IF(M104="A","Média",IF(M104="","","Alta"))) | O104: =IF(ISBLANK(H104),"",IF(H104="ALI",IF(M104="L",7,IF(M104="A",10,15)),IF(H104="AIE",IF(M104="L",5,IF(M104="A",7,10)),IF(H104="SE",IF(M104="L",4,IF(M104="A",5,7)),IF(OR(H104="EE",H104="CE"),IF(M104="L",3,IF(M104="A",4,6))))))) | P104: =IF(I104="I",O104*Contagem!$W$15,IF(I104="E",O104*Contagem!$W$17,IF(I104="A",O104*Contagem!$W$16,IF(I104="T",O104*Contagem!$W$18,"")))) | Q104: Prova: Rota GET /gestao/config-apis?aba=geocoding (manter-parametros). Tela: gestao/config-apis/index, aba Geocodificação (menu Configuração > APIs). O gestor abre a configuração da integração e vê os valores em uso, montados por ApiIntegracaoController@edit a partir dos parâmetros listados em ApiIntegracaoCatalog para esta integração; credenciais nunca são reexibidas. Lê Parâmetro; não grava (o método edit não chama AuditService nem altera registro). Teste: tests/Feature/Gestao/ApiIntegracaoControllerTest.php::test_administrador_ve_as_abas_sem_credencial_em_claro (confere as 8 abas e o client secret do GOV.BR só com a indicação de valor gravado). Processo elementar independente: na visão lógica do usuário (CPM Parte 1 §5.5.2.1) cada integração é um cadastro independente, consultado e mantido por si; a consulta da integração Geocodificação é completa por si e não altera dados. A carga conjunta das oito abas numa resposta é decisão de interface (as integrações poderiam ser itens de menu separados) e não define o processo elementar. Unicidade (§5.5.2.2): o conjunto de DER desta aba e a lógica de apresentação (campos e credenciais mascaradas próprios da integração) diferem das demais abas, logo é consulta distinta. Classificação: CE, só recupera e apresenta, sem cálculo, derivação ou atualização de ALI (§5.5.3). TD=8 (integração, descrição, geocodificação habilitada, usar produção, URL de homologação, URL de produção, ajuda do campo, ação). AR=1 (Parâmetro). Recontagem 16/10/2026: mantida (linha 482 da contagem de 01/10/2026).
A105: =IF(H105="",IF(C105="",A104,A104+1),A104) | B105: =IF(A105=A104,"",CONCATENATE("F",A105)) | C105: APIs - consultar configuração GeoServer | H105: CE | I105: I | J105: 11 | K105: 1 | L105: =CONCATENATE(H105,M105) | M105: =IF(OR(ISBLANK(J105),ISBLANK(K105)),IF(OR(H105="ALI",H105="AIE"),"L",IF(ISBLANK(H105),"","A")),IF(H105="EE",IF(K105>=3,IF(J105>=5,"H","A"),IF(K105>=2,IF(J105>=16,"H",IF(J105<=4,"L","A")),IF(J105<=15,"L","A"))),IF(OR(H105="SE",H105="CE"),IF(K105>=4,IF(J105>=6,"H","A"),IF(K105>=2,IF(J105>=20,"H",IF(J105<=5,"L","A")),IF(J105<=19,"L","A"))),IF(OR(H105="ALI",H105="AIE"),IF(K105>=6,IF(J105>=20,"H","A"),IF(K105>=2,IF(J105>=51,"H",IF(J105<=19,"L","A")),IF(J105<=50,"L","A"))))))) | N105: =IF(M105="L","Baixa",IF(M105="A","Média",IF(M105="","","Alta"))) | O105: =IF(ISBLANK(H105),"",IF(H105="ALI",IF(M105="L",7,IF(M105="A",10,15)),IF(H105="AIE",IF(M105="L",5,IF(M105="A",7,10)),IF(H105="SE",IF(M105="L",4,IF(M105="A",5,7)),IF(OR(H105="EE",H105="CE"),IF(M105="L",3,IF(M105="A",4,6))))))) | P105: =IF(I105="I",O105*Contagem!$W$15,IF(I105="E",O105*Contagem!$W$17,IF(I105="A",O105*Contagem!$W$16,IF(I105="T",O105*Contagem!$W$18,"")))) | Q105: Prova: Rota GET /gestao/config-apis?aba=geoserver (manter-parametros). Tela: gestao/config-apis/index, aba GeoServer (menu Configuração > APIs). O gestor abre a configuração da integração e vê os valores em uso, montados por ApiIntegracaoController@edit a partir dos parâmetros listados em ApiIntegracaoCatalog para esta integração; credenciais nunca são reexibidas. Lê Parâmetro; não grava (o método edit não chama AuditService nem altera registro). Teste: tests/Feature/Gestao/ApiIntegracaoControllerTest.php::test_administrador_ve_as_abas_sem_credencial_em_claro (confere as 8 abas e o client secret do GOV.BR só com a indicação de valor gravado). Processo elementar independente: na visão lógica do usuário (CPM Parte 1 §5.5.2.1) cada integração é um cadastro independente, consultado e mantido por si; a consulta da integração GeoServer é completa por si e não altera dados. A carga conjunta das oito abas numa resposta é decisão de interface (as integrações poderiam ser itens de menu separados) e não define o processo elementar. Unicidade (§5.5.2.2): o conjunto de DER desta aba e a lógica de apresentação (campos e credenciais mascaradas próprios da integração) diferem das demais abas, logo é consulta distinta. Classificação: CE, só recupera e apresenta, sem cálculo, derivação ou atualização de ALI (§5.5.3). TD=11 (integração, descrição, consulta de zona habilitada, regras territoriais habilitadas, classificação viária habilitada, polígono do endereçamento habilitado, usar produção, URL de homologação, URL de produção, ajuda do campo, ação). AR=1 (Parâmetro). Recontagem 16/10/2026: alterada (linha 484 da contagem de 01/10/2026: "APIs - consultar configuração GeoServer", CE Baixa 3 PF, TD 10, AR 1). Motivo: TD 10 para 11: a aba passou a exibir o interruptor "Polígono do endereçamento habilitado" (features.geoserver_enderecamento, commit f8abe514 de 02/10/2026). PF inalterado (Baixa).
...

Sheet Sumário
C1: Sudoeste Informática
C2: Sudoeste Informática e Consultoria
C3: Missão: "Ser a mais completa solução na área de Tecnologia da Informação, de forma a contribuir para a modernização da Gestão pública."
A4: Sumário da Contagem
A7: =Contagem!A8&" : "&Contagem!F8 | F7: =Contagem!A9&" : "&Contagem!F9
A8: DV Número: | C8: =Contagem!F10 | D8: Versão: | F8: =Contagem!N10
A9: =Contagem!A11&" : "&Contagem!F11 | F9: =Contagem!A12&" : "&Contagem!F12
A10: =Contagem!A7&" : "&Contagem!F7 | F10: =Contagem!R7&" = "&VALUE(Contagem!T7) | H10: =" Custo= "&DOLLAR(Contagem!Y7) | K10: ="PF = "&VALUE(Contagem!Y8)
A11: Tipo de Função | C11: Complexidade Funcional | G11: Total por Complexidade | I11: %
B14: EE | C14: =COUNTIF(CF,"EEL") | E14: Baixa | F14: x 3 | G14: =C14*3
C15: =COUNTIF(CF,"EEA") | E15: Média | F15: x 4 | G15: =C15*4
C16: =COUNTIF(CF,"EEH") | E16: Alta | F16: x 6 | G16: =C16*6
B18: Total | C18: =SUM(C14:C16) | F18: Total | G18: =SUM(G14:G16) | I18: =IF($G$49<>0,G18/$G$49,"")
B21: SE | C21: =COUNTIF(CF,"SEL") | E21: Baixa | F21: x 4 | G21: =C21*4
C22: =COUNTIF(CF,"SEA") | E22: Média | F22: x 5 | G22: =C22*5
C23: =COUNTIF(CF,"SEH") | E23: Alta | F23: x 7 | G23: =C23*7
B25: Total | C25: =SUM(C21:C23) | F25: Total | G25: =SUM(G21:G23) | I25: =IF($G$49<>0,G25/$G$49,"")
B28: CE | C28: =COUNTIF(CF,"CEL") | E28: Baixa | F28: x 3 | G28: =C28*3
C29: =COUNTIF(CF,"CEA") | E29: Média | F29: x 4 | G29: =C29*4
C30: =COUNTIF(CF,"CEH") | E30: Alta | F30: x 6 | G30: =C30*6
B32: Total | C32: =SUM(C28:C30) | F32: Total | G32: =SUM(G28:G30) | I32: =IF($G$49<>0,G32/$G$49,"")
B35: ALI | C35: =COUNTIF(CF,"ALIL") | E35: Baixa | F35: x 7 | G35: =C35*7
C36: =COUNTIF(CF,"ALIA") | E36: Média | F36: x 10 | G36: =C36*10
C37: =COUNTIF(CF,"ALIH") | E37: Alta | F37: x 15 | G37: =C37*15
B39: Total | C39: =SUM(C35:C37) | F39: Total | G39: =SUM(G35:G37) | I39: =IF($G$49<>0,G39/$G$49,"")
B42: AIE | C42: =COUNTIF(CF,"AIEL") | E42: Baixa | F42: x 5 | G42: =C42*5
C43: =COUNTIF(CF,"AIEA") | E43: Média | F43: x 7 | G43: =C43*7
C44: =COUNTIF(CF,"AIEH") | E44: Alta | F44: x 10 | G44: =C44*10
B46: Total | C46: =SUM(C42:C44) | F46: Total | G46: =SUM(G42:G44) | I46: =IF($G$49<>0,G46/$G$49,"")
B49: Total PF não ajustados (contagem detalhada) | G49: =SUM(G18+G25+G32+G39+G46)
B50: Total PF não ajustados (contagem estimativa) | G50: =(C14+C15+C16)*4+(C21+C22+C23)*5+(C28+C29+C30)*4+(C35+C36+C37)*7+(C42+C43+C44)*5
B51: Total PF não ajustados (contagem indicativa) | G51: =(C35+C36+C37)*35+(C42+C43+C44)*15
B55: Total de PF Local
E56: NÃO AJS | F56: DFL | G56: LOCAL
B57: INCLUSÃO (ADD) | E57: =SUMIF(Funções!$I$12:$I$1000,"I",Funções!$O$12:$O$1000) | F57: =Contagem!W15 | G57: =F57*E57
B58: ALTERAÇÃO (CHG) | E58: =SUMIF(Funções!$I$12:$I$1000,"A",Funções!$O$12:$O$1000) | F58: =Contagem!W16 | G58: =F58*E58 | K58: TOTAL
B59: EXCLUSÃO (DEL) | E59: =SUMIF(Funções!$I$12:$I$1000,"E",Funções!$O$12:$O$1000) | F59: =Contagem!W17 | G59: =F59*E59 | K59: =Contagem!Y8
B60: CONSULTA | E60: =SUMIF(Funções!$I$12:$I$1000,"C",Funções!$O$12:$O$1000) | F60: =Contagem!W18 | G60: =F60*E60
